[
  {
    "index": 0,
    "text": "朝、いつもと同じ時間に家を出たのに、信号が全部青だった。",
    "raw_text": "朝、いつもと同じ時間に家を出たのに、信号が全部青だった。",
    "b_text": "朝、いつもと同じ時間に家を出たのに、信号が全部青だった。"
  },
  {
    "index": 1,
    "text": "普段は混む電車が空いていて、座れた。",
    "raw_text": "普段は混む電車が空いていて、座れた。",
    "b_text": "普段は混む電車が空いていて、座れた。"
  },
  {
    "index": 2,
    "text": "たまたま隣に座った人の落とした名刺が、後で仕事につながった。",
    "raw_text": "たまたま隣に座った人の落とした名刺が、後で仕事につながった。",
    "b_text": "たまたま隣に座った人の落とした名刺が、後で仕事につながった。"
  },
  {
    "index": 3,
    "text": "そんな偶然が重なると、自分の力が強くなった気がします。",
    "raw_text": "そんな偶然が重なると、自分の力が強くなった気がします。",
    "b_text": "そんな偶然が重なると、自分の力が強くなった気がします。"
  },
  {
    "index": 4,
    "text": "逆に、努力しても報われず、たまたまの一言で計画が崩れると、運の残酷さを思い知らされます。",
    "raw_text": "逆に、努力しても報われず、たまたまの一言で計画が崩れると、運の残酷さを思い知らされます。",
    "b_text": "逆に、努力しても報われず、たまたまの一言で計画が崩れると、運の残酷さを思い知らされます。"
  },
  {
    "index": 5,
    "text": "運は味方にも敵にもなる。",
    "raw_text": "運は味方にも敵にもなる。",
    "b_text": "運は味方にも敵にもなる。"
  },
  {
    "index": 6,
    "text": "今日は、この見えない力との付き合い方を、わかりやすくほどきます。",
    "raw_text": "今日は、この見えない力との付き合い方を、わかりやすくほどきます。",
    "b_text": "今日は、この見えない力との付き合い方を、わかりやすくほどきます。"
  },
  {
    "index": 7,
    "text": "運は気まぐれに見えますが、私たちが運に意味を与えることで揺れが大きくなります。",
    "raw_text": "運は気まぐれに見えますが、私たちが運に意味を与えることで揺れが大きくなります。",
    "b_text": "運は気まぐれに見えますが、私たちが運に意味を与えることで揺れが大きくなります。"
  },
  {
    "index": 8,
    "text": "コイントスは五回連続で表が出ることもあります。",
    "raw_text": "コイントスは五回連続で表が出ることもあります。",
    "b_text": "コイントスは五回連続で表が出ることもあります。"
  },
  {
    "index": 9,
    "text": "確率が偏っているわけではなく、偶然が続くことも普通に起こる。",
    "raw_text": "確率が偏っているわけではなく、偶然が続くことも普通に起こる。",
    "b_text": "確率が偏っているわけではなく、偶然が続くことも普通に起こる。"
  },
  {
    "index": 10,
    "text": "それなのに「次こそ裏が出るはずだ」と思い込む。",
    "raw_text": "それなのに「次こそ裏が出るはずだ」と思い込む。",
    "b_text": "それなのに「次こそ裏が出るはずだ」と思い込む。"
  },
  {
    "index": 11,
    "text": "これがギャンブラーの誤謬です。",
    "raw_text": "これがギャンブラーの誤謬です。",
    "b_text": "これがギャンブラーの誤謬です。"
  },
  {
    "index": 12,
    "text": "運をコントロールできる錯覚が、余計な期待と落胆を生みます。",
    "raw_text": "運をコントロールできる錯覚が、余計な期待と落胆を生みます。",
    "b_text": "運をコントロールできる錯覚が、余計な期待と落胆を生みます。"
  },
  {
    "index": 13,
    "text": "成功者の話を聞くと、「毎日早起きした」「とにかく行動した」などの習慣が並びます。",
    "raw_text": "成功者の話を聞くと、「毎日早起きした」「とにかく行動した」などの習慣が並びます。",
    "b_text": "成功者の話を聞くと、「毎日早起きした」「とにかく行動した」などの習慣が並びます。"
  },
  {
    "index": 14,
    "text": "大切なこともありますが、その人が成功した背景には時代や環境、出会いといった偶然が必ず混ざっています。",
    "raw_text": "大切なこともありますが、その人が成功した背景には時代や環境、出会いといった偶然が必ず混ざっています。",
    "b_text": "大切なこともありますが、その人が成功した背景には時代や環境、出会いといった偶然が必ず混ざっています。"
  },
  {
    "index": 15,
    "text": "生存者バイアスが抜け落ちると、「自分も同じようにやれば必ず成功するはずだ」という危険な確信が生まれます。",
    "raw_text": "生存者バイアスが抜け落ちると、「自分も同じようにやれば必ず成功するはずだ」という危険な確信が生まれます。",
    "b_text": "生存者バイアスが抜け落ちると、「自分も同じようにやれば必ず成功するはずだ」という危険な確信が生まれます。"
  },
  {
    "index": 16,
    "text": "偶然の成分を見落としたまま突き進むと、運が外れたときに立てなくなります。",
    "raw_text": "偶然の成分を見落としたまま突き進むと、運が外れたときに立てなくなります。",
    "b_text": "偶然の成分を見落としたまま突き進むと、運が外れたときに立てなくなります。"
  },
  {
    "index": 17,
    "text": "逆に、運の悪さだけを拾い集める人もいます。",
    "raw_text": "逆に、運の悪さだけを拾い集める人もいます。",
    "b_text": "逆に、運の悪さだけを拾い集める人もいます。"
  },
  {
    "index": 18,
    "text": "「自分だけ不公平だ」「あの人は運が良いだけだ」と思い込むと、偶然の中にある自分の行動の余地を見逃します。",
    "raw_text": "「自分だけ不公平だ」「あの人は運が良いだけだ」と思い込むと、偶然の中にある自分の行動の余地を見逃します。",
    "b_text": "「自分だけ不公平だ」「あの人は運が良いだけだ」と思い込むと、偶然の中にある自分の行動の余地を見逃します。"
  },
  {
    "index": 19,
    "text": "運任せにして動きを止めれば、偶然の機会も拾えません。",
    "raw_text": "運任せにして動きを止めれば、偶然の機会も拾えません。",
    "b_text": "運任せにして動きを止めれば、偶然の機会も拾えません。"
  },
  {
    "index": 20,
    "text": "運と行動は切り離せません。",
    "raw_text": "運と行動は切り離せません。",
    "b_text": "運と行動は切り離せません。"
  },
  {
    "index": 21,
    "text": "偶然の波は勝手に来ますが、乗るかどうかは自分で決められます。",
    "raw_text": "偶然の波は勝手に来ますが、乗るかどうかは自分で決められます。",
    "b_text": "偶然の波は勝手に来ますが、乗るかどうかは自分で決められます。"
  },
  {
    "index": 22,
    "text": "私たちは物語が好きです。",
    "raw_text": "私たちは物語が好きです。",
    "b_text": "私たちは物語が好きです。"
  },
  {
    "index": 23,
    "text": "偶然を語るときも、無意識に物語にします。",
    "raw_text": "偶然を語るときも、無意識に物語にします。",
    "b_text": "偶然を語るときも、無意識に物語にします。"
  },
  {
    "index": 24,
    "text": "子どもの頃に出会った一冊の本が人生を変えた。",
    "raw_text": "子どもの頃に出会った一冊の本が人生を変えた。",
    "b_text": "子どもの頃に出会った一冊の本が人生を変えた。"
  },
  {
    "index": 25,
    "text": "偶然の出会いから結婚した。",
    "raw_text": "偶然の出会いから結婚した。",
    "b_text": "偶然の出会いから結婚した。"
  },
  {
    "index": 26,
    "text": "物語として語ると、運が一つの意味を持ってしまいます。",
    "raw_text": "物語として語ると、運が一つの意味を持ってしまいます。",
    "b_text": "物語として語ると、運が一つの意味を持ってしまいます。"
  },
  {
    "index": 27,
    "text": "意味を持たせるのは悪いことではありませんが、「意味があったはず」と考えすぎると、偶然に絡み取られます。",
    "raw_text": "意味を持たせるのは悪いことではありませんが、「意味があったはず」と考えすぎると、偶然に絡み取られます。",
    "b_text": "意味を持たせるのは悪いことではありませんが、「意味があったはず」と考えすぎると、偶然に絡み取られます。"
  },
  {
    "index": 28,
    "text": "偶然に意味を全部乗せず、事実として置いておく余白を残すと、心が軽くなります。",
    "raw_text": "偶然に意味を全部乗せず、事実として置いておく余白を残すと、心が軽くなります。",
    "b_text": "偶然に意味を全部乗せず、事実として置いておく余白を残すと、心が軽くなります。"
  },
  {
    "index": 29,
    "text": "哲学者は、運とどのように向き合ってきたのでしょうか。",
    "raw_text": "哲学者は、運とどのように向き合ってきたのでしょうか。",
    "b_text": "哲学者は、運とどのように向き合ってきたのでしょうか。"
  },
  {
    "index": 30,
    "text": "古代のストア派は、運を「自分で動かせないもの」と切り分けました。",
    "raw_text": "古代のストア派は、運を「自分で動かせないもの」と切り分けました。",
    "b_text": "古代のストア派は、運を「自分で動かせないもの」と切り分けました。"
  },
  {
    "index": 31,
    "text": "自分で動かせないものに心を奪われず、自分で動かせるものに集中する。",
    "raw_text": "自分で動かせないものに心を奪われず、自分で動かせるものに集中する。",
    "b_text": "自分で動かせないものに心を奪われず、自分で動かせるものに集中する。"
  },
  {
    "index": 32,
    "text": "それは冷たさではなく、運に振り回されないための優しさです。",
    "raw_text": "それは冷たさではなく、運に振り回されないための優しさです。",
    "b_text": "それは冷たさではなく、運に振り回されないための優しさです。"
  },
  {
    "index": 33,
    "text": "禅でも「なるべくしてなる」と捉え、結果に固執しない態度を育てます。",
    "raw_text": "禅でも「なるべくしてなる」と捉え、結果に固執しない態度を育てます。",
    "b_text": "禅でも「なるべくしてなる」と捉え、結果に固執しない態度を育てます。"
  },
  {
    "index": 34,
    "text": "結果に固執しないからこそ、偶然の風が吹いたときに軽く動けます。",
    "raw_text": "結果に固執しないからこそ、偶然の風が吹いたときに軽く動けます。",
    "b_text": "結果に固執しないからこそ、偶然の風が吹いたときに軽く動けます。"
  },
  {
    "index": 35,
    "text": "心理学では制御の所在という概念があります。",
    "raw_text": "心理学では制御の所在という概念があります。",
    "b_text": "心理学では制御の所在という概念があります。"
  },
  {
    "index": 36,
    "text": "自分の人生は自分が操っていると思う人と、外的な力に左右されていると思う人で、行動や幸福感が変わります。",
    "raw_text": "自分の人生は自分が操っていると思う人と、外的な力に左右されていると思う人で、行動や幸福感が変わります。",
    "b_text": "自分の人生は自分が操っていると思う人と、外的な力に左右されていると思う人で、行動や幸福感が変わります。"
  },
  {
    "index": 37,
    "text": "全部を自分で操れると思うと、運に裏切られたときに折れます。",
    "raw_text": "全部を自分で操れると思うと、運に裏切られたときに折れます。",
    "b_text": "全部を自分で操れると思うと、運に裏切られたときに折れます。"
  },
  {
    "index": 38,
    "text": "全部を外に委ねると、何も動けず萎れます。",
    "raw_text": "全部を外に委ねると、何も動けず萎れます。",
    "b_text": "全部を外に委ねると、何も動けず萎れます。"
  },
  {
    "index": 39,
    "text": "現実は、その間にあります。",
    "raw_text": "現実は、その間にあります。",
    "b_text": "現実は、その間にあります。"
  },
  {
    "index": 40,
    "text": "操れない部分を認めつつ、動ける部分に責任を持つ。",
    "raw_text": "操れない部分を認めつつ、動ける部分に責任を持つ。",
    "b_text": "操れない部分を認めつつ、動ける部分に責任を持つ。"
  },
  {
    "index": 41,
    "text": "この中間に立つ感覚が、運との健全な距離です。",
    "raw_text": "この中間に立つ感覚が、運との健全な距離です。",
    "b_text": "この中間に立つ感覚が、運との健全な距離です。"
  },
  {
    "index": 42,
    "text": "運を味方にするためにおまじないを使う人もいます。",
    "raw_text": "運を味方にするためにおまじないを使う人もいます。",
    "b_text": "運を味方にするためにおまじないを使う人もいます。"
  },
  {
    "index": 43,
    "text": "お気に入りのペン、勝負服、神社への参拝。",
    "raw_text": "お気に入りのペン、勝負服、神社への参拝。",
    "b_text": "お気に入りのペン、勝負服、神社への参拝。"
  },
  {
    "index": 44,
    "text": "科学的には力がなくても、心を整える効果があります。",
    "raw_text": "科学的には力がなくても、心を整える効果があります。",
    "b_text": "科学的には力がなくても、心を整える効果があります。"
  },
  {
    "index": 45,
    "text": "緊張が下がれば本来の力が出せます。",
    "raw_text": "緊張が下がれば本来の力が出せます。",
    "b_text": "緊張が下がれば本来の力が出せます。"
  },
  {
    "index": 46,
    "text": "大切なのは、おまじないが「準備のきっかけ」であって、結果の保証ではないと理解することです。",
    "raw_text": "大切なのは、おまじないが「準備のきっかけ」であって、結果の保証ではないと理解することです。",
    "b_text": "大切なのは、おまじないが「準備のきっかけ」であって、結果の保証ではないと理解することです。"
  },
  {
    "index": 47,
    "text": "保証と勘違いすると、外れたときに信じるものがなくなります。",
    "raw_text": "保証と勘違いすると、外れたときに信じるものがなくなります。",
    "b_text": "保証と勘違いすると、外れたときに信じるものがなくなります。"
  },
  {
    "index": 48,
    "text": "偶然の連鎖に振り回されないための簡単な方法があります。",
    "raw_text": "偶然の連鎖に振り回されないための簡単な方法があります。",
    "b_text": "偶然の連鎖に振り回されないための簡単な方法があります。"
  },
  {
    "index": 49,
    "text": "できるだけ複数の選択肢を持っておくことです。",
    "raw_text": "できるだけ複数の選択肢を持っておくことです。",
    "b_text": "できるだけ複数の選択肢を持っておくことです。"
  },
  {
    "index": 50,
    "text": "一つの道しかないと、運の揺れが直撃します。",
    "raw_text": "一つの道しかないと、運の揺れが直撃します。",
    "b_text": "一つの道しかないと、運の揺れが直撃します。"
  },
  {
    "index": 51,
    "text": "複数の道があれば、どれかで風に乗れます。",
    "raw_text": "複数の道があれば、どれかで風に乗れます。",
    "b_text": "複数の道があれば、どれかで風に乗れます。"
  },
  {
    "index": 52,
    "text": "人とのつながりも同じです。",
    "raw_text": "人とのつながりも同じです。",
    "b_text": "人とのつながりも同じです。"
  },
  {
    "index": 53,
    "text": "少数の関係に全てを預けると、その偶然に左右されます。",
    "raw_text": "少数の関係に全てを預けると、その偶然に左右されます。",
    "b_text": "少数の関係に全てを預けると、その偶然に左右されます。"
  },
  {
    "index": 54,
    "text": "複数の小さなつながりがあると、偶然の機会が増え、どこかで拾えます。",
    "raw_text": "複数の小さなつながりがあると、偶然の機会が増え、どこかで拾えます。",
    "b_text": "複数の小さなつながりがあると、偶然の機会が増え、どこかで拾えます。"
  },
  {
    "index": 55,
    "text": "数字に頼りすぎるのも危ういです。",
    "raw_text": "数字に頼りすぎるのも危ういです。",
    "b_text": "数字に頼りすぎるのも危ういです。"
  },
  {
    "index": 56,
    "text": "試験の合格率、売上予測、勝率。",
    "raw_text": "試験の合格率、売上予測、勝率。",
    "b_text": "試験の合格率、売上予測、勝率。"
  },
  {
    "index": 57,
    "text": "数字は目安ですが、偶然は数字の裏で揺れます。",
    "raw_text": "数字は目安ですが、偶然は数字の裏で揺れます。",
    "b_text": "数字は目安ですが、偶然は数字の裏で揺れます。"
  },
  {
    "index": 58,
    "text": "合格率が低くても受かる人はいるし、高くても落ちる人がいます。",
    "raw_text": "合格率が低くても受かる人はいるし、高くても落ちる人がいます。",
    "b_text": "合格率が低くても受かる人はいるし、高くても落ちる人がいます。"
  },
  {
    "index": 59,
    "text": "数字を見て計画を立てつつ、数字は揺れると覚えておく。",
    "raw_text": "数字を見て計画を立てつつ、数字は揺れると覚えておく。",
    "b_text": "数字を見て計画を立てつつ、数字は揺れると覚えておく。"
  },
  {
    "index": 60,
    "text": "揺れを前提にすると、外れたときに自分を責めすぎず、修正に移れます。",
    "raw_text": "揺れを前提にすると、外れたときに自分を責めすぎず、修正に移れます。",
    "b_text": "揺れを前提にすると、外れたときに自分を責めすぎず、修正に移れます。"
  },
  {
    "index": 61,
    "text": "ときには、運の悪さに耐えるしかない場面があります。",
    "raw_text": "ときには、運の悪さに耐えるしかない場面があります。",
    "b_text": "ときには、運の悪さに耐えるしかない場面があります。"
  },
  {
    "index": 62,
    "text": "病気、事故、災害。",
    "raw_text": "病気、事故、災害。",
    "b_text": "病気、事故、災害。"
  },
  {
    "index": 63,
    "text": "どれだけ準備しても避けられないことがあります。",
    "raw_text": "どれだけ準備しても避けられないことがあります。",
    "b_text": "どれだけ準備しても避けられないことがあります。"
  },
  {
    "index": 64,
    "text": "そこで大事なのは、比べないことです。",
    "raw_text": "そこで大事なのは、比べないことです。",
    "b_text": "そこで大事なのは、比べないことです。"
  },
  {
    "index": 65,
    "text": "「自分だけが不幸だ」と思うと苦しさが増えます。",
    "raw_text": "「自分だけが不幸だ」と思うと苦しさが増えます。",
    "b_text": "「自分だけが不幸だ」と思うと苦しさが増えます。"
  },
  {
    "index": 66,
    "text": "「世界には理不尽がある」と認めると、少し動けます。",
    "raw_text": "「世界には理不尽がある」と認めると、少し動けます。",
    "b_text": "「世界には理不尽がある」と認めると、少し動けます。"
  },
  {
    "index": 67,
    "text": "認めることは諦めではなく、次に何をするかを決めるための土台です。",
    "raw_text": "認めることは諦めではなく、次に何をするかを決めるための土台です。",
    "b_text": "認めることは諦めではなく、次に何をするかを決めるための土台です。"
  },
  {
    "index": 68,
    "text": "偶然を味方にする小さな習慣を持つと、運の波に乗りやすくなります。",
    "raw_text": "偶然を味方にする小さな習慣を持つと、運の波に乗りやすくなります。",
    "b_text": "偶然を味方にする小さな習慣を持つと、運の波に乗りやすくなります。"
  },
  {
    "index": 69,
    "text": "いつもと違う道を歩く、知らない店に入る、初めて会う人と三分だけ話す。",
    "raw_text": "いつもと違う道を歩く、知らない店に入る、初めて会う人と三分だけ話す。",
    "b_text": "いつもと違う道を歩く、知らない店に入る、初めて会う人と三分だけ話す。"
  },
  {
    "index": 70,
    "text": "小さな揺らぎを入れると、偶然が入り込む隙が生まれます。",
    "raw_text": "小さな揺らぎを入れると、偶然が入り込む隙が生まれます。",
    "b_text": "小さな揺らぎを入れると、偶然が入り込む隙が生まれます。"
  },
  {
    "index": 71,
    "text": "隙があると、思わぬ情報が手に入り、出会いが生まれます。",
    "raw_text": "隙があると、思わぬ情報が手に入り、出会いが生まれます。",
    "b_text": "隙があると、思わぬ情報が手に入り、出会いが生まれます。"
  },
  {
    "index": 72,
    "text": "大きな賭けではなく、小さなずらしが、運の入り口です。",
    "raw_text": "大きな賭けではなく、小さなずらしが、運の入り口です。",
    "b_text": "大きな賭けではなく、小さなずらしが、運の入り口です。"
  },
  {
    "index": 73,
    "text": "逆に、偶然に飲まれすぎないための習慣も必要です。",
    "raw_text": "逆に、偶然に飲まれすぎないための習慣も必要です。",
    "b_text": "逆に、偶然に飲まれすぎないための習慣も必要です。"
  },
  {
    "index": 74,
    "text": "寝る前にニュースを無限に見るのをやめる、SNSのおすすめを全部追わない。",
    "raw_text": "寝る前にニュースを無限に見るのをやめる、SNSのおすすめを全部追わない。",
    "b_text": "寝る前にニュースを無限に見るのをやめる、ＳＮＳのおすすめを全部追わない。"
  },
  {
    "index": 75,
    "text": "偶然の刺激は中毒性があります。",
    "raw_text": "偶然の刺激は中毒性があります。",
    "b_text": "偶然の刺激は中毒性があります。"
  },
  {
    "index": 76,
    "text": "刺激を減らすと、自分の行動の余地が見えます。",
    "raw_text": "刺激を減らすと、自分の行動の余地が見えます。",
    "b_text": "刺激を減らすと、自分の行動の余地が見えます。"
  },
  {
    "index": 77,
    "text": "余地が見えると、運と自分の境界がわかります。",
    "raw_text": "余地が見えると、運と自分の境界がわかります。",
    "b_text": "余地が見えると、運と自分の境界がわかります。"
  },
  {
    "index": 78,
    "text": "境界がわかれば、疲れにくくなります。",
    "raw_text": "境界がわかれば、疲れにくくなります。",
    "b_text": "境界がわかれば、疲れにくくなります。"
  },
  {
    "index": 79,
    "text": "運に敏感な人ほど、罪悪感を持ちがちです。",
    "raw_text": "運に敏感な人ほど、罪悪感を持ちがちです。",
    "b_text": "運に敏感な人ほど、罪悪感を持ちがちです。"
  },
  {
    "index": 80,
    "text": "「自分だけ幸運で申し訳ない」「運が悪いのは自分のせいだ」と抱え込む。",
    "raw_text": "「自分だけ幸運で申し訳ない」「運が悪いのは自分のせいだ」と抱え込む。",
    "b_text": "「自分だけ幸運で申し訳ない」「運が悪いのは自分のせいだ」と抱え込む。"
  },
  {
    "index": 81,
    "text": "幸運は配分されているわけではありません。",
    "raw_text": "幸運は配分されているわけではありません。",
    "b_text": "幸運は配分されているわけではありません。"
  },
  {
    "index": 82,
    "text": "誰かが幸運だからといって、あなたの幸運が減るわけではない。",
    "raw_text": "誰かが幸運だからといって、あなたの幸運が減るわけではない。",
    "b_text": "誰かが幸運だからといって、あなたの幸運が減るわけではない。"
  },
  {
    "index": 83,
    "text": "運の悪さも、あなたの人間性の証明ではありません。",
    "raw_text": "運の悪さも、あなたの人間性の証明ではありません。",
    "b_text": "運の悪さも、あなたの人間性の証明ではありません。"
  },
  {
    "index": 84,
    "text": "運は性格ではなく環境の揺れです。",
    "raw_text": "運は性格ではなく環境の揺れです。",
    "b_text": "運は性格ではなく環境の揺れです。"
  },
  {
    "index": 85,
    "text": "罪悪感を外すと、次の行動を選びやすくなります。",
    "raw_text": "罪悪感を外すと、次の行動を選びやすくなります。",
    "b_text": "罪悪感を外すと、次の行動を選びやすくなります。"
  },
  {
    "index": 86,
    "text": "運がないと感じるとき、自分を責めるより、試行回数を増やす方が効きます。",
    "raw_text": "運がないと感じるとき、自分を責めるより、試行回数を増やす方が効きます。",
    "b_text": "運がないと感じるとき、自分を責めるより、試行回数を増やす方が効きます。"
  },
  {
    "index": 87,
    "text": "応募を一件から十件に増やす。",
    "raw_text": "応募を一件から十件に増やす。",
    "b_text": "応募を一件から十件に増やす。"
  },
  {
    "index": 88,
    "text": "人に声をかける回数を増やす。",
    "raw_text": "人に声をかける回数を増やす。",
    "b_text": "人に声をかける回数を増やす。"
  },
  {
    "index": 89,
    "text": "回数を増やすと、偶然に当たる確率が上がります。",
    "raw_text": "回数を増やすと、偶然に当たる確率が上がります。",
    "b_text": "回数を増やすと、偶然に当たる確率が上がります。"
  },
  {
    "index": 90,
    "text": "運がないのではなく、まだ当たっていないだけかもしれません。",
    "raw_text": "運がないのではなく、まだ当たっていないだけかもしれません。",
    "b_text": "運がないのではなく、まだ当たっていないだけかもしれません。"
  },
  {
    "index": 91,
    "text": "試行回数を増やすのは、運に頼ることではなく、運を呼び込む行動です。",
    "raw_text": "試行回数を増やすのは、運に頼ることではなく、運を呼び込む行動です。",
    "b_text": "試行回数を増やすのは、運に頼ることではなく、運を呼び込む行動です。"
  },
  {
    "index": 92,
    "text": "ただし、回数を増やしても疲れます。",
    "raw_text": "ただし、回数を増やしても疲れます。",
    "b_text": "ただし、回数を増やしても疲れます。"
  },
  {
    "index": 93,
    "text": "疲れたら止まる。",
    "raw_text": "疲れたら止まる。",
    "b_text": "疲れたら止まる。"
  },
  {
    "index": 94,
    "text": "止まると波が見えます。",
    "raw_text": "止まると波が見えます。",
    "b_text": "止まると波が見えます。"
  },
  {
    "index": 95,
    "text": "波が見えれば、乗るタイミングもずらせます。",
    "raw_text": "波が見えれば、乗るタイミングもずらせます。",
    "b_text": "波が見えれば、乗るタイミングもずらせます。"
  },
  {
    "index": 96,
    "text": "止まることも行動です。",
    "raw_text": "止まることも行動です。",
    "b_text": "止まることも行動です。"
  },
  {
    "index": 97,
    "text": "止まる勇気が、運の波に飲まれずに済む防波堤になります。",
    "raw_text": "止まる勇気が、運の波に飲まれずに済む防波堤になります。",
    "b_text": "止まる勇気が、運の波に飲まれずに済む防波堤になります。"
  },
  {
    "index": 98,
    "text": "偶然を振り返るときには、「自分が選んだもの」と「勝手に起きたもの」を分けてみます。",
    "raw_text": "偶然を振り返るときには、「自分が選んだもの」と「勝手に起きたもの」を分けてみます。",
    "b_text": "偶然を振り返るときには、「自分が選んだもの」と「勝手に起きたもの」を分けてみます。"
  },
  {
    "index": 99,
    "text": "選んだものは次に活かせます。",
    "raw_text": "選んだものは次に活かせます。",
    "b_text": "選んだものは次に活かせます。"
  },
  {
    "index": 100,
    "text": "勝手に起きたものは、受け止め方を学べます。",
    "raw_text": "勝手に起きたものは、受け止め方を学べます。",
    "b_text": "勝手に起きたものは、受け止め方を学べます。"
  },
  {
    "index": 101,
    "text": "分けるだけで、混ざった感情が少し整います。",
    "raw_text": "分けるだけで、混ざった感情が少し整います。",
    "b_text": "分けるだけで、混ざった感情が少し整います。"
  },
  {
    "index": 102,
    "text": "運が良かったときは、誰かと分けるのも一つです。",
    "raw_text": "運が良かったときは、誰かと分けるのも一つです。",
    "b_text": "運が良かったときは、誰かと分けるのも一つです。"
  },
  {
    "index": 103,
    "text": "手に入った情報を共有する、感謝を伝える、寄付をする。",
    "raw_text": "手に入った情報を共有する、感謝を伝える、寄付をする。",
    "b_text": "手に入った情報を共有する、感謝を伝える、寄付をする。"
  },
  {
    "index": 104,
    "text": "分けることで、自分が偶然の産物を独占していない感覚が生まれます。",
    "raw_text": "分けることで、自分が偶然の産物を独占していない感覚が生まれます。",
    "b_text": "分けることで、自分が偶然の産物を独占していない感覚が生まれます。"
  },
  {
    "index": 105,
    "text": "罪悪感が薄れ、次の偶然を素直に受け取れます。",
    "raw_text": "罪悪感が薄れ、次の偶然を素直に受け取れます。",
    "b_text": "罪悪感が薄れ、次の偶然を素直に受け取れます。"
  },
  {
    "index": 106,
    "text": "運が悪かったときは、誰かに話す。",
    "raw_text": "運が悪かったときは、誰かに話す。",
    "b_text": "運が悪かったときは、誰かに話す。"
  },
  {
    "index": 107,
    "text": "話すことで、偶然を言葉に置き、心から切り離せます。",
    "raw_text": "話すことで、偶然を言葉に置き、心から切り離せます。",
    "b_text": "話すことで、偶然を言葉に置き、心から切り離せます。"
  },
  {
    "index": 108,
    "text": "話す相手がいなければ、紙に書く。",
    "raw_text": "話す相手がいなければ、紙に書く。",
    "b_text": "話す相手がいなければ、紙に書く。"
  },
  {
    "index": 109,
    "text": "書くと、偶然が出来事に変わります。",
    "raw_text": "書くと、偶然が出来事に変わります。",
    "b_text": "書くと、偶然が出来事に変わります。"
  },
  {
    "index": 110,
    "text": "出来事になれば、距離ができます。",
    "raw_text": "出来事になれば、距離ができます。",
    "b_text": "出来事になれば、距離ができます。"
  },
  {
    "index": 111,
    "text": "距離ができれば、動き出せます。",
    "raw_text": "距離ができれば、動き出せます。",
    "b_text": "距離ができれば、動き出せます。"
  },
  {
    "index": 112,
    "text": "期待しすぎないことも大切です。",
    "raw_text": "期待しすぎないことも大切です。",
    "b_text": "期待しすぎないことも大切です。"
  },
  {
    "index": 113,
    "text": "「この一回で人生が変わる」と肩に力を入れると、運の揺れで折れます。",
    "raw_text": "「この一回で人生が変わる」と肩に力を入れると、運の揺れで折れます。",
    "b_text": "「この一回で人生が変わる」と肩に力を入れると、運の揺れで折れます。"
  },
  {
    "index": 114,
    "text": "「これがうまくいったらいいな」くらいで動くと、外れても立ち直りやすい。",
    "raw_text": "「これがうまくいったらいいな」くらいで動くと、外れても立ち直りやすい。",
    "b_text": "「これがうまくいったらいいな」くらいで動くと、外れても立ち直りやすい。"
  },
  {
    "index": 115,
    "text": "期待を少し薄めることは、怠けではなく持続のための技術です。",
    "raw_text": "期待を少し薄めることは、怠けではなく持続のための技術です。",
    "b_text": "期待を少し薄めることは、怠けではなく持続のための技術です。"
  },
  {
    "index": 116,
    "text": "運を語るときに、神や星占いを持ち出す人もいます。",
    "raw_text": "運を語るときに、神や星占いを持ち出す人もいます。",
    "b_text": "運を語るときに、神や星占いを持ち出す人もいます。"
  },
  {
    "index": 117,
    "text": "それを信じるかどうかは自由です。",
    "raw_text": "それを信じるかどうかは自由です。",
    "b_text": "それを信じるかどうかは自由です。"
  },
  {
    "index": 118,
    "text": "ただ、何を信じるにせよ、自分の行動を止めないことが大切です。",
    "raw_text": "ただ、何を信じるにせよ、自分の行動を止めないことが大切です。",
    "b_text": "ただ、何を信じるにせよ、自分の行動を止めないことが大切です。"
  },
  {
    "index": 119,
    "text": "信じるものを持ちながら、できることを淡々とやる。",
    "raw_text": "信じるものを持ちながら、できることを淡々とやる。",
    "b_text": "信じるものを持ちながら、できることを淡々とやる。"
  },
  {
    "index": 120,
    "text": "信じるものに全部預けるのではなく、半分だけ預ける感覚が、心を保ちます。",
    "raw_text": "信じるものに全部預けるのではなく、半分だけ預ける感覚が、心を保ちます。",
    "b_text": "信じるものに全部預けるのではなく、半分だけ預ける感覚が、心を保ちます。"
  },
  {
    "index": 121,
    "text": "偶然と必然は、後から決まります。",
    "raw_text": "偶然と必然は、後から決まります。",
    "b_text": "偶然と必然は、後から決まります。"
  },
  {
    "index": 122,
    "text": "起きたことに意味を与えるのは、いつも後です。",
    "raw_text": "起きたことに意味を与えるのは、いつも後です。",
    "b_text": "起きたことに意味を与えるのは、いつも後です。"
  },
  {
    "index": 123,
    "text": "だからこそ、今起きている偶然に過剰な意味を乗せすぎない。",
    "raw_text": "だからこそ、今起きている偶然に過剰な意味を乗せすぎない。",
    "b_text": "だからこそ、今起きている偶然に過剰な意味を乗せすぎない。"
  },
  {
    "index": 124,
    "text": "結果が出てから意味を考えれば十分です。",
    "raw_text": "結果が出てから意味を考えれば十分です。",
    "b_text": "結果が出てから意味を考えれば十分です。"
  },
  {
    "index": 125,
    "text": "今は、波が来たら乗るか、見送るかを決めるだけです。",
    "raw_text": "今は、波が来たら乗るか、見送るかを決めるだけです。",
    "b_text": "今は、波が来たら乗るか、見送るかを決めるだけです。"
  },
  {
    "index": 126,
    "text": "小さなラッキーを見逃さない習慣も、心を穏やかにします。",
    "raw_text": "小さなラッキーを見逃さない習慣も、心を穏やかにします。",
    "b_text": "小さなラッキーを見逃さない習慣も、心を穏やかにします。"
  },
  {
    "index": 127,
    "text": "財布の中にあった千円、予定より早く終わった会議、雨上がりの空。",
    "raw_text": "財布の中にあった千円、予定より早く終わった会議、雨上がりの空。",
    "b_text": "財布の中にあった千円、予定より早く終わった会議、雨上がりの空。"
  },
  {
    "index": 128,
    "text": "小さな偶然に気づくと、運が悪い日でも心の温度が少し上がります。",
    "raw_text": "小さな偶然に気づくと、運が悪い日でも心の温度が少し上がります。",
    "b_text": "小さな偶然に気づくと、運が悪い日でも心の温度が少し上がります。"
  },
  {
    "index": 129,
    "text": "温度が上がれば、動く力も戻ります。",
    "raw_text": "温度が上がれば、動く力も戻ります。",
    "b_text": "温度が上がれば、動く力も戻ります。"
  },
  {
    "index": 130,
    "text": "同時に、小さなアンラッキーを大事に扱わないことも大切です。",
    "raw_text": "同時に、小さなアンラッキーを大事に扱わないことも大切です。",
    "b_text": "同時に、小さなアンラッキーを大事に扱わないことも大切です。"
  },
  {
    "index": 131,
    "text": "電車が遅れた、メールの返事が遅い、天気が崩れた。",
    "raw_text": "電車が遅れた、メールの返事が遅い、天気が崩れた。",
    "b_text": "電車が遅れた、メールの返事が遅い、天気が崩れた。"
  },
  {
    "index": 132,
    "text": "これらは日常の揺れです。",
    "raw_text": "これらは日常の揺れです。",
    "b_text": "これらは日常の揺れです。"
  },
  {
    "index": 133,
    "text": "大きな意味を与えず、「そういう日もある」と通過させる。",
    "raw_text": "大きな意味を与えず、「そういう日もある」と通過させる。",
    "b_text": "大きな意味を与えず、「そういう日もある」と通過させる。"
  },
  {
    "index": 134,
    "text": "通過させる力が、運の波に溺れない力です。",
    "raw_text": "通過させる力が、運の波に溺れない力です。",
    "b_text": "通過させる力が、運の波に溺れない力です。"
  },
  {
    "index": 135,
    "text": "偶然を完全に排除することはできません。",
    "raw_text": "偶然を完全に排除することはできません。",
    "b_text": "偶然を完全に排除することはできません。"
  },
  {
    "index": 136,
    "text": "だからこそ、偶然をどう扱うかが生きやすさを決めます。",
    "raw_text": "だからこそ、偶然をどう扱うかが生きやすさを決めます。",
    "b_text": "だからこそ、偶然をどう扱うかが生きやすさを決めます。"
  },
  {
    "index": 137,
    "text": "運を神格化も悪魔化もせず、波として扱う。",
    "raw_text": "運を神格化も悪魔化もせず、波として扱う。",
    "b_text": "運を神格化も悪魔化もせず、波として扱う。"
  },
  {
    "index": 138,
    "text": "波が来たら乗る、荒れていたら避ける。",
    "raw_text": "波が来たら乗る、荒れていたら避ける。",
    "b_text": "波が来たら乗る、荒れていたら避ける。"
  },
  {
    "index": 139,
    "text": "波に名前をつけすぎず、ただ波と見る。",
    "raw_text": "波に名前をつけすぎず、ただ波と見る。",
    "b_text": "波に名前をつけすぎず、ただ波と見る。"
  },
  {
    "index": 140,
    "text": "この距離感が、心を軽くします。",
    "raw_text": "この距離感が、心を軽くします。",
    "b_text": "この距離感が、心を軽くします。"
  },
  {
    "index": 141,
    "text": "最後に、自分に向ける言葉を変えてみてください。",
    "raw_text": "最後に、自分に向ける言葉を変えてみてください。",
    "b_text": "最後に、自分に向ける言葉を変えてみてください。"
  },
  {
    "index": 142,
    "text": "運がないではなく「まだ当たっていないだけかもしれない」「今日は波が荒いから、少し沖を避けよう」。",
    "raw_text": "運がないではなく「まだ当たっていないだけかもしれない」「今日は波が荒いから、少し沖を避けよう」。",
    "b_text": "運がないではなく「まだ当たっていないだけかもしれない」「今日は波が荒いから、少し沖を避けよう」。"
  },
  {
    "index": 143,
    "text": "言葉を変えると、見える波も変わります。",
    "raw_text": "言葉を変えると、見える波も変わります。",
    "b_text": "言葉を変えると、見える波も変わります。"
  },
  {
    "index": 144,
    "text": "波が見えれば、板を握る手も落ち着きます。",
    "raw_text": "波が見えれば、板を握る手も落ち着きます。",
    "b_text": "波が見えれば、板を握る手も落ち着きます。"
  },
  {
    "index": 145,
    "text": "偶然の海は広いですが、泳ぎ方を選べます。",
    "raw_text": "偶然の海は広いですが、泳ぎ方を選べます。",
    "b_text": "偶然の海は広いですが、泳ぎ方を選べます。"
  },
  {
    "index": 146,
    "text": "選べることが自由です。",
    "raw_text": "選べることが自由です。",
    "b_text": "選べることが自由です。"
  },
  {
    "index": 147,
    "text": "自由な泳ぎ方で、あなたのペースで進んでください。",
    "raw_text": "自由な泳ぎ方で、あなたのペースで進んでください。",
    "b_text": "自由な泳ぎ方で、あなたのペースで進んでください。"
  },
  {
    "index": 148,
    "text": "時には運を運命と呼びたくなることがあります。",
    "raw_text": "時には運を運命と呼びたくなることがあります。",
    "b_text": "時には運を運命と呼びたくなることがあります。"
  },
  {
    "index": 149,
    "text": "大きな出来事が重なると、「そうなるようになっていた」と感じます。",
    "raw_text": "大きな出来事が重なると、「そうなるようになっていた」と感じます。",
    "b_text": "大きな出来事が重なると、「そうなるようになっていた」と感じます。"
  },
  {
    "index": 150,
    "text": "この感覚は心を落ち着けますが、全てを運命とすると行動が弱くなります。",
    "raw_text": "この感覚は心を落ち着けますが、全てを運命とすると行動が弱くなります。",
    "b_text": "この感覚は心を落ち着けますが、全てを運命とすると行動が弱くなります。"
  },
  {
    "index": 151,
    "text": "行動の余地を残したまま運命を受け入れるには、「起きたことは受け止める、これからすることは選ぶ」と切り分けます。",
    "raw_text": "行動の余地を残したまま運命を受け入れるには、「起きたことは受け止める、これからすることは選ぶ」と切り分けます。",
    "b_text": "行動の余地を残したまま運命を受け入れるには、「起きたことは受け止める、これからすることは選ぶ」と切り分けます。"
  },
  {
    "index": 152,
    "text": "切り分けると、安堵と主体性を同時に持てます。",
    "raw_text": "切り分けると、安堵と主体性を同時に持てます。",
    "b_text": "切り分けると、安堵と主体性を同時に持てます。"
  },
  {
    "index": 153,
    "text": "哲学者ニーチェは運命愛という考え方を提案しました。",
    "raw_text": "哲学者ニーチェは運命愛という考え方を提案しました。",
    "b_text": "哲学者ニーチェは運命愛という考え方を提案しました。"
  },
  {
    "index": 154,
    "text": "起きたことを愛する態度です。",
    "raw_text": "起きたことを愛する態度です。",
    "b_text": "起きたことを愛する態度です。"
  },
  {
    "index": 155,
    "text": "愛するとは、無理にポジティブに捉えることではなく、逃げずに見て、引き受けることです。",
    "raw_text": "愛するとは、無理にポジティブに捉えることではなく、逃げずに見て、引き受けることです。",
    "b_text": "愛するとは、無理にポジティブに捉えることではなく、逃げずに見て、引き受けることです。"
  },
  {
    "index": 156,
    "text": "引き受けた上で、今できる最善を静かに置く。",
    "raw_text": "引き受けた上で、今できる最善を静かに置く。",
    "b_text": "引き受けた上で、今できる最善を静かに置く。"
  },
  {
    "index": 157,
    "text": "これが運と共に生きる姿勢です。",
    "raw_text": "これが運と共に生きる姿勢です。",
    "b_text": "これが運と共に生きる姿勢です。"
  },
  {
    "index": 158,
    "text": "運を愛するとは、運に支配されることではなく、運と並走することです。",
    "raw_text": "運を愛するとは、運に支配されることではなく、運と並走することです。",
    "b_text": "運を愛するとは、運に支配されることではなく、運と並走することです。"
  },
  {
    "index": 159,
    "text": "「運が良い人はチャンスを掴むのがうまい」と言われます。",
    "raw_text": "「運が良い人はチャンスを掴むのがうまい」と言われます。",
    "b_text": "「運が良い人はチャンスを掴むのがうまい」と言われます。"
  },
  {
    "index": 160,
    "text": "実際には、チャンスをチャンスと認識する練習をしているだけかもしれません。",
    "raw_text": "実際には、チャンスをチャンスと認識する練習をしているだけかもしれません。",
    "b_text": "実際には、チャンスをチャンスと認識する練習をしているだけかもしれません。"
  },
  {
    "index": 161,
    "text": "普段から小さな変化に気づき、興味を持つ癖があると、偶然を拾いやすくなります。",
    "raw_text": "普段から小さな変化に気づき、興味を持つ癖があると、偶然を拾いやすくなります。",
    "b_text": "普段から小さな変化に気づき、興味を持つ癖があると、偶然を拾いやすくなります。"
  },
  {
    "index": 162,
    "text": "変化に気づく目を持つことが、運を呼ぶ一番の技術です。",
    "raw_text": "変化に気づく目を持つことが、運を呼ぶ一番の技術です。",
    "b_text": "変化に気づく目を持つことが、運を呼ぶ一番の技術です。"
  },
  {
    "index": 163,
    "text": "運に関する迷信は世界中にあります。",
    "raw_text": "運に関する迷信は世界中にあります。",
    "b_text": "運に関する迷信は世界中にあります。"
  },
  {
    "index": 164,
    "text": "黒猫、四つ葉のクローバー、ラッキーナンバー。",
    "raw_text": "黒猫、四つ葉のクローバー、ラッキーナンバー。",
    "b_text": "黒猫、四つ葉のクローバー、ラッキーナンバー。"
  },
  {
    "index": 165,
    "text": "迷信は非合理ですが、心を整える儀式でもあります。",
    "raw_text": "迷信は非合理ですが、心を整える儀式でもあります。",
    "b_text": "迷信は非合理ですが、心を整える儀式でもあります。"
  },
  {
    "index": 166,
    "text": "迷信を楽しみつつ、それに人生を預けすぎない。",
    "raw_text": "迷信を楽しみつつ、それに人生を預けすぎない。",
    "b_text": "迷信を楽しみつつ、それに人生を預けすぎない。"
  },
  {
    "index": 167,
    "text": "楽しむ程度に留めると、心の遊びが増え、硬直した思考がほぐれます。",
    "raw_text": "楽しむ程度に留めると、心の遊びが増え、硬直した思考がほぐれます。",
    "b_text": "楽しむ程度に留めると、心の遊びが増え、硬直した思考がほぐれます。"
  },
  {
    "index": 168,
    "text": "「運が良すぎて怖い」という瞬間もあります。",
    "raw_text": "「運が良すぎて怖い」という瞬間もあります。",
    "b_text": "「運が良すぎて怖い」という瞬間もあります。"
  },
  {
    "index": 169,
    "text": "幸運が続くと「次に悪いことが起きるのでは」と身構えます。",
    "raw_text": "幸運が続くと「次に悪いことが起きるのでは」と身構えます。",
    "b_text": "幸運が続くと「次に悪いことが起きるのでは」と身構えます。"
  },
  {
    "index": 170,
    "text": "幸運の後に不運が来るという法則はありません。",
    "raw_text": "幸運の後に不運が来るという法則はありません。",
    "b_text": "幸運の後に不運が来るという法則はありません。"
  },
  {
    "index": 171,
    "text": "怖さが出てきたら、幸運を使い道に変えます。",
    "raw_text": "怖さが出てきたら、幸運を使い道に変えます。",
    "b_text": "怖さが出てきたら、幸運を使い道に変えます。"
  },
  {
    "index": 172,
    "text": "学びに投資する、誰かを助ける、休むために使う。",
    "raw_text": "学びに投資する、誰かを助ける、休むために使う。",
    "b_text": "学びに投資する、誰かを助ける、休むために使う。"
  },
  {
    "index": 173,
    "text": "幸運を行動に変えると、怖さが減ります。",
    "raw_text": "幸運を行動に変えると、怖さが減ります。",
    "b_text": "幸運を行動に変えると、怖さが減ります。"
  },
  {
    "index": 174,
    "text": "偶然の衝撃を和らげるために、毎日少しだけ「最悪のシミュレーション」をしておくのも役立ちます。",
    "raw_text": "偶然の衝撃を和らげるために、毎日少しだけ「最悪のシミュレーション」をしておくのも役立ちます。",
    "b_text": "偶然の衝撃を和らげるために、毎日少しだけ「最悪のシミュレーション」をしておくのも役立ちます。"
  },
  {
    "index": 175,
    "text": "財布を落としたらどうするか、予定が全部キャンセルになったらどうするか。",
    "raw_text": "財布を落としたらどうするか、予定が全部キャンセルになったらどうするか。",
    "b_text": "財布を落としたらどうするか、予定が全部キャンセルになったらどうするか。"
  },
  {
    "index": 176,
    "text": "事前に手順を決めておくと、起きたときに慌てず動けます。",
    "raw_text": "事前に手順を決めておくと、起きたときに慌てず動けます。",
    "b_text": "事前に手順を決めておくと、起きたときに慌てず動けます。"
  },
  {
    "index": 177,
    "text": "準備は不安を生むのではなく、不安を薄めます。",
    "raw_text": "準備は不安を生むのではなく、不安を薄めます。",
    "b_text": "準備は不安を生むのではなく、不安を薄めます。"
  },
  {
    "index": 178,
    "text": "未来の偶然を完全に予測することはできませんが、過去の偶然を分解することはできます。",
    "raw_text": "未来の偶然を完全に予測することはできませんが、過去の偶然を分解することはできます。",
    "b_text": "未来の偶然を完全に予測することはできませんが、過去の偶然を分解することはできます。"
  },
  {
    "index": 179,
    "text": "偶然があった出来事を三つ選び、自分の行動他人の行動環境の揺れに分けてみる。",
    "raw_text": "偶然があった出来事を三つ選び、自分の行動他人の行動環境の揺れに分けてみる。",
    "b_text": "偶然があった出来事を三つ選び、自分の行動他人の行動環境の揺れに分けてみる。"
  },
  {
    "index": 180,
    "text": "分けると、自分が変えられる部分と変えられない部分が見えます。",
    "raw_text": "分けると、自分が変えられる部分と変えられない部分が見えます。",
    "b_text": "分けると、自分が変えられる部分と変えられない部分が見えます。"
  },
  {
    "index": 181,
    "text": "見えると、次にどこに力を入れるか決められます。",
    "raw_text": "見えると、次にどこに力を入れるか決められます。",
    "b_text": "見えると、次にどこに力を入れるか決められます。"
  },
  {
    "index": 182,
    "text": "運が悪い人のそばにいると、自分まで引きずられる気がすることがあります。",
    "raw_text": "運が悪い人のそばにいると、自分まで引きずられる気がすることがあります。",
    "b_text": "運が悪い人のそばにいると、自分まで引きずられる気がすることがあります。"
  },
  {
    "index": 183,
    "text": "実際には、運の良し悪しが移るわけではありませんが、悲観的な言葉や行動パターンは影響します。",
    "raw_text": "実際には、運の良し悪しが移るわけではありませんが、悲観的な言葉や行動パターンは影響します。",
    "b_text": "実際には、運の良し悪しが移るわけではありませんが、悲観的な言葉や行動パターンは影響します。"
  },
  {
    "index": 184,
    "text": "影響されすぎないために、自分の言葉の温度を少し上げてみてください。",
    "raw_text": "影響されすぎないために、自分の言葉の温度を少し上げてみてください。",
    "b_text": "影響されすぎないために、自分の言葉の温度を少し上げてみてください。"
  },
  {
    "index": 185,
    "text": "最悪だではなく「面倒だけど何とかするか」。",
    "raw_text": "最悪だではなく「面倒だけど何とかするか」。",
    "b_text": "最悪だではなく「面倒だけど何とかするか」。"
  },
  {
    "index": 186,
    "text": "温度を上げる言葉は、運に対する姿勢を整えます。",
    "raw_text": "温度を上げる言葉は、運に対する姿勢を整えます。",
    "b_text": "温度を上げる言葉は、運に対する姿勢を整えます。"
  },
  {
    "index": 187,
    "text": "逆に、運が良い人のそばにいると、自分も行動したくなります。",
    "raw_text": "逆に、運が良い人のそばにいると、自分も行動したくなります。",
    "b_text": "逆に、運が良い人のそばにいると、自分も行動したくなります。"
  },
  {
    "index": 188,
    "text": "これは模倣の力です。",
    "raw_text": "これは模倣の力です。",
    "b_text": "これは模倣の力です。"
  },
  {
    "index": 189,
    "text": "模倣は悪いものだけでなく、良いものも運びます。",
    "raw_text": "模倣は悪いものだけでなく、良いものも運びます。",
    "b_text": "模倣は悪いものだけでなく、良いものも運びます。"
  },
  {
    "index": 190,
    "text": "運の良さを真似するのではなく、運に対する軽やかな態度を真似する。",
    "raw_text": "運の良さを真似するのではなく、運に対する軽やかな態度を真似する。",
    "b_text": "運の良さを真似するのではなく、運に対する軽やかな態度を真似する。"
  },
  {
    "index": 191,
    "text": "軽さが伝染すると、偶然に対して柔軟になれます。",
    "raw_text": "軽さが伝染すると、偶然に対して柔軟になれます。",
    "b_text": "軽さが伝染すると、偶然に対して柔軟になれます。"
  },
  {
    "index": 192,
    "text": "避けられない不運に直面したとき、慰めにならない言葉をかけられることがあります。",
    "raw_text": "避けられない不運に直面したとき、慰めにならない言葉をかけられることがあります。",
    "b_text": "避けられない不運に直面したとき、慰めにならない言葉をかけられることがあります。"
  },
  {
    "index": 193,
    "text": "「時間が解決するよ」「これにも意味があるよ」。",
    "raw_text": "「時間が解決するよ」「これにも意味があるよ」。",
    "b_text": "「時間が解決するよ」「これにも意味があるよ」。"
  },
  {
    "index": 194,
    "text": "意味が見えないときは、「意味を探さなくていい」と自分に言ってください。",
    "raw_text": "意味が見えないときは、「意味を探さなくていい」と自分に言ってください。",
    "b_text": "意味が見えないときは、「意味を探さなくていい」と自分に言ってください。"
  },
  {
    "index": 195,
    "text": "意味は後からしか生まれません。",
    "raw_text": "意味は後からしか生まれません。",
    "b_text": "意味は後からしか生まれません。"
  },
  {
    "index": 196,
    "text": "今は痛みがあると認めるだけで十分です。",
    "raw_text": "今は痛みがあると認めるだけで十分です。",
    "b_text": "今は痛みがあると認めるだけで十分です。"
  },
  {
    "index": 197,
    "text": "認めることが、次の意味を育てる土壌になります。",
    "raw_text": "認めることが、次の意味を育てる土壌になります。",
    "b_text": "認めることが、次の意味を育てる土壌になります。"
  },
  {
    "index": 198,
    "text": "偶然の中で、人はよくもしあのときを考えます。",
    "raw_text": "偶然の中で、人はよくもしあのときを考えます。",
    "b_text": "偶然の中で、人はよくもしあのときを考えます。"
  },
  {
    "index": 199,
    "text": "別の選択をしていれば、別の運が来たのではないか。",
    "raw_text": "別の選択をしていれば、別の運が来たのではないか。",
    "b_text": "別の選択をしていれば、別の運が来たのではないか。"
  },
  {
    "index": 200,
    "text": "考えるのは自然ですが、無限の可能性に飲まれると動けなくなります。",
    "raw_text": "考えるのは自然ですが、無限の可能性に飲まれると動けなくなります。",
    "b_text": "考えるのは自然ですが、無限の可能性に飲まれると動けなくなります。"
  },
  {
    "index": 201,
    "text": "「あのときの自分はその時点の最善を選んだ」と区切ると、戻れない過去から離れやすくなります。",
    "raw_text": "「あのときの自分はその時点の最善を選んだ」と区切ると、戻れない過去から離れやすくなります。",
    "b_text": "「あのときの自分はその時点の最善を選んだ」と区切ると、戻れない過去から離れやすくなります。"
  },
  {
    "index": 202,
    "text": "区切ることで、今の選択に集中できます。",
    "raw_text": "区切ることで、今の選択に集中できます。",
    "b_text": "区切ることで、今の選択に集中できます。"
  },
  {
    "index": 203,
    "text": "偶然と倫理の関係も考えておきたいところです。",
    "raw_text": "偶然と倫理の関係も考えておきたいところです。",
    "b_text": "偶然と倫理の関係も考えておきたいところです。"
  },
  {
    "index": 204,
    "text": "道徳哲学ではモラルラックと呼ばれる問題があります。",
    "raw_text": "道徳哲学ではモラルラックと呼ばれる問題があります。",
    "b_text": "道徳哲学ではモラルラックと呼ばれる問題があります。"
  },
  {
    "index": 205,
    "text": "同じ行為でも、結果がたまたま悪く出ると非難され、良く出ると称賛される。",
    "raw_text": "同じ行為でも、結果がたまたま悪く出ると非難され、良く出ると称賛される。",
    "b_text": "同じ行為でも、結果がたまたま悪く出ると非難され、良く出ると称賛される。"
  },
  {
    "index": 206,
    "text": "結果の偶然で評価が揺れる現実を知っておくと、他人を責めすぎず、自分を責めすぎずに済みます。",
    "raw_text": "結果の偶然で評価が揺れる現実を知っておくと、他人を責めすぎず、自分を責めすぎずに済みます。",
    "b_text": "結果の偶然で評価が揺れる現実を知っておくと、他人を責めすぎず、自分を責めすぎずに済みます。"
  },
  {
    "index": 207,
    "text": "意図と努力を見て判断する視点を持つと、運の揺れに左右されにくくなります。",
    "raw_text": "意図と努力を見て判断する視点を持つと、運の揺れに左右されにくくなります。",
    "b_text": "意図と努力を見て判断する視点を持つと、運の揺れに左右されにくくなります。"
  },
  {
    "index": 208,
    "text": "会社でも偶然が評価を左右します。",
    "raw_text": "会社でも偶然が評価を左右します。",
    "b_text": "会社でも偶然が評価を左右します。"
  },
  {
    "index": 209,
    "text": "景気が良い時期に出した成果と、不況期に出した成果では見え方が違います。",
    "raw_text": "景気が良い時期に出した成果と、不況期に出した成果では見え方が違います。",
    "b_text": "景気が良い時期に出した成果と、不況期に出した成果では見え方が違います。"
  },
  {
    "index": 210,
    "text": "運の要素を言語化しておくと、評価が揺れたときに冷静でいられます。",
    "raw_text": "運の要素を言語化しておくと、評価が揺れたときに冷静でいられます。",
    "b_text": "運の要素を言語化しておくと、評価が揺れたときに冷静でいられます。"
  },
  {
    "index": 211,
    "text": "「今回は追い風だった」「今回は向かい風だった」と共有するだけで、過度な自己責任や他責を防げます。",
    "raw_text": "「今回は追い風だった」「今回は向かい風だった」と共有するだけで、過度な自己責任や他責を防げます。",
    "b_text": "「今回は追い風だった」「今回は向かい風だった」と共有するだけで、過度な自己責任や他責を防げます。"
  },
  {
    "index": 212,
    "text": "偶然を利用するためにゆらぎを日常に入れる方法をもう一つ。",
    "raw_text": "偶然を利用するためにゆらぎを日常に入れる方法をもう一つ。",
    "b_text": "偶然を利用するためにゆらぎを日常に入れる方法をもう一つ。"
  },
  {
    "index": 213,
    "text": "机の配置を少し変える、通勤の座る位置を変える、読む本のジャンルを変える。",
    "raw_text": "机の配置を少し変える、通勤の座る位置を変える、読む本のジャンルを変える。",
    "b_text": "机の配置を少し変える、通勤の座る位置を変える、読む本のジャンルを変える。"
  },
  {
    "index": 214,
    "text": "微小な変化が、新しい偶然を連れてきます。",
    "raw_text": "微小な変化が、新しい偶然を連れてきます。",
    "b_text": "微小な変化が、新しい偶然を連れてきます。"
  },
  {
    "index": 215,
    "text": "大きな変化は怖くても、小さな変化なら遊び心でできる。",
    "raw_text": "大きな変化は怖くても、小さな変化なら遊び心でできる。",
    "b_text": "大きな変化は怖くても、小さな変化なら遊び心でできる。"
  },
  {
    "index": 216,
    "text": "遊び心があると、運に対する余裕が生まれます。",
    "raw_text": "遊び心があると、運に対する余裕が生まれます。",
    "b_text": "遊び心があると、運に対する余裕が生まれます。"
  },
  {
    "index": 217,
    "text": "大きな計画を立てるときは、運の枠を決めておきます。",
    "raw_text": "大きな計画を立てるときは、運の枠を決めておきます。",
    "b_text": "大きな計画を立てるときは、運の枠を決めておきます。"
  },
  {
    "index": 218,
    "text": "期限に余裕を持たせ、予算にバッファを入れ、人手に余白を持つ。",
    "raw_text": "期限に余裕を持たせ、予算にバッファを入れ、人手に余白を持つ。",
    "b_text": "期限に余裕を持たせ、予算にバッファを入れ、人手に余白を持つ。"
  },
  {
    "index": 219,
    "text": "余白は運の揺れを吸収します。",
    "raw_text": "余白は運の揺れを吸収します。",
    "b_text": "余白は運の揺れを吸収します。"
  },
  {
    "index": 220,
    "text": "余白がない計画ほど、偶然に弱い。",
    "raw_text": "余白がない計画ほど、偶然に弱い。",
    "b_text": "余白がない計画ほど、偶然に弱い。"
  },
  {
    "index": 221,
    "text": "余白を作ることは、運を敵視しないための設計です。",
    "raw_text": "余白を作ることは、運を敵視しないための設計です。",
    "b_text": "余白を作ることは、運を敵視しないための設計です。"
  },
  {
    "index": 222,
    "text": "運が味方したと思える瞬間があったら、その前後に何があったかを書き留めておきます。",
    "raw_text": "運が味方したと思える瞬間があったら、その前後に何があったかを書き留めておきます。",
    "b_text": "運が味方したと思える瞬間があったら、その前後に何があったかを書き留めておきます。"
  },
  {
    "index": 223,
    "text": "偶然が重なる前にどんな準備や行動をしていたのか、どんな人と関わっていたのか。",
    "raw_text": "偶然が重なる前にどんな準備や行動をしていたのか、どんな人と関わっていたのか。",
    "b_text": "偶然が重なる前にどんな準備や行動をしていたのか、どんな人と関わっていたのか。"
  },
  {
    "index": 224,
    "text": "パターンが見えると、自分なりの運の呼び方が見つかります。",
    "raw_text": "パターンが見えると、自分なりの運の呼び方が見つかります。",
    "b_text": "パターンが見えると、自分なりの運の呼び方が見つかります。"
  },
  {
    "index": 225,
    "text": "見つかれば、再現性のある行動として使えます。",
    "raw_text": "見つかれば、再現性のある行動として使えます。",
    "b_text": "見つかれば、再現性のある行動として使えます。"
  },
  {
    "index": 226,
    "text": "睡眠不足や体調不良の日は、運の揺れに弱くなります。",
    "raw_text": "睡眠不足や体調不良の日は、運の揺れに弱くなります。",
    "b_text": "睡眠不足や体調不良の日は、運の揺れに弱くなります。"
  },
  {
    "index": 227,
    "text": "小さなトラブルが大きく感じられ、判断がぶれます。",
    "raw_text": "小さなトラブルが大きく感じられ、判断がぶれます。",
    "b_text": "小さなトラブルが大きく感じられ、判断がぶれます。"
  },
  {
    "index": 228,
    "text": "体を整えることは、運の波に耐えるための下地づくりです。",
    "raw_text": "体を整えることは、運の波に耐えるための下地づくりです。",
    "b_text": "体を整えることは、運の波に耐えるための下地づくりです。"
  },
  {
    "index": 229,
    "text": "体が整うと、偶然の揺れを必要以上に大きく感じません。",
    "raw_text": "体が整うと、偶然の揺れを必要以上に大きく感じません。",
    "b_text": "体が整うと、偶然の揺れを必要以上に大きく感じません。"
  },
  {
    "index": 230,
    "text": "体調管理は、運との付き合い方でもあります。",
    "raw_text": "体調管理は、運との付き合い方でもあります。",
    "b_text": "体調管理は、運との付き合い方でもあります。"
  },
  {
    "index": 231,
    "text": "最後にもう一度、言葉の力について。",
    "raw_text": "最後にもう一度、言葉の力について。",
    "b_text": "最後にもう一度、言葉の力について。"
  },
  {
    "index": 232,
    "text": "運に対する言葉が変わると、運に対する態度が変わります。",
    "raw_text": "運に対する言葉が変わると、運に対する態度が変わります。",
    "b_text": "運に対する言葉が変わると、運に対する態度が変わります。"
  },
  {
    "index": 233,
    "text": "運が悪い日だではなく波が荒い日だ。",
    "raw_text": "運が悪い日だではなく波が荒い日だ。",
    "b_text": "運が悪い日だではなく波が荒い日だ。"
  },
  {
    "index": 234,
    "text": "荒い日は、港に戻って船を整える。",
    "raw_text": "荒い日は、港に戻って船を整える。",
    "b_text": "荒い日は、港に戻って船を整える。"
  },
  {
    "index": 235,
    "text": "整え終わったら、また出ればいい。",
    "raw_text": "整え終わったら、また出ればいい。",
    "b_text": "整え終わったら、また出ればいい。"
  },
  {
    "index": 236,
    "text": "こうした言葉の置き換えが、偶然に左右されずに生きるための小さな舵になります。",
    "raw_text": "こうした言葉の置き換えが、偶然に左右されずに生きるための小さな舵になります。",
    "b_text": "こうした言葉の置き換えが、偶然に左右されずに生きるための小さな舵になります。"
  },
  {
    "index": 237,
    "text": "日常で運に振り回されたと感じたら、三つだけ確認してください。",
    "raw_text": "日常で運に振り回されたと感じたら、三つだけ確認してください。",
    "b_text": "日常で運に振り回されたと感じたら、三つだけ確認してください。"
  },
  {
    "index": 238,
    "text": "今日の睡眠は十分か。",
    "raw_text": "今日の睡眠は十分か。",
    "b_text": "今日の睡眠は十分か。"
  },
  {
    "index": 239,
    "text": "食事は乱れていないか。",
    "raw_text": "食事は乱れていないか。",
    "b_text": "食事は乱れていないか。"
  },
  {
    "index": 240,
    "text": "息を深く吐く時間を取ったか。",
    "raw_text": "息を深く吐く時間を取ったか。",
    "b_text": "息を深く吐く時間を取ったか。"
  },
  {
    "index": 241,
    "text": "この三つが整うと、同じ出来事でも揺れ方が変わります。",
    "raw_text": "この三つが整うと、同じ出来事でも揺れ方が変わります。",
    "b_text": "この三つが整うと、同じ出来事でも揺れ方が変わります。"
  },
  {
    "index": 242,
    "text": "整っていなければ、運ではなく疲れが揺らしているだけかもしれません。",
    "raw_text": "整っていなければ、運ではなく疲れが揺らしているだけかもしれません。",
    "b_text": "整っていなければ、運ではなく疲れが揺らしているだけかもしれません。"
  },
  {
    "index": 243,
    "text": "大きな決断をするときは、偶然に左右されにくい最小単位を決めておきます。",
    "raw_text": "大きな決断をするときは、偶然に左右されにくい最小単位を決めておきます。",
    "b_text": "大きな決断をするときは、偶然に左右されにくい最小単位を決めておきます。"
  },
  {
    "index": 244,
    "text": "たとえば転職なら、まずは履歴書を書く、小さな会社説明会に出る、信頼できる人に相談する。",
    "raw_text": "たとえば転職なら、まずは履歴書を書く、小さな会社説明会に出る、信頼できる人に相談する。",
    "b_text": "たとえば転職なら、まずは履歴書を書く、小さな会社説明会に出る、信頼できる人に相談する。"
  },
  {
    "index": 245,
    "text": "決断を小さな行動に分けると、一回の偶然で全てが崩れにくくなります。",
    "raw_text": "決断を小さな行動に分けると、一回の偶然で全てが崩れにくくなります。",
    "b_text": "決断を小さな行動に分けると、一回の偶然で全てが崩れにくくなります。"
  },
  {
    "index": 246,
    "text": "小さな行動の積み重ねは、運の揺れを平均化します。",
    "raw_text": "小さな行動の積み重ねは、運の揺れを平均化します。",
    "b_text": "小さな行動の積み重ねは、運の揺れを平均化します。"
  },
  {
    "index": 247,
    "text": "人間関係でも偶然は働きます。",
    "raw_text": "人間関係でも偶然は働きます。",
    "b_text": "人間関係でも偶然は働きます。"
  },
  {
    "index": 248,
    "text": "たまたま隣の席だった人と仲良くなる。",
    "raw_text": "たまたま隣の席だった人と仲良くなる。",
    "b_text": "たまたま隣の席だった人と仲良くなる。"
  },
  {
    "index": 249,
    "text": "偶然の一言で距離が縮まる。",
    "raw_text": "偶然の一言で距離が縮まる。",
    "b_text": "偶然の一言で距離が縮まる。"
  },
  {
    "index": 250,
    "text": "これを完全にコントロールすることはできませんが、挨拶をする、名前を覚える、小さな好意を返すといった行動は、自分で選べます。",
    "raw_text": "これを完全にコントロールすることはできませんが、挨拶をする、名前を覚える、小さな好意を返すといった行動は、自分で選べます。",
    "b_text": "これを完全にコントロールすることはできませんが、挨拶をする、名前を覚える、小さな好意を返すといった行動は、自分で選べます。"
  },
  {
    "index": 251,
    "text": "選んだ行動が偶然を育てます。",
    "raw_text": "選んだ行動が偶然を育てます。",
    "b_text": "選んだ行動が偶然を育てます。"
  },
  {
    "index": 252,
    "text": "若い頃の偶然を美化しすぎると、今の偶然を軽く見てしまいます。",
    "raw_text": "若い頃の偶然を美化しすぎると、今の偶然を軽く見てしまいます。",
    "b_text": "若い頃の偶然を美化しすぎると、今の偶然を軽く見てしまいます。"
  },
  {
    "index": 253,
    "text": "「あの頃は運が良かった」と懐かしむのは自然ですが、今も小さな運は起きています。",
    "raw_text": "「あの頃は運が良かった」と懐かしむのは自然ですが、今も小さな運は起きています。",
    "b_text": "「あの頃は運が良かった」と懐かしむのは自然ですが、今も小さな運は起きています。"
  },
  {
    "index": 254,
    "text": "気づけるかどうかだけが違います。",
    "raw_text": "気づけるかどうかだけが違います。",
    "b_text": "気づけるかどうかだけが違います。"
  },
  {
    "index": 255,
    "text": "過去の運を振り返るときは、今の小さな運にも目を向けてください。",
    "raw_text": "過去の運を振り返るときは、今の小さな運にも目を向けてください。",
    "b_text": "過去の運を振り返るときは、今の小さな運にも目を向けてください。"
  },
  {
    "index": 256,
    "text": "今に気づく力が、次の波に乗る力になります。",
    "raw_text": "今に気づく力が、次の波に乗る力になります。",
    "b_text": "今に気づく力が、次の波に乗る力になります。"
  },
  {
    "index": 257,
    "text": "災害や事故のような理不尽に出会ったとき、人はなぜ自分がと問います。",
    "raw_text": "災害や事故のような理不尽に出会ったとき、人はなぜ自分がと問います。",
    "b_text": "災害や事故のような理不尽に出会ったとき、人はなぜ自分がと問います。"
  },
  {
    "index": 258,
    "text": "答えが見つからない問いを抱え続けるのは苦しい。",
    "raw_text": "答えが見つからない問いを抱え続けるのは苦しい。",
    "b_text": "答えが見つからない問いを抱え続けるのは苦しい。"
  },
  {
    "index": 259,
    "text": "そんなときは、問いを変えます。",
    "raw_text": "そんなときは、問いを変えます。",
    "b_text": "そんなときは、問いを変えます。"
  },
  {
    "index": 260,
    "text": "「この状況で何ができるか」「誰に助けを求めるか」。",
    "raw_text": "「この状況で何ができるか」「誰に助けを求めるか」。",
    "b_text": "「この状況で何ができるか」「誰に助けを求めるか」。"
  },
  {
    "index": 261,
    "text": "問いを変えると、運の意味を探す苦しみから、行動の方へ視点が移ります。",
    "raw_text": "問いを変えると、運の意味を探す苦しみから、行動の方へ視点が移ります。",
    "b_text": "問いを変えると、運の意味を探す苦しみから、行動の方へ視点が移ります。"
  },
  {
    "index": 262,
    "text": "視点が動くと、少しだけ呼吸がしやすくなります。",
    "raw_text": "視点が動くと、少しだけ呼吸がしやすくなります。",
    "b_text": "視点が動くと、少しだけ呼吸がしやすくなります。"
  },
  {
    "index": 263,
    "text": "運の話をするとき、人はよく「運が良い人の真似をしろ」と言います。",
    "raw_text": "運の話をするとき、人はよく「運が良い人の真似をしろ」と言います。",
    "b_text": "運の話をするとき、人はよく「運が良い人の真似をしろ」と言います。"
  },
  {
    "index": 264,
    "text": "真似するなら、具体的な行動を真似してください。",
    "raw_text": "真似するなら、具体的な行動を真似してください。",
    "b_text": "真似するなら、具体的な行動を真似してください。"
  },
  {
    "index": 265,
    "text": "朝の散歩、情報の取り方、人への声かけの仕方。",
    "raw_text": "朝の散歩、情報の取り方、人への声かけの仕方。",
    "b_text": "朝の散歩、情報の取り方、人への声かけの仕方。"
  },
  {
    "index": 266,
    "text": "結果だけを真似しても運は移りません。",
    "raw_text": "結果だけを真似しても運は移りません。",
    "b_text": "結果だけを真似しても運は移りません。"
  },
  {
    "index": 267,
    "text": "行動を真似すると、自分の中に小さな揺らぎが生まれ、偶然の入り口が増えます。",
    "raw_text": "行動を真似すると、自分の中に小さな揺らぎが生まれ、偶然の入り口が増えます。",
    "b_text": "行動を真似すると、自分の中に小さな揺らぎが生まれ、偶然の入り口が増えます。"
  },
  {
    "index": 268,
    "text": "偶然を計画に入れることもできます。",
    "raw_text": "偶然を計画に入れることもできます。",
    "b_text": "偶然を計画に入れることもできます。"
  },
  {
    "index": 269,
    "text": "旅の予定を一日だけ空ける、仕事のスケジュールに余白日を入れる。",
    "raw_text": "旅の予定を一日だけ空ける、仕事のスケジュールに余白日を入れる。",
    "b_text": "旅の予定を一日だけ空ける、仕事のスケジュールに余白日を入れる。"
  },
  {
    "index": 270,
    "text": "余白は偶然のための箱です。",
    "raw_text": "余白は偶然のための箱です。",
    "b_text": "余白は偶然のための箱です。"
  },
  {
    "index": 271,
    "text": "箱があれば、突発のチャンスもストレスなく拾えます。",
    "raw_text": "箱があれば、突発のチャンスもストレスなく拾えます。",
    "b_text": "箱があれば、突発のチャンスもストレスなく拾えます。"
  },
  {
    "index": 272,
    "text": "余白がない予定は、偶然を敵に回します。",
    "raw_text": "余白がない予定は、偶然を敵に回します。",
    "b_text": "余白がない予定は、偶然を敵に回します。"
  },
  {
    "index": 273,
    "text": "余白がある予定は、偶然を友にします。",
    "raw_text": "余白がある予定は、偶然を友にします。",
    "b_text": "余白がある予定は、偶然を友にします。"
  },
  {
    "index": 274,
    "text": "運にまつわる不公平を見たとき、怒りが湧きます。",
    "raw_text": "運にまつわる不公平を見たとき、怒りが湧きます。",
    "b_text": "運にまつわる不公平を見たとき、怒りが湧きます。"
  },
  {
    "index": 275,
    "text": "その怒りは大切です。",
    "raw_text": "その怒りは大切です。",
    "b_text": "その怒りは大切です。"
  },
  {
    "index": 276,
    "text": "構造的な不公平は、個人の努力では解決しません。",
    "raw_text": "構造的な不公平は、個人の努力では解決しません。",
    "b_text": "構造的な不公平は、個人の努力では解決しません。"
  },
  {
    "index": 277,
    "text": "社会的な問題に対しては、怒りを声にすることも行動です。",
    "raw_text": "社会的な問題に対しては、怒りを声にすることも行動です。",
    "b_text": "社会的な問題に対しては、怒りを声にすることも行動です。"
  },
  {
    "index": 278,
    "text": "投票する、意見を伝える、支援する。",
    "raw_text": "投票する、意見を伝える、支援する。",
    "b_text": "投票する、意見を伝える、支援する。"
  },
  {
    "index": 279,
    "text": "運の揺れを個人だけに押し付けず、社会として調整する動きは、運の残酷さを和らげます。",
    "raw_text": "運の揺れを個人だけに押し付けず、社会として調整する動きは、運の残酷さを和らげます。",
    "b_text": "運の揺れを個人だけに押し付けず、社会として調整する動きは、運の残酷さを和らげます。"
  },
  {
    "index": 280,
    "text": "棚からぼた餅という言葉があります。",
    "raw_text": "棚からぼた餅という言葉があります。",
    "b_text": "棚からぼた餅という言葉があります。"
  },
  {
    "index": 281,
    "text": "偶然の幸運を笑う表現ですが、棚の下にいる人にしか落ちません。",
    "raw_text": "偶然の幸運を笑う表現ですが、棚の下にいる人にしか落ちません。",
    "b_text": "偶然の幸運を笑う表現ですが、棚の下にいる人にしか落ちません。"
  },
  {
    "index": 282,
    "text": "ぼた餅を狙って棚の下に座り続けるのは愚かですが、棚の下を通りかかる回数を増やすのは合理的です。",
    "raw_text": "ぼた餅を狙って棚の下に座り続けるのは愚かですが、棚の下を通りかかる回数を増やすのは合理的です。",
    "b_text": "ぼた餅を狙って棚の下に座り続けるのは愚かですが、棚の下を通りかかる回数を増やすのは合理的です。"
  },
  {
    "index": 283,
    "text": "棚の下を通るとは、動くこと、試すこと、人と会うことです。",
    "raw_text": "棚の下を通るとは、動くこと、試すこと、人と会うことです。",
    "b_text": "棚の下を通るとは、動くこと、試すこと、人と会うことです。"
  },
  {
    "index": 284,
    "text": "動きながら偶然に開いておく。",
    "raw_text": "動きながら偶然に開いておく。",
    "b_text": "動きながら偶然に開いておく。"
  },
  {
    "index": 285,
    "text": "これが、運と現実的に付き合う方法です。",
    "raw_text": "これが、運と現実的に付き合う方法です。",
    "b_text": "これが、運と現実的に付き合う方法です。"
  },
  {
    "index": 286,
    "text": "自分の運の波が読めてくると、他人の運にも寛容になります。",
    "raw_text": "自分の運の波が読めてくると、他人の運にも寛容になります。",
    "b_text": "自分の運の波が読めてくると、他人の運にも寛容になります。"
  },
  {
    "index": 287,
    "text": "誰かが偶然で得をしたときに嫉妬よりも「そういう風が吹いたんだな」と受け止められます。",
    "raw_text": "誰かが偶然で得をしたときに嫉妬よりも「そういう風が吹いたんだな」と受け止められます。",
    "b_text": "誰かが偶然で得をしたときに嫉妬よりも「そういう風が吹いたんだな」と受け止められます。"
  },
  {
    "index": 288,
    "text": "誰かが偶然で損をしたときにも、たまたまだと思えば責めすぎません。",
    "raw_text": "誰かが偶然で損をしたときにも、たまたまだと思えば責めすぎません。",
    "b_text": "誰かが偶然で損をしたときにも、たまたまだと思えば責めすぎません。"
  },
  {
    "index": 289,
    "text": "寛容さは、運の波に対するクッションです。",
    "raw_text": "寛容さは、運の波に対するクッションです。",
    "b_text": "寛容さは、運の波に対するクッションです。"
  },
  {
    "index": 290,
    "text": "クッションが厚いほど、心は柔らかく保てます。",
    "raw_text": "クッションが厚いほど、心は柔らかく保てます。",
    "b_text": "クッションが厚いほど、心は柔らかく保てます。"
  },
  {
    "index": 291,
    "text": "最後にもう一つ、小さな実験を提案します。",
    "raw_text": "最後にもう一つ、小さな実験を提案します。",
    "b_text": "最後にもう一つ、小さな実験を提案します。"
  },
  {
    "index": 292,
    "text": "今日、いつもと違う時間に外に出てください。",
    "raw_text": "今日、いつもと違う時間に外に出てください。",
    "b_text": "今日、いつもと違う時間に外に出てください。"
  },
  {
    "index": 293,
    "text": "違う時間に歩くだけで、出会う人も景色も変わります。",
    "raw_text": "違う時間に歩くだけで、出会う人も景色も変わります。",
    "b_text": "違う時間に歩くだけで、出会う人も景色も変わります。"
  },
  {
    "index": 294,
    "text": "小さな違いが、偶然を連れてきます。",
    "raw_text": "小さな違いが、偶然を連れてきます。",
    "b_text": "小さな違いが、偶然を連れてきます。"
  },
  {
    "index": 295,
    "text": "偶然に出会えたら、「今、波が来た」と心の中で言ってみてください。",
    "raw_text": "偶然に出会えたら、「今、波が来た」と心の中で言ってみてください。",
    "b_text": "偶然に出会えたら、「今、波が来た」と心の中で言ってみてください。"
  },
  {
    "index": 296,
    "text": "波に名前をつけず、ただ波として見る練習です。",
    "raw_text": "波に名前をつけず、ただ波として見る練習です。",
    "b_text": "波に名前をつけず、ただ波として見る練習です。"
  },
  {
    "index": 297,
    "text": "その練習が、運に飲まれずに生きる力になります。",
    "raw_text": "その練習が、運に飲まれずに生きる力になります。",
    "b_text": "その練習が、運に飲まれずに生きる力になります。"
  }
]