[
  {
    "index": 0,
    "text": "あなたは、自分の親を選んで生まれてきたのかもしれません。",
    "group_id": 0,
    "raw_text": "あなたは、自分の親を選んで生まれてきたのかもしれません。",
    "b_text": "あなたは、自分の親を選んで生まれてきたのかもしれません。",
    "duration_sec": 3.8186666666666667
  },
  {
    "index": 1,
    "text": "この言葉を聞いて、どう思いましたか。",
    "group_id": 0,
    "raw_text": "この言葉を聞いて、どう思いましたか。",
    "b_text": "この言葉を聞いて、どう思いましたか。",
    "duration_sec": 2.8266666666666667
  },
  {
    "index": 2,
    "text": "もし親との関係が良好なら「そうかもしれない」と思えるかもしれません。",
    "group_id": 0,
    "raw_text": "もし親との関係が良好なら「そうかもしれない」と思えるかもしれません。",
    "b_text": "もし親との関係が良好なら「そうかもしれない」と思えるかもしれません。",
    "duration_sec": 5.226666666666667
  },
  {
    "index": 3,
    "text": "しかし、虐待を受けた人、愛されなかった人、辛い家庭環境で育った人は「なぜこの親を選ぶ必要があったのか」と思うかもしれません。",
    "group_id": 0,
    "raw_text": "しかし、虐待を受けた人、愛されなかった人、辛い家庭環境で育った人は「なぜこの親を選ぶ必要があったのか」と思うかもしれません。",
    "b_text": "しかし、虐待を受けた人、愛されなかった人、辛い家庭環境で育った人は「なぜこの親を選ぶ必要があったのか」と思うかもしれません。",
    "duration_sec": 10.4
  },
  {
    "index": 4,
    "text": "実際、この考えに反発を感じる人は少なくありません。",
    "group_id": 0,
    "raw_text": "実際、この考えに反発を感じる人は少なくありません。",
    "b_text": "実際、この考えに反発を感じる人は少なくありません。",
    "duration_sec": 4.266666666666667
  },
  {
    "index": 5,
    "text": "「私は好んでこの苦しみを選んだわけではない」「被害者を責めているのか」と。",
    "group_id": 0,
    "raw_text": "「私は好んでこの苦しみを選んだわけではない」「被害者を責めているのか」と。",
    "b_text": "「私は好んでこの苦しみを選んだわけではない」「被害者を責めているのか」と。",
    "duration_sec": 5.365333333333333
  },
  {
    "index": 6,
    "text": "その感情は当然です。",
    "group_id": 0,
    "raw_text": "その感情は当然です。",
    "b_text": "その感情は当然です。",
    "duration_sec": 1.8453333333333333
  },
  {
    "index": 7,
    "text": "傷ついた人に「あなたが選んだ」と言うのは、残酷にさえ聞こえるかもしれません。",
    "group_id": 0,
    "raw_text": "傷ついた人に「あなたが選んだ」と言うのは、残酷にさえ聞こえるかもしれません。",
    "b_text": "傷ついた人に「あなたが選んだ」と言うのは、残酷にさえ聞こえるかもしれません。",
    "duration_sec": 5.792
  },
  {
    "index": 8,
    "text": "しかし今回の動画では、魂が親を選ぶというスピリチュアルな概念について、心理学的な視点も交えながら深く探っていきます。",
    "group_id": 0,
    "raw_text": "しかし今回の動画では、魂が親を選ぶというスピリチュアルな概念について、心理学的な視点も交えながら深く探っていきます。",
    "b_text": "しかし今回の動画では、魂が親を選ぶというスピリチュアルな概念について、心理学的な視点も交えながら深く探っていきます。",
    "duration_sec": 8.96
  },
  {
    "index": 9,
    "text": "これは、過去を変えるためではなく、今と未来を変えるための智慧です。",
    "group_id": 0,
    "raw_text": "これは、過去を変えるためではなく、今と未来を変えるための智慧です。",
    "b_text": "これは、過去を変えるためではなく、今と未来を変えるための智慧です。",
    "duration_sec": 4.736
  },
  {
    "index": 10,
    "text": "最後まで聴いていただければ、この概念が持つ深い意味と、それがあなたの癒しにどう役立つかが分かるでしょう。",
    "group_id": 0,
    "raw_text": "最後まで聴いていただければ、この概念が持つ深い意味と、それがあなたの癒しにどう役立つかが分かるでしょう。",
    "b_text": "最後まで聴いていただければ、この概念が持つ深い意味と、それがあなたの癒しにどう役立つかが分かるでしょう。",
    "duration_sec": 7.1786666666666665
  },
  {
    "index": 11,
    "text": "まず、魂が親を選ぶという概念を理解しましょう。",
    "group_id": 0,
    "raw_text": "まず、魂が親を選ぶという概念を理解しましょう。",
    "b_text": "まず、魂が親を選ぶという概念を理解しましょう。",
    "duration_sec": 4.032
  },
  {
    "index": 12,
    "text": "多くのスピリチュアルな伝統では、私たちの魂は肉体を持つ前から存在し、生まれ変わりを繰り返すと考えられています。",
    "group_id": 0,
    "raw_text": "多くのスピリチュアルな伝統では、私たちの魂は肉体を持つ前から存在し、生まれ変わりを繰り返すと考えられています。",
    "b_text": "多くのスピリチュアルな伝統では、私たちの魂は肉体を持つ前から存在し、生まれ変わりを繰り返すと考えられています。",
    "duration_sec": 8.512
  },
  {
    "index": 13,
    "text": "ヒンドゥー教の輪廻転生、仏教の再生、プラトンの魂の旅。",
    "group_id": 0,
    "raw_text": "ヒンドゥー教の輪廻転生、仏教の再生、プラトンの魂の旅。",
    "b_text": "ヒンドゥー教の輪廻転生、仏教の再生、プラトンの魂の旅。",
    "duration_sec": 5.301333333333333
  },
  {
    "index": 14,
    "text": "東西を問わず、多くの古代の叡智が、魂の永続性について語っています。",
    "group_id": 0,
    "raw_text": "東西を問わず、多くの古代の叡智が、魂の永続性について語っています。",
    "b_text": "東西を問わず、多くの古代の叡智が、魂の永続性について語っています。",
    "duration_sec": 5.749333333333333
  },
  {
    "index": 15,
    "text": "そして、各人生の前に、魂はその人生で学ぶべきテーマ、会う人々、生まれる家庭を選ぶとされています。",
    "group_id": 0,
    "raw_text": "そして、各人生の前に、魂はその人生で学ぶべきテーマ、会う人々、生まれる家庭を選ぶとされています。",
    "b_text": "そして、各人生の前に、魂はその人生で学ぶべきテーマ、会う人々、生まれる家庭を選ぶとされています。",
    "duration_sec": 8.565333333333333
  },
  {
    "index": 16,
    "text": "これは学校で時間割を決めるようなものかもしれません。",
    "group_id": 0,
    "raw_text": "これは学校で時間割を決めるようなものかもしれません。",
    "b_text": "これは学校で時間割を決めるようなものかもしれません。",
    "duration_sec": 3.477333333333333
  },
  {
    "index": 17,
    "text": "どの科目を履修するか、どの先生に学ぶか。",
    "group_id": 0,
    "raw_text": "どの科目を履修するか、どの先生に学ぶか。",
    "b_text": "どの科目を履修するか、どの先生に学ぶか。",
    "duration_sec": 3.3813333333333335
  },
  {
    "index": 18,
    "text": "この考えによれば、あなたの親は偶然ではありません。",
    "group_id": 0,
    "raw_text": "この考えによれば、あなたの親は偶然ではありません。",
    "b_text": "この考えによれば、あなたの親は偶然ではありません。",
    "duration_sec": 3.8933333333333335
  },
  {
    "index": 19,
    "text": "魂は、成長のために最適な環境を選んだのです。",
    "group_id": 0,
    "raw_text": "魂は、成長のために最適な環境を選んだのです。",
    "b_text": "魂は、成長のために最適な環境を選んだのです。",
    "duration_sec": 4.021333333333334
  },
  {
    "index": 20,
    "text": "それが厳しい環境であっても、その厳しさから学ぶべきことがあったから選んだ。",
    "group_id": 0,
    "raw_text": "それが厳しい環境であっても、その厳しさから学ぶべきことがあったから選んだ。",
    "b_text": "それが厳しい環境であっても、その厳しさから学ぶべきことがあったから選んだ。",
    "duration_sec": 5.1946666666666665
  },
  {
    "index": 21,
    "text": "これは運命論ではありません。",
    "group_id": 0,
    "raw_text": "これは運命論ではありません。",
    "b_text": "これは運命論ではありません。",
    "duration_sec": 1.984
  },
  {
    "index": 22,
    "text": "選んだのはあなた自身であり、そこから何を学ぶかもあなた次第です。",
    "group_id": 0,
    "raw_text": "選んだのはあなた自身であり、そこから何を学ぶかもあなた次第です。",
    "b_text": "選んだのはあなた自身であり、そこから何を学ぶかもあなた次第です。",
    "duration_sec": 4.565333333333333
  },
  {
    "index": 23,
    "text": "被害者として人生を終えることも、学びを得て成長することも、選択できます。",
    "group_id": 0,
    "raw_text": "被害者として人生を終えることも、学びを得て成長することも、選択できます。",
    "b_text": "被害者として人生を終えることも、学びを得て成長することも、選択できます。",
    "duration_sec": 5.632
  },
  {
    "index": 24,
    "text": "ヨガナンダは言いました。",
    "group_id": 0,
    "raw_text": "ヨガナンダは言いました。",
    "b_text": "ヨガナンダは言いました。",
    "duration_sec": 1.5146666666666666
  },
  {
    "index": 25,
    "text": "「私たちは魂として、この人生の脚本を書いてから生まれてくる。",
    "group_id": 0,
    "raw_text": "「私たちは魂として、この人生の脚本を書いてから生まれてくる。",
    "b_text": "「私たちは魂として、この人生の脚本を書いてから生まれてくる。",
    "duration_sec": 4.554666666666667
  },
  {
    "index": 26,
    "text": "困難もまた、自分で選んだ章である」と。",
    "group_id": 0,
    "raw_text": "困難もまた、自分で選んだ章である」と。",
    "b_text": "困難もまた、自分で選んだ章である」と。",
    "duration_sec": 3.7226666666666666
  },
  {
    "index": 27,
    "text": "しかし、なぜ困難な環境を選ぶ必要があるのでしょうか。",
    "group_id": 0,
    "raw_text": "しかし、なぜ困難な環境を選ぶ必要があるのでしょうか。",
    "b_text": "しかし、なぜ困難な環境を選ぶ必要があるのでしょうか。",
    "duration_sec": 4.341333333333333
  },
  {
    "index": 28,
    "text": "魂の観点から見ると、成長は困難を通じて起こります。",
    "group_id": 0,
    "raw_text": "魂の観点から見ると、成長は困難を通じて起こります。",
    "b_text": "魂の観点から見ると、成長は困難を通じて起こります。",
    "duration_sec": 4.448
  },
  {
    "index": 29,
    "text": "筋肉は負荷がかかることで強くなり、知恵は経験を通じて深まります。",
    "group_id": 0,
    "raw_text": "筋肉は負荷がかかることで強くなり、知恵は経験を通じて深まります。",
    "b_text": "筋肉は負荷がかかることで強くなり、知恵は経験を通じて深まります。",
    "duration_sec": 4.896
  },
  {
    "index": 30,
    "text": "魂も同様です。",
    "group_id": 0,
    "raw_text": "魂も同様です。",
    "b_text": "魂も同様です。",
    "duration_sec": 1.5253333333333334
  },
  {
    "index": 31,
    "text": "温室で育った植物より、風雨にさらされた植物の方が強い根を張る。",
    "group_id": 0,
    "raw_text": "温室で育った植物より、風雨にさらされた植物の方が強い根を張る。",
    "b_text": "温室で育った植物より、風雨にさらされた植物の方が強い根を張る。",
    "duration_sec": 4.992
  },
  {
    "index": 32,
    "text": "もし魂がすでに完璧で、学ぶべきことがないなら、生まれてくる必要はありません。",
    "group_id": 0,
    "raw_text": "もし魂がすでに完璧で、学ぶべきことがないなら、生まれてくる必要はありません。",
    "b_text": "もし魂がすでに完璧で、学ぶべきことがないなら、生まれてくる必要はありません。",
    "duration_sec": 5.8133333333333335
  },
  {
    "index": 33,
    "text": "何かを学ぶため、何かを経験するため、何かを癒すために、私たちは肉体を持って生まれてきます。",
    "group_id": 0,
    "raw_text": "何かを学ぶため、何かを経験するため、何かを癒すために、私たちは肉体を持って生まれてきます。",
    "b_text": "何かを学ぶため、何かを経験するため、何かを癒すために、私たちは肉体を持って生まれてきます。",
    "duration_sec": 7.626666666666667
  },
  {
    "index": 34,
    "text": "肉体がなければ経験できない種類の学びがあるのです。",
    "group_id": 0,
    "raw_text": "肉体がなければ経験できない種類の学びがあるのです。",
    "b_text": "肉体がなければ経験できない種類の学びがあるのです。",
    "duration_sec": 3.456
  },
  {
    "index": 35,
    "text": "例えば、自己価値を学ぶ必要がある魂は、自己価値を否定される環境を選ぶかもしれません。",
    "group_id": 0,
    "raw_text": "例えば、自己価値を学ぶ必要がある魂は、自己価値を否定される環境を選ぶかもしれません。",
    "b_text": "例えば、自己価値を学ぶ必要がある魂は、自己価値を否定される環境を選ぶかもしれません。",
    "duration_sec": 6.730666666666667
  },
  {
    "index": 36,
    "text": "そこで傷つき、苦しみ、そして自ら自己価値を見出すプロセスを経験するために。",
    "group_id": 0,
    "raw_text": "そこで傷つき、苦しみ、そして自ら自己価値を見出すプロセスを経験するために。",
    "b_text": "そこで傷つき、苦しみ、そして自ら自己価値を見出すプロセスを経験するために。",
    "duration_sec": 5.9093333333333335
  },
  {
    "index": 37,
    "text": "愛される家庭で育てば、自己価値は自然と育まれる。",
    "group_id": 0,
    "raw_text": "愛される家庭で育てば、自己価値は自然と育まれる。",
    "b_text": "愛される家庭で育てば、自己価値は自然と育まれる。",
    "duration_sec": 3.776
  },
  {
    "index": 38,
    "text": "しかし、否定される環境で自ら自己価値を見出すなら、それは揺るがない深い自信になる。",
    "group_id": 0,
    "raw_text": "しかし、否定される環境で自ら自己価値を見出すなら、それは揺るがない深い自信になる。",
    "b_text": "しかし、否定される環境で自ら自己価値を見出すなら、それは揺るがない深い自信になる。",
    "duration_sec": 6.304
  },
  {
    "index": 39,
    "text": "境界線を引くを学ぶ必要がある魂は、支配的な親のもとに生まれるかもしれません。",
    "group_id": 0,
    "raw_text": "境界線を引くを学ぶ必要がある魂は、支配的な親のもとに生まれるかもしれません。",
    "b_text": "境界線を引くを学ぶ必要がある魂は、支配的な親のもとに生まれるかもしれません。",
    "duration_sec": 5.898666666666666
  },
  {
    "index": 40,
    "text": "そこで自分を守る力を育てるために。",
    "group_id": 0,
    "raw_text": "そこで自分を守る力を育てるために。",
    "b_text": "そこで自分を守る力を育てるために。",
    "duration_sec": 2.624
  },
  {
    "index": 41,
    "text": "境界線を引かなくても安全な環境なら、その必要性を学べない。",
    "group_id": 0,
    "raw_text": "境界線を引かなくても安全な環境なら、その必要性を学べない。",
    "b_text": "境界線を引かなくても安全な環境なら、その必要性を学べない。",
    "duration_sec": 4.8853333333333335
  },
  {
    "index": 42,
    "text": "困難な環境だからこそ、生存のために境界線を学ぶ。",
    "group_id": 0,
    "raw_text": "困難な環境だからこそ、生存のために境界線を学ぶ。",
    "b_text": "困難な環境だからこそ、生存のために境界線を学ぶ。",
    "duration_sec": 4.341333333333333
  },
  {
    "index": 43,
    "text": "愛とは何かを学ぶ必要がある魂は、愛のない家庭を経験するかもしれません。",
    "group_id": 0,
    "raw_text": "愛とは何かを学ぶ必要がある魂は、愛のない家庭を経験するかもしれません。",
    "b_text": "愛とは何かを学ぶ必要がある魂は、愛のない家庭を経験するかもしれません。",
    "duration_sec": 5.664
  },
  {
    "index": 44,
    "text": "そこで真の愛を渇望し、見つけ、与えることを学ぶために。",
    "group_id": 0,
    "raw_text": "そこで真の愛を渇望し、見つけ、与えることを学ぶために。",
    "b_text": "そこで真の愛を渇望し、見つけ、与えることを学ぶために。",
    "duration_sec": 4.714666666666667
  },
  {
    "index": 45,
    "text": "愛に満ちた家庭で育てば、愛は空気のように当たり前になる。",
    "group_id": 0,
    "raw_text": "愛に満ちた家庭で育てば、愛は空気のように当たり前になる。",
    "b_text": "愛に満ちた家庭で育てば、愛は空気のように当たり前になる。",
    "duration_sec": 4.213333333333333
  },
  {
    "index": 46,
    "text": "しかし、愛を欠いた環境で育つと、愛の価値を深く理解するようになる。",
    "group_id": 0,
    "raw_text": "しかし、愛を欠いた環境で育つと、愛の価値を深く理解するようになる。",
    "b_text": "しかし、愛を欠いた環境で育つと、愛の価値を深く理解するようになる。",
    "duration_sec": 5.290666666666667
  },
  {
    "index": 47,
    "text": "強さを学ぶ必要がある魂は、逆境に満ちた環境を選ぶかもしれません。",
    "group_id": 0,
    "raw_text": "強さを学ぶ必要がある魂は、逆境に満ちた環境を選ぶかもしれません。",
    "b_text": "強さを学ぶ必要がある魂は、逆境に満ちた環境を選ぶかもしれません。",
    "duration_sec": 5.770666666666667
  },
  {
    "index": 48,
    "text": "安易に守られる環境では得られない、内なる強さを育てるために。",
    "group_id": 0,
    "raw_text": "安易に守られる環境では得られない、内なる強さを育てるために。",
    "b_text": "安易に守られる環境では得られない、内なる強さを育てるために。",
    "duration_sec": 4.554666666666667
  },
  {
    "index": 49,
    "text": "逆説的に聞こえるかもしれませんが、最も深い学びは、しばしば最も困難な状況から生まれます。",
    "group_id": 0,
    "raw_text": "逆説的に聞こえるかもしれませんが、最も深い学びは、しばしば最も困難な状況から生まれます。",
    "b_text": "逆説的に聞こえるかもしれませんが、最も深い学びは、しばしば最も困難な状況から生まれます。",
    "duration_sec": 7.221333333333333
  },
  {
    "index": 50,
    "text": "仏陀は言いました。",
    "group_id": 0,
    "raw_text": "仏陀は言いました。",
    "b_text": "仏陀は言いました。",
    "duration_sec": 1.312
  },
  {
    "index": 51,
    "text": "「蓮は泥の中から美しく咲く。",
    "group_id": 0,
    "raw_text": "「蓮は泥の中から美しく咲く。",
    "b_text": "「蓮は泥の中から美しく咲く。",
    "duration_sec": 2.112
  },
  {
    "index": 52,
    "text": "苦しみは悟りの土壌となる」と。",
    "group_id": 0,
    "raw_text": "苦しみは悟りの土壌となる」と。",
    "b_text": "苦しみは悟りの土壌となる」と。",
    "duration_sec": 2.7733333333333334
  },
  {
    "index": 53,
    "text": "蓮が泥を選ぶように、魂も成長のための泥を選ぶのかもしれません。",
    "group_id": 0,
    "raw_text": "蓮が泥を選ぶように、魂も成長のための泥を選ぶのかもしれません。",
    "b_text": "蓮が泥を選ぶように、魂も成長のための泥を選ぶのかもしれません。",
    "duration_sec": 4.992
  },
  {
    "index": 54,
    "text": "ある女性の話をしましょう。",
    "group_id": 0,
    "raw_text": "ある女性の話をしましょう。",
    "b_text": "ある女性の話をしましょう。",
    "duration_sec": 1.8666666666666667
  },
  {
    "index": 55,
    "text": "彼女は、感情的に不安定な母親のもとで育ちました。",
    "group_id": 0,
    "raw_text": "彼女は、感情的に不安定な母親のもとで育ちました。",
    "b_text": "彼女は、感情的に不安定な母親のもとで育ちました。",
    "duration_sec": 4.117333333333334
  },
  {
    "index": 56,
    "text": "母親の機嫌は予測不能で、ある日は優しく、次の日は攻撃的。",
    "group_id": 0,
    "raw_text": "母親の機嫌は予測不能で、ある日は優しく、次の日は攻撃的。",
    "b_text": "母親の機嫌は予測不能で、ある日は優しく、次の日は攻撃的。",
    "duration_sec": 5.28
  },
  {
    "index": 57,
    "text": "彼女は常に母親の顔色をうかがい、自分を殺して生きてきました。",
    "group_id": 0,
    "raw_text": "彼女は常に母親の顔色をうかがい、自分を殺して生きてきました。",
    "b_text": "彼女は常に母親の顔色をうかがい、自分を殺して生きてきました。",
    "duration_sec": 4.682666666666667
  },
  {
    "index": 58,
    "text": "子供時代、彼女は透明人間になろうとしました。",
    "group_id": 0,
    "raw_text": "子供時代、彼女は透明人間になろうとしました。",
    "b_text": "子供時代、彼女は透明人間になろうとしました。",
    "duration_sec": 3.7546666666666666
  },
  {
    "index": 59,
    "text": "目立てば攻撃される。",
    "group_id": 0,
    "raw_text": "目立てば攻撃される。",
    "b_text": "目立てば攻撃される。",
    "duration_sec": 1.504
  },
  {
    "index": 60,
    "text": "意見を言えば怒られる。",
    "group_id": 0,
    "raw_text": "意見を言えば怒られる。",
    "b_text": "意見を言えば怒られる。",
    "duration_sec": 1.536
  },
  {
    "index": 61,
    "text": "自分を消せば消すほど、安全だった。",
    "group_id": 0,
    "raw_text": "自分を消せば消すほど、安全だった。",
    "b_text": "自分を消せば消すほど、安全だった。",
    "duration_sec": 2.7946666666666666
  },
  {
    "index": 62,
    "text": "その生存戦略は、子供時代を生き延びるために必要でした。",
    "group_id": 0,
    "raw_text": "その生存戦略は、子供時代を生き延びるために必要でした。",
    "b_text": "その生存戦略は、子供時代を生き延びるために必要でした。",
    "duration_sec": 4.298666666666667
  },
  {
    "index": 63,
    "text": "大人になっても、そのパターンは続きました。",
    "group_id": 0,
    "raw_text": "大人になっても、そのパターンは続きました。",
    "b_text": "大人になっても、そのパターンは続きました。",
    "duration_sec": 2.965333333333333
  },
  {
    "index": 64,
    "text": "他人の機嫌を取り、自分のニーズを無視し、感情的に不安定な人に惹かれる。",
    "group_id": 0,
    "raw_text": "他人の機嫌を取り、自分のニーズを無視し、感情的に不安定な人に惹かれる。",
    "b_text": "他人の機嫌を取り、自分のニーズを無視し、感情的に不安定な人に惹かれる。",
    "duration_sec": 5.749333333333333
  },
  {
    "index": 65,
    "text": "まるで幼少期を繰り返しているようでした。",
    "group_id": 0,
    "raw_text": "まるで幼少期を繰り返しているようでした。",
    "b_text": "まるで幼少期を繰り返しているようでした。",
    "duration_sec": 2.6133333333333333
  },
  {
    "index": 66,
    "text": "無意識のうちに、馴染みのある関係パターンを再現していたのです。",
    "group_id": 0,
    "raw_text": "無意識のうちに、馴染みのある関係パターンを再現していたのです。",
    "b_text": "無意識のうちに、馴染みのある関係パターンを再現していたのです。",
    "duration_sec": 4.490666666666667
  },
  {
    "index": 67,
    "text": "職場では上司の顔色をうかがい、恋愛では相手の感情に振り回される。",
    "group_id": 0,
    "raw_text": "職場では上司の顔色をうかがい、恋愛では相手の感情に振り回される。",
    "b_text": "職場では上司の顔色をうかがい、恋愛では相手の感情に振り回される。",
    "duration_sec": 5.034666666666666
  },
  {
    "index": 68,
    "text": "自分がどこにもいない人生でした。",
    "group_id": 0,
    "raw_text": "自分がどこにもいない人生でした。",
    "b_text": "自分がどこにもいない人生でした。",
    "duration_sec": 2.24
  },
  {
    "index": 69,
    "text": "あるとき、彼女は魂が親を選ぶという概念に出会いました。",
    "group_id": 0,
    "raw_text": "あるとき、彼女は魂が親を選ぶという概念に出会いました。",
    "b_text": "あるとき、彼女は魂が親を選ぶという概念に出会いました。",
    "duration_sec": 4.330666666666667
  },
  {
    "index": 70,
    "text": "最初は怒りがわきました。",
    "group_id": 0,
    "raw_text": "最初は怒りがわきました。",
    "b_text": "最初は怒りがわきました。",
    "duration_sec": 1.8026666666666666
  },
  {
    "index": 71,
    "text": "「なぜ私がこんな母親を選んだのか。",
    "group_id": 0,
    "raw_text": "「なぜ私がこんな母親を選んだのか。",
    "b_text": "「なぜ私がこんな母親を選んだのか。",
    "duration_sec": 2.56
  },
  {
    "index": 72,
    "text": "選んだ覚えはない」と。",
    "group_id": 0,
    "raw_text": "選んだ覚えはない」と。",
    "b_text": "選んだ覚えはない」と。",
    "duration_sec": 2.1653333333333333
  },
  {
    "index": 73,
    "text": "「これは被害者を責める考えだ」と反発しました。",
    "group_id": 0,
    "raw_text": "「これは被害者を責める考えだ」と反発しました。",
    "b_text": "「これは被害者を責める考えだ」と反発しました。",
    "duration_sec": 3.530666666666667
  },
  {
    "index": 74,
    "text": "しかし、セラピストと共に深く探求する中で、彼女は気づき始めました。",
    "group_id": 0,
    "raw_text": "しかし、セラピストと共に深く探求する中で、彼女は気づき始めました。",
    "b_text": "しかし、セラピストと共に深く探求する中で、彼女は気づき始めました。",
    "duration_sec": 5.418666666666667
  },
  {
    "index": 75,
    "text": "この経験を通じて、彼女は何を学んだのか。",
    "group_id": 0,
    "raw_text": "この経験を通じて、彼女は何を学んだのか。",
    "b_text": "この経験を通じて、彼女は何を学んだのか。",
    "duration_sec": 3.488
  },
  {
    "index": 76,
    "text": "単に傷ついただけなのか、それとも何かを得たのか。",
    "group_id": 0,
    "raw_text": "単に傷ついただけなのか、それとも何かを得たのか。",
    "b_text": "単に傷ついただけなのか、それとも何かを得たのか。",
    "duration_sec": 3.541333333333333
  },
  {
    "index": 77,
    "text": "彼女は、他者の感情に敏感になりました。",
    "group_id": 0,
    "raw_text": "彼女は、他者の感情に敏感になりました。",
    "b_text": "彼女は、他者の感情に敏感になりました。",
    "duration_sec": 3.1573333333333333
  },
  {
    "index": 78,
    "text": "これは傷であると同時に、才能でもありました。",
    "group_id": 0,
    "raw_text": "これは傷であると同時に、才能でもありました。",
    "b_text": "これは傷であると同時に、才能でもありました。",
    "duration_sec": 3.296
  },
  {
    "index": 79,
    "text": "微細な感情の変化を読み取る能力。",
    "group_id": 0,
    "raw_text": "微細な感情の変化を読み取る能力。",
    "b_text": "微細な感情の変化を読み取る能力。",
    "duration_sec": 2.570666666666667
  },
  {
    "index": 80,
    "text": "言葉にならない痛みを察知する力。",
    "group_id": 0,
    "raw_text": "言葉にならない痛みを察知する力。",
    "b_text": "言葉にならない痛みを察知する力。",
    "duration_sec": 2.506666666666667
  },
  {
    "index": 81,
    "text": "カウンセラーとして、彼女はこの敏感さを使って多くの人を助けるようになりました。",
    "group_id": 0,
    "raw_text": "カウンセラーとして、彼女はこの敏感さを使って多くの人を助けるようになりました。",
    "b_text": "カウンセラーとして、彼女はこの敏感さを使って多くの人を助けるようになりました。",
    "duration_sec": 5.429333333333333
  },
  {
    "index": 82,
    "text": "彼女は、健全な境界線の重要性を体験的に学びました。",
    "group_id": 0,
    "raw_text": "彼女は、健全な境界線の重要性を体験的に学びました。",
    "b_text": "彼女は、健全な境界線の重要性を体験的に学びました。",
    "duration_sec": 4.661333333333333
  },
  {
    "index": 83,
    "text": "健全な家庭で育った人には分からない深さで、境界線の必要性を理解していました。",
    "group_id": 0,
    "raw_text": "健全な家庭で育った人には分からない深さで、境界線の必要性を理解していました。",
    "b_text": "健全な家庭で育った人には分からない深さで、境界線の必要性を理解していました。",
    "duration_sec": 5.941333333333334
  },
  {
    "index": 84,
    "text": "なぜなら、境界線がなかった苦しみを知っているから。",
    "group_id": 0,
    "raw_text": "なぜなら、境界線がなかった苦しみを知っているから。",
    "b_text": "なぜなら、境界線がなかった苦しみを知っているから。",
    "duration_sec": 3.68
  },
  {
    "index": 85,
    "text": "彼女は、「自分で自分を愛する」ことを学びました。",
    "group_id": 0,
    "raw_text": "彼女は、「自分で自分を愛する」ことを学びました。",
    "b_text": "彼女は、「自分で自分を愛する」ことを学びました。",
    "duration_sec": 4.010666666666666
  },
  {
    "index": 86,
    "text": "外から愛をもらえなかったからこそ、内側から愛を見つける必要があった。",
    "group_id": 0,
    "raw_text": "外から愛をもらえなかったからこそ、内側から愛を見つける必要があった。",
    "b_text": "外から愛をもらえなかったからこそ、内側から愛を見つける必要があった。",
    "duration_sec": 5.066666666666666
  },
  {
    "index": 87,
    "text": "その結果、彼女は他者に依存しない自己愛を持つようになりました。",
    "group_id": 0,
    "raw_text": "その結果、彼女は他者に依存しない自己愛を持つようになりました。",
    "b_text": "その結果、彼女は他者に依存しない自己愛を持つようになりました。",
    "duration_sec": 4.544
  },
  {
    "index": 88,
    "text": "誰かに愛されなくても、自分で自分を愛せる強さを身につけました。",
    "group_id": 0,
    "raw_text": "誰かに愛されなくても、自分で自分を愛せる強さを身につけました。",
    "b_text": "誰かに愛されなくても、自分で自分を愛せる強さを身につけました。",
    "duration_sec": 4.597333333333333
  },
  {
    "index": 89,
    "text": "彼女は言いました。",
    "group_id": 0,
    "raw_text": "彼女は言いました。",
    "b_text": "彼女は言いました。",
    "duration_sec": 1.28
  },
  {
    "index": 90,
    "text": "「あの経験がなければ、今の私はいない。",
    "group_id": 0,
    "raw_text": "「あの経験がなければ、今の私はいない。",
    "b_text": "「あの経験がなければ、今の私はいない。",
    "duration_sec": 3.008
  },
  {
    "index": 91,
    "text": "傷は痛かったけれど、その傷から成長の力が生まれた。",
    "group_id": 0,
    "raw_text": "傷は痛かったけれど、その傷から成長の力が生まれた。",
    "b_text": "傷は痛かったけれど、その傷から成長の力が生まれた。",
    "duration_sec": 4.064
  },
  {
    "index": 92,
    "text": "もしかしたら、魂はこれを知っていたのかもしれない」と。",
    "group_id": 0,
    "raw_text": "もしかしたら、魂はこれを知っていたのかもしれない」と。",
    "b_text": "もしかしたら、魂はこれを知っていたのかもしれない」と。",
    "duration_sec": 4.341333333333333
  },
  {
    "index": 93,
    "text": "これは傷を否定することではありません。",
    "group_id": 0,
    "raw_text": "これは傷を否定することではありません。",
    "b_text": "これは傷を否定することではありません。",
    "duration_sec": 2.464
  },
  {
    "index": 94,
    "text": "傷は傷として認める。",
    "group_id": 0,
    "raw_text": "傷は傷として認める。",
    "b_text": "傷は傷として認める。",
    "duration_sec": 1.5573333333333332
  },
  {
    "index": 95,
    "text": "痛みは痛みとして感じる。",
    "group_id": 0,
    "raw_text": "痛みは痛みとして感じる。",
    "b_text": "痛みは痛みとして感じる。",
    "duration_sec": 1.7066666666666668
  },
  {
    "index": 96,
    "text": "しかし、そこから何を学んだかを見ることで、経験に意味が生まれる。",
    "group_id": 0,
    "raw_text": "しかし、そこから何を学んだかを見ることで、経験に意味が生まれる。",
    "b_text": "しかし、そこから何を学んだかを見ることで、経験に意味が生まれる。",
    "duration_sec": 4.842666666666666
  },
  {
    "index": 97,
    "text": "「魂が親を選んだ」という視点は、どのような変化をもたらすでしょうか。",
    "group_id": 0,
    "raw_text": "「魂が親を選んだ」という視点は、どのような変化をもたらすでしょうか。",
    "b_text": "「魂が親を選んだ」という視点は、どのような変化をもたらすでしょうか。",
    "duration_sec": 5.205333333333333
  },
  {
    "index": 98,
    "text": "まず、被害者意識から抜け出すことができます。",
    "group_id": 0,
    "raw_text": "まず、被害者意識から抜け出すことができます。",
    "b_text": "まず、被害者意識から抜け出すことができます。",
    "duration_sec": 3.264
  },
  {
    "index": 99,
    "text": "「親のせいで私の人生はこうなった」という思考から、「この経験から何を学べるか」という思考へ移行できます。",
    "group_id": 0,
    "raw_text": "「親のせいで私の人生はこうなった」という思考から、「この経験から何を学べるか」という思考へ移行できます。",
    "b_text": "「親のせいで私の人生はこうなった」という思考から、「この経験から何を学べるか」という思考へ移行できます。",
    "duration_sec": 8.106666666666667
  },
  {
    "index": 100,
    "text": "被害者意識は、短期的には心を守ります。",
    "group_id": 0,
    "raw_text": "被害者意識は、短期的には心を守ります。",
    "b_text": "被害者意識は、短期的には心を守ります。",
    "duration_sec": 3.3706666666666667
  },
  {
    "index": 101,
    "text": "「自分は悪くない、環境が悪かった」と思うことで、自己価値を守れる。",
    "group_id": 0,
    "raw_text": "「自分は悪くない、環境が悪かった」と思うことで、自己価値を守れる。",
    "b_text": "「自分は悪くない、環境が悪かった」と思うことで、自己価値を守れる。",
    "duration_sec": 5.450666666666667
  },
  {
    "index": 102,
    "text": "しかし、長期的には自分を無力にします。",
    "group_id": 0,
    "raw_text": "しかし、長期的には自分を無力にします。",
    "b_text": "しかし、長期的には自分を無力にします。",
    "duration_sec": 3.2853333333333334
  },
  {
    "index": 103,
    "text": "環境のせいにしている限り、自分で変える力を持てない。",
    "group_id": 0,
    "raw_text": "環境のせいにしている限り、自分で変える力を持てない。",
    "b_text": "環境のせいにしている限り、自分で変える力を持てない。",
    "duration_sec": 3.957333333333333
  },
  {
    "index": 104,
    "text": "過去を変えることはできませんが、過去の解釈は変えられます。",
    "group_id": 0,
    "raw_text": "過去を変えることはできませんが、過去の解釈は変えられます。",
    "b_text": "過去を変えることはできませんが、過去の解釈は変えられます。",
    "duration_sec": 3.9466666666666668
  },
  {
    "index": 105,
    "text": "同じ経験でも、被害として見るか、学びとして見るかで、その意味は全く変わります。",
    "group_id": 0,
    "raw_text": "同じ経験でも、被害として見るか、学びとして見るかで、その意味は全く変わります。",
    "b_text": "同じ経験でも、被害として見るか、学びとして見るかで、その意味は全く変わります。",
    "duration_sec": 6.261333333333333
  },
  {
    "index": 106,
    "text": "そして、その解釈が未来を形作ります。",
    "group_id": 0,
    "raw_text": "そして、その解釈が未来を形作ります。",
    "b_text": "そして、その解釈が未来を形作ります。",
    "duration_sec": 3.2746666666666666
  },
  {
    "index": 107,
    "text": "次に、親への怒りや恨みを手放しやすくなります。",
    "group_id": 0,
    "raw_text": "次に、親への怒りや恨みを手放しやすくなります。",
    "b_text": "次に、親への怒りや恨みを手放しやすくなります。",
    "duration_sec": 3.6053333333333333
  },
  {
    "index": 108,
    "text": "親もまた、彼らなりの傷を抱えていた人間です。",
    "group_id": 0,
    "raw_text": "親もまた、彼らなりの傷を抱えていた人間です。",
    "b_text": "親もまた、彼らなりの傷を抱えていた人間です。",
    "duration_sec": 3.584
  },
  {
    "index": 109,
    "text": "完璧な親はいません。",
    "group_id": 0,
    "raw_text": "完璧な親はいません。",
    "b_text": "完璧な親はいません。",
    "duration_sec": 1.5786666666666667
  },
  {
    "index": 110,
    "text": "あなたが親に傷つけられたように、親も誰かに傷つけられていた。",
    "group_id": 0,
    "raw_text": "あなたが親に傷つけられたように、親も誰かに傷つけられていた。",
    "b_text": "あなたが親に傷つけられたように、親も誰かに傷つけられていた。",
    "duration_sec": 4.256
  },
  {
    "index": 111,
    "text": "あなたの親も、その親からパターンを受け継いだ。",
    "group_id": 0,
    "raw_text": "あなたの親も、その親からパターンを受け継いだ。",
    "b_text": "あなたの親も、その親からパターンを受け継いだ。",
    "duration_sec": 3.264
  },
  {
    "index": 112,
    "text": "そのまた親も。",
    "group_id": 0,
    "raw_text": "そのまた親も。",
    "b_text": "そのまた親も。",
    "duration_sec": 1.152
  },
  {
    "index": 113,
    "text": "傷は世代を超えて引き継がれてきた。",
    "group_id": 0,
    "raw_text": "傷は世代を超えて引き継がれてきた。",
    "b_text": "傷は世代を超えて引き継がれてきた。",
    "duration_sec": 2.2506666666666666
  },
  {
    "index": 114,
    "text": "あなたは被害者であると同時に、その連鎖を断ち切る力を持つ者でもある。",
    "group_id": 0,
    "raw_text": "あなたは被害者であると同時に、その連鎖を断ち切る力を持つ者でもある。",
    "b_text": "あなたは被害者であると同時に、その連鎖を断ち切る力を持つ者でもある。",
    "duration_sec": 4.810666666666667
  },
  {
    "index": 115,
    "text": "親を許すことは、親のためではなく、あなた自身のためです。",
    "group_id": 0,
    "raw_text": "親を許すことは、親のためではなく、あなた自身のためです。",
    "b_text": "親を許すことは、親のためではなく、あなた自身のためです。",
    "duration_sec": 4.533333333333333
  },
  {
    "index": 116,
    "text": "怒りを抱え続けることは、毒を自分に飲ませ続けるようなもの。",
    "group_id": 0,
    "raw_text": "怒りを抱え続けることは、毒を自分に飲ませ続けるようなもの。",
    "b_text": "怒りを抱え続けることは、毒を自分に飲ませ続けるようなもの。",
    "duration_sec": 4.288
  },
  {
    "index": 117,
    "text": "相手を傷つけたいと思いながら、実際に傷ついているのは自分自身。",
    "group_id": 0,
    "raw_text": "相手を傷つけたいと思いながら、実際に傷ついているのは自分自身。",
    "b_text": "相手を傷つけたいと思いながら、実際に傷ついているのは自分自身。",
    "duration_sec": 4.768
  },
  {
    "index": 118,
    "text": "許すことで、あなた自身が解放されます。",
    "group_id": 0,
    "raw_text": "許すことで、あなた自身が解放されます。",
    "b_text": "許すことで、あなた自身が解放されます。",
    "duration_sec": 3.1466666666666665
  },
  {
    "index": 119,
    "text": "許しは、相手の行為が正しかったと認めることではありません。",
    "group_id": 0,
    "raw_text": "許しは、相手の行為が正しかったと認めることではありません。",
    "b_text": "許しは、相手の行為が正しかったと認めることではありません。",
    "duration_sec": 4.2026666666666666
  },
  {
    "index": 120,
    "text": "傷つけられた事実は変わらない。",
    "group_id": 0,
    "raw_text": "傷つけられた事実は変わらない。",
    "b_text": "傷つけられた事実は変わらない。",
    "duration_sec": 2.016
  },
  {
    "index": 121,
    "text": "しかし、その重荷を下ろし、前に進むことを許すのです。",
    "group_id": 0,
    "raw_text": "しかし、その重荷を下ろし、前に進むことを許すのです。",
    "b_text": "しかし、その重荷を下ろし、前に進むことを許すのです。",
    "duration_sec": 4.522666666666667
  },
  {
    "index": 122,
    "text": "自分自身への許可証なのです。",
    "group_id": 0,
    "raw_text": "自分自身への許可証なのです。",
    "b_text": "自分自身への許可証なのです。",
    "duration_sec": 2.1546666666666665
  },
  {
    "index": 123,
    "text": "そして、人生の目的意識が生まれます。",
    "group_id": 0,
    "raw_text": "そして、人生の目的意識が生まれます。",
    "b_text": "そして、人生の目的意識が生まれます。",
    "duration_sec": 3.029333333333333
  },
  {
    "index": 124,
    "text": "この経験を通じて学んだことを、どう活かすか。",
    "group_id": 0,
    "raw_text": "この経験を通じて学んだことを、どう活かすか。",
    "b_text": "この経験を通じて学んだことを、どう活かすか。",
    "duration_sec": 3.456
  },
  {
    "index": 125,
    "text": "傷を深みに変え、苦しみを他者への慈悲に変える。",
    "group_id": 0,
    "raw_text": "傷を深みに変え、苦しみを他者への慈悲に変える。",
    "b_text": "傷を深みに変え、苦しみを他者への慈悲に変える。",
    "duration_sec": 3.4346666666666668
  },
  {
    "index": 126,
    "text": "それが魂の成長なのかもしれません。",
    "group_id": 0,
    "raw_text": "それが魂の成長なのかもしれません。",
    "b_text": "それが魂の成長なのかもしれません。",
    "duration_sec": 2.656
  },
  {
    "index": 127,
    "text": "同じ苦しみを経験した人を助ける。",
    "group_id": 0,
    "raw_text": "同じ苦しみを経験した人を助ける。",
    "b_text": "同じ苦しみを経験した人を助ける。",
    "duration_sec": 2.453333333333333
  },
  {
    "index": 128,
    "text": "世代間連鎖を断ち切る。",
    "group_id": 0,
    "raw_text": "世代間連鎖を断ち切る。",
    "b_text": "世代間連鎖を断ち切る。",
    "duration_sec": 1.792
  },
  {
    "index": 129,
    "text": "自分の子供には違う経験を与える。",
    "group_id": 0,
    "raw_text": "自分の子供には違う経験を与える。",
    "b_text": "自分の子供には違う経験を与える。",
    "duration_sec": 2.5493333333333332
  },
  {
    "index": 130,
    "text": "あなたの傷には、目的があるのかもしれません。",
    "group_id": 0,
    "raw_text": "あなたの傷には、目的があるのかもしれません。",
    "b_text": "あなたの傷には、目的があるのかもしれません。",
    "duration_sec": 3.1466666666666665
  },
  {
    "index": 131,
    "text": "カルマの視点からも考えてみましょう。",
    "group_id": 0,
    "raw_text": "カルマの視点からも考えてみましょう。",
    "b_text": "カルマの視点からも考えてみましょう。",
    "duration_sec": 2.304
  },
  {
    "index": 132,
    "text": "親子関係には、過去世からのカルマが関わっていることがあります。",
    "group_id": 0,
    "raw_text": "親子関係には、過去世からのカルマが関わっていることがあります。",
    "b_text": "親子関係には、過去世からのカルマが関わっていることがあります。",
    "duration_sec": 4.234666666666667
  },
  {
    "index": 133,
    "text": "過去世で傷つけ合った魂が、今世で親子として和解のチャンスを得る。",
    "group_id": 0,
    "raw_text": "過去世で傷つけ合った魂が、今世で親子として和解のチャンスを得る。",
    "b_text": "過去世で傷つけ合った魂が、今世で親子として和解のチャンスを得る。",
    "duration_sec": 4.618666666666667
  },
  {
    "index": 134,
    "text": "過去世で深く愛し合った魂が、今世で再び出会う。",
    "group_id": 0,
    "raw_text": "過去世で深く愛し合った魂が、今世で再び出会う。",
    "b_text": "過去世で深く愛し合った魂が、今世で再び出会う。",
    "duration_sec": 3.8293333333333335
  },
  {
    "index": 135,
    "text": "困難な親子関係は、過去世のカルマを清算する機会かもしれません。",
    "group_id": 0,
    "raw_text": "困難な親子関係は、過去世のカルマを清算する機会かもしれません。",
    "b_text": "困難な親子関係は、過去世のカルマを清算する機会かもしれません。",
    "duration_sec": 4.704
  },
  {
    "index": 136,
    "text": "今世でその関係を癒すことで、来世には持ち越さなくて済む。",
    "group_id": 0,
    "raw_text": "今世でその関係を癒すことで、来世には持ち越さなくて済む。",
    "b_text": "今世でその関係を癒すことで、来世には持ち越さなくて済む。",
    "duration_sec": 4.181333333333333
  },
  {
    "index": 137,
    "text": "また、あなたが親として経験することは、子供として経験したことの反映でもあります。",
    "group_id": 0,
    "raw_text": "また、あなたが親として経験することは、子供として経験したことの反映でもあります。",
    "b_text": "また、あなたが親として経験することは、子供として経験したことの反映でもあります。",
    "duration_sec": 6.08
  },
  {
    "index": 138,
    "text": "世代間で繰り返されるパターンを認識し、意識的に断ち切ることができます。",
    "group_id": 0,
    "raw_text": "世代間で繰り返されるパターンを認識し、意識的に断ち切ることができます。",
    "b_text": "世代間で繰り返されるパターンを認識し、意識的に断ち切ることができます。",
    "duration_sec": 5.226666666666667
  },
  {
    "index": 139,
    "text": "ヨガナンダはこう語りました。",
    "group_id": 0,
    "raw_text": "ヨガナンダはこう語りました。",
    "b_text": "ヨガナンダはこう語りました。",
    "duration_sec": 1.8453333333333333
  },
  {
    "index": 140,
    "text": "「家族は魂のグループである。",
    "group_id": 0,
    "raw_text": "「家族は魂のグループである。",
    "b_text": "「家族は魂のグループである。",
    "duration_sec": 2.026666666666667
  },
  {
    "index": 141,
    "text": "何度も生まれ変わりながら、異なる関係で再会する。",
    "group_id": 0,
    "raw_text": "何度も生まれ変わりながら、異なる関係で再会する。",
    "b_text": "何度も生まれ変わりながら、異なる関係で再会する。",
    "duration_sec": 3.7546666666666666
  },
  {
    "index": 142,
    "text": "今世の親は、過去世では子供だったかもしれない」と。",
    "group_id": 0,
    "raw_text": "今世の親は、過去世では子供だったかもしれない」と。",
    "b_text": "今世の親は、過去世では子供だったかもしれない」と。",
    "duration_sec": 4.032
  },
  {
    "index": 143,
    "text": "この視点を持つと、親子関係がより広い文脈で見えてきます。",
    "group_id": 0,
    "raw_text": "この視点を持つと、親子関係がより広い文脈で見えてきます。",
    "b_text": "この視点を持つと、親子関係がより広い文脈で見えてきます。",
    "duration_sec": 4.330666666666667
  },
  {
    "index": 144,
    "text": "この視点を日常に取り入れるための実践をお伝えします。",
    "group_id": 0,
    "raw_text": "この視点を日常に取り入れるための実践をお伝えします。",
    "b_text": "この視点を日常に取り入れるための実践をお伝えします。",
    "duration_sec": 3.6693333333333333
  },
  {
    "index": 145,
    "text": "まず、親との関係を振り返ってください。",
    "group_id": 0,
    "raw_text": "まず、親との関係を振り返ってください。",
    "b_text": "まず、親との関係を振り返ってください。",
    "duration_sec": 3.1786666666666665
  },
  {
    "index": 146,
    "text": "何が辛かったか、何が傷になったか。",
    "group_id": 0,
    "raw_text": "何が辛かったか、何が傷になったか。",
    "b_text": "何が辛かったか、何が傷になったか。",
    "duration_sec": 2.912
  },
  {
    "index": 147,
    "text": "それを否定せず、認めてください。",
    "group_id": 0,
    "raw_text": "それを否定せず、認めてください。",
    "b_text": "それを否定せず、認めてください。",
    "duration_sec": 2.528
  },
  {
    "index": 148,
    "text": "傷は傷として認めることが、癒しの第一歩です。",
    "group_id": 0,
    "raw_text": "傷は傷として認めることが、癒しの第一歩です。",
    "b_text": "傷は傷として認めることが、癒しの第一歩です。",
    "duration_sec": 3.552
  },
  {
    "index": 149,
    "text": "紙に書き出すのもいいでしょう。",
    "group_id": 0,
    "raw_text": "紙に書き出すのもいいでしょう。",
    "b_text": "紙に書き出すのもいいでしょう。",
    "duration_sec": 1.8026666666666666
  },
  {
    "index": 150,
    "text": "次に問いかけてください。",
    "group_id": 0,
    "raw_text": "次に問いかけてください。",
    "b_text": "次に問いかけてください。",
    "duration_sec": 1.5893333333333333
  },
  {
    "index": 151,
    "text": "「この経験から、私は何を学んだか」「この経験が、私をどう成長させたか」「この傷が、どんな強さを与えてくれたか」。",
    "group_id": 0,
    "raw_text": "「この経験から、私は何を学んだか」「この経験が、私をどう成長させたか」「この傷が、どんな強さを与えてくれたか」。",
    "b_text": "「この経験から、私は何を学んだか」「この経験が、私をどう成長させたか」「この傷が、どんな強さを与えてくれたか」。",
    "duration_sec": 9.504
  },
  {
    "index": 152,
    "text": "すぐに答えが出なくても構いません。",
    "group_id": 0,
    "raw_text": "すぐに答えが出なくても構いません。",
    "b_text": "すぐに答えが出なくても構いません。",
    "duration_sec": 2.2933333333333334
  },
  {
    "index": 153,
    "text": "問い続けてください。",
    "group_id": 0,
    "raw_text": "問い続けてください。",
    "b_text": "問い続けてください。",
    "duration_sec": 1.3013333333333332
  },
  {
    "index": 154,
    "text": "答えは、あなたの準備ができたときに来ます。",
    "group_id": 0,
    "raw_text": "答えは、あなたの準備ができたときに来ます。",
    "b_text": "答えは、あなたの準備ができたときに来ます。",
    "duration_sec": 3.082666666666667
  },
  {
    "index": 155,
    "text": "許しの練習をしてください。",
    "group_id": 0,
    "raw_text": "許しの練習をしてください。",
    "b_text": "許しの練習をしてください。",
    "duration_sec": 1.888
  },
  {
    "index": 156,
    "text": "許しは一度で終わるものではありません。",
    "group_id": 0,
    "raw_text": "許しは一度で終わるものではありません。",
    "b_text": "許しは一度で終わるものではありません。",
    "duration_sec": 2.432
  },
  {
    "index": 157,
    "text": "何度も繰り返し、少しずつ手放していくプロセスです。",
    "group_id": 0,
    "raw_text": "何度も繰り返し、少しずつ手放していくプロセスです。",
    "b_text": "何度も繰り返し、少しずつ手放していくプロセスです。",
    "duration_sec": 3.872
  },
  {
    "index": 158,
    "text": "「私は〇〇を許す」と心の中で唱える。",
    "group_id": 0,
    "raw_text": "「私は〇〇を許す」と心の中で唱える。",
    "b_text": "「私はまるまるを許す」と心の中で唱える。",
    "duration_sec": 3.4133333333333336
  },
  {
    "index": 159,
    "text": "今日許せなくても、明日また唱える。",
    "group_id": 0,
    "raw_text": "今日許せなくても、明日また唱える。",
    "b_text": "今日許せなくても、明日また唱える。",
    "duration_sec": 2.688
  },
  {
    "index": 160,
    "text": "少しずつ、軽くなっていきます。",
    "group_id": 0,
    "raw_text": "少しずつ、軽くなっていきます。",
    "b_text": "少しずつ、軽くなっていきます。",
    "duration_sec": 2.5813333333333333
  },
  {
    "index": 161,
    "text": "自分自身を親として見てください。",
    "group_id": 0,
    "raw_text": "自分自身を親として見てください。",
    "b_text": "自分自身を親として見てください。",
    "duration_sec": 2.1973333333333334
  },
  {
    "index": 162,
    "text": "あなたの中には、インナーチャイルド（内なる子供）がいます。",
    "group_id": 0,
    "raw_text": "あなたの中には、インナーチャイルド（内なる子供）がいます。",
    "b_text": "あなたの中には、インナーチャイルド（内なる子供）がいます。",
    "duration_sec": 4.757333333333333
  },
  {
    "index": 163,
    "text": "その子供に、今のあなたが親としてあげられなかったものをあげる。",
    "group_id": 0,
    "raw_text": "その子供に、今のあなたが親としてあげられなかったものをあげる。",
    "b_text": "その子供に、今のあなたが親としてあげられなかったものをあげる。",
    "duration_sec": 4.1386666666666665
  },
  {
    "index": 164,
    "text": "安心、愛、認められる感覚。",
    "group_id": 0,
    "raw_text": "安心、愛、認められる感覚。",
    "b_text": "安心、愛、認められる感覚。",
    "duration_sec": 3.1253333333333333
  },
  {
    "index": 165,
    "text": "自分で自分を育て直すことができます。",
    "group_id": 0,
    "raw_text": "自分で自分を育て直すことができます。",
    "b_text": "自分で自分を育て直すことができます。",
    "duration_sec": 2.6666666666666665
  },
  {
    "index": 166,
    "text": "「小さなあなたは、何を必要としていた？",
    "group_id": 0,
    "raw_text": "「小さなあなたは、何を必要としていた？",
    "b_text": "「小さなあなたは、何を必要としていた？",
    "duration_sec": 3.168
  },
  {
    "index": 167,
    "text": "」と問いかけてください。",
    "group_id": 0,
    "raw_text": "」と問いかけてください。",
    "b_text": "」と問いかけてください。",
    "duration_sec": 1.3333333333333333
  },
  {
    "index": 168,
    "text": "安全、認められること、無条件の愛。",
    "group_id": 0,
    "raw_text": "安全、認められること、無条件の愛。",
    "b_text": "安全、認められること、無条件の愛。",
    "duration_sec": 3.445333333333333
  },
  {
    "index": 169,
    "text": "今の大人のあなたが、それを与えることができます。",
    "group_id": 0,
    "raw_text": "今の大人のあなたが、それを与えることができます。",
    "b_text": "今の大人のあなたが、それを与えることができます。",
    "duration_sec": 3.456
  },
  {
    "index": 170,
    "text": "そして、もし子供がいるなら、または将来持つなら、世代間パターンを意識してください。",
    "group_id": 0,
    "raw_text": "そして、もし子供がいるなら、または将来持つなら、世代間パターンを意識してください。",
    "b_text": "そして、もし子供がいるなら、または将来持つなら、世代間パターンを意識してください。",
    "duration_sec": 6.368
  },
  {
    "index": 171,
    "text": "自分が受けた傷を、子供に引き継がないようにする。",
    "group_id": 0,
    "raw_text": "自分が受けた傷を、子供に引き継がないようにする。",
    "b_text": "自分が受けた傷を、子供に引き継がないようにする。",
    "duration_sec": 3.3706666666666667
  },
  {
    "index": 172,
    "text": "意識的な子育てが、カルマの連鎖を断ち切ります。",
    "group_id": 0,
    "raw_text": "意識的な子育てが、カルマの連鎖を断ち切ります。",
    "b_text": "意識的な子育てが、カルマの連鎖を断ち切ります。",
    "duration_sec": 3.488
  },
  {
    "index": 173,
    "text": "あなたは、傷の連鎖を終わらせる人になれます。",
    "group_id": 0,
    "raw_text": "あなたは、傷の連鎖を終わらせる人になれます。",
    "b_text": "あなたは、傷の連鎖を終わらせる人になれます。",
    "duration_sec": 3.232
  },
  {
    "index": 174,
    "text": "この動画をここまで見てくださったあなたへ。",
    "group_id": 0,
    "raw_text": "この動画をここまで見てくださったあなたへ。",
    "b_text": "この動画をここまで見てくださったあなたへ。",
    "duration_sec": 2.538666666666667
  },
  {
    "index": 175,
    "text": "「魂が親を選んだ」という考えは、証明できるものではありません。",
    "group_id": 0,
    "raw_text": "「魂が親を選んだ」という考えは、証明できるものではありません。",
    "b_text": "「魂が親を選んだ」という考えは、証明できるものではありません。",
    "duration_sec": 5.0986666666666665
  },
  {
    "index": 176,
    "text": "信じるか信じないかは、あなた次第です。",
    "group_id": 0,
    "raw_text": "信じるか信じないかは、あなた次第です。",
    "b_text": "信じるか信じないかは、あなた次第です。",
    "duration_sec": 3.04
  },
  {
    "index": 177,
    "text": "スピリチュアルな真実として受け取るか、心理的なツールとして使うか、それもあなたの選択です。",
    "group_id": 0,
    "raw_text": "スピリチュアルな真実として受け取るか、心理的なツールとして使うか、それもあなたの選択です。",
    "b_text": "スピリチュアルな真実として受け取るか、心理的なツールとして使うか、それもあなたの選択です。",
    "duration_sec": 6.496
  },
  {
    "index": 178,
    "text": "しかし、この視点を持つことで、過去への見方が変わり、現在の生き方が変わり、未来への可能性が広がるなら、それには価値があります。",
    "group_id": 0,
    "raw_text": "しかし、この視点を持つことで、過去への見方が変わり、現在の生き方が変わり、未来への可能性が広がるなら、それには価値があります。",
    "b_text": "しかし、この視点を持つことで、過去への見方が変わり、現在の生き方が変わり、未来への可能性が広がるなら、それには価値があります。",
    "duration_sec": 10.069333333333333
  },
  {
    "index": 179,
    "text": "あなたの経験には、意味があります。",
    "group_id": 0,
    "raw_text": "あなたの経験には、意味があります。",
    "b_text": "あなたの経験には、意味があります。",
    "duration_sec": 2.624
  },
  {
    "index": 180,
    "text": "その意味を見つけ、活かすことができるのは、あなただけです。",
    "group_id": 0,
    "raw_text": "その意味を見つけ、活かすことができるのは、あなただけです。",
    "b_text": "その意味を見つけ、活かすことができるのは、あなただけです。",
    "duration_sec": 4.128
  },
  {
    "index": 181,
    "text": "傷は、あなたを定義するものではありません。",
    "group_id": 0,
    "raw_text": "傷は、あなたを定義するものではありません。",
    "b_text": "傷は、あなたを定義するものではありません。",
    "duration_sec": 3.0933333333333333
  },
  {
    "index": 182,
    "text": "傷から何を学び、どう成長するかが、あなたを定義します。",
    "group_id": 0,
    "raw_text": "傷から何を学び、どう成長するかが、あなたを定義します。",
    "b_text": "傷から何を学び、どう成長するかが、あなたを定義します。",
    "duration_sec": 4.608
  },
  {
    "index": 183,
    "text": "親との関係について、もう少し深く探ってみましょう。",
    "group_id": 0,
    "raw_text": "親との関係について、もう少し深く探ってみましょう。",
    "b_text": "親との関係について、もう少し深く探ってみましょう。",
    "duration_sec": 3.8186666666666667
  },
  {
    "index": 184,
    "text": "親との関係は、人生で最も影響力のある関係の一つです。",
    "group_id": 0,
    "raw_text": "親との関係は、人生で最も影響力のある関係の一つです。",
    "b_text": "親との関係は、人生で最も影響力のある関係の一つです。",
    "duration_sec": 4.746666666666667
  },
  {
    "index": 185,
    "text": "良くも悪くも、私たちの自己イメージ、人間関係のパターン、世界の見方に深く影響を与えます。",
    "group_id": 0,
    "raw_text": "良くも悪くも、私たちの自己イメージ、人間関係のパターン、世界の見方に深く影響を与えます。",
    "b_text": "良くも悪くも、私たちの自己イメージ、人間関係のパターン、世界の見方に深く影響を与えます。",
    "duration_sec": 7.509333333333333
  },
  {
    "index": 186,
    "text": "しかし、親も完璧ではありませんでした。",
    "group_id": 0,
    "raw_text": "しかし、親も完璧ではありませんでした。",
    "b_text": "しかし、親も完璧ではありませんでした。",
    "duration_sec": 3.072
  },
  {
    "index": 187,
    "text": "親自身が傷を抱え、不完全な環境で育った。",
    "group_id": 0,
    "raw_text": "親自身が傷を抱え、不完全な環境で育った。",
    "b_text": "親自身が傷を抱え、不完全な環境で育った。",
    "duration_sec": 3.957333333333333
  },
  {
    "index": 188,
    "text": "その親から学んだパターンを、無意識に繰り返していた。",
    "group_id": 0,
    "raw_text": "その親から学んだパターンを、無意識に繰り返していた。",
    "b_text": "その親から学んだパターンを、無意識に繰り返していた。",
    "duration_sec": 3.7866666666666666
  },
  {
    "index": 189,
    "text": "傷ついた人が傷つけてしまう。",
    "group_id": 0,
    "raw_text": "傷ついた人が傷つけてしまう。",
    "b_text": "傷ついた人が傷つけてしまう。",
    "duration_sec": 2.026666666666667
  },
  {
    "index": 190,
    "text": "それは意図的な悪意ではなく、知らないがゆえの連鎖でした。",
    "group_id": 0,
    "raw_text": "それは意図的な悪意ではなく、知らないがゆえの連鎖でした。",
    "b_text": "それは意図的な悪意ではなく、知らないがゆえの連鎖でした。",
    "duration_sec": 4.0
  },
  {
    "index": 191,
    "text": "この理解は、許しを容易にします。",
    "group_id": 0,
    "raw_text": "この理解は、許しを容易にします。",
    "b_text": "この理解は、許しを容易にします。",
    "duration_sec": 2.784
  },
  {
    "index": 192,
    "text": "親を神聖化する必要も、悪魔化する必要もない。",
    "group_id": 0,
    "raw_text": "親を神聖化する必要も、悪魔化する必要もない。",
    "b_text": "親を神聖化する必要も、悪魔化する必要もない。",
    "duration_sec": 3.712
  },
  {
    "index": 193,
    "text": "ただ、不完全な人間として見る。",
    "group_id": 0,
    "raw_text": "ただ、不完全な人間として見る。",
    "b_text": "ただ、不完全な人間として見る。",
    "duration_sec": 2.528
  },
  {
    "index": 194,
    "text": "不完全でありながら、精一杯生きようとした人間として。",
    "group_id": 0,
    "raw_text": "不完全でありながら、精一杯生きようとした人間として。",
    "b_text": "不完全でありながら、精一杯生きようとした人間として。",
    "duration_sec": 4.096
  },
  {
    "index": 195,
    "text": "また、良い親悪い親という二元論を超えることも大切です。",
    "group_id": 0,
    "raw_text": "また、良い親悪い親という二元論を超えることも大切です。",
    "b_text": "また、良い親悪い親という二元論を超えることも大切です。",
    "duration_sec": 4.341333333333333
  },
  {
    "index": 196,
    "text": "ほとんどの親は、良い面と悪い面の両方を持っています。",
    "group_id": 0,
    "raw_text": "ほとんどの親は、良い面と悪い面の両方を持っています。",
    "b_text": "ほとんどの親は、良い面と悪い面の両方を持っています。",
    "duration_sec": 3.978666666666667
  },
  {
    "index": 197,
    "text": "愛情深い瞬間もあれば、傷つける瞬間もあった。",
    "group_id": 0,
    "raw_text": "愛情深い瞬間もあれば、傷つける瞬間もあった。",
    "b_text": "愛情深い瞬間もあれば、傷つける瞬間もあった。",
    "duration_sec": 3.8506666666666667
  },
  {
    "index": 198,
    "text": "全体を見ることで、より正確な理解が生まれます。",
    "group_id": 0,
    "raw_text": "全体を見ることで、より正確な理解が生まれます。",
    "b_text": "全体を見ることで、より正確な理解が生まれます。",
    "duration_sec": 3.5946666666666665
  },
  {
    "index": 199,
    "text": "あなたが親になったとき、または親として生きているなら、完璧を目指す必要はありません。",
    "group_id": 0,
    "raw_text": "あなたが親になったとき、または親として生きているなら、完璧を目指す必要はありません。",
    "b_text": "あなたが親になったとき、または親として生きているなら、完璧を目指す必要はありません。",
    "duration_sec": 6.069333333333334
  },
  {
    "index": 200,
    "text": "完璧な親はいないからです。",
    "group_id": 0,
    "raw_text": "完璧な親はいないからです。",
    "b_text": "完璧な親はいないからです。",
    "duration_sec": 1.9093333333333333
  },
  {
    "index": 201,
    "text": "大切なのは、意識的であること。",
    "group_id": 0,
    "raw_text": "大切なのは、意識的であること。",
    "b_text": "大切なのは、意識的であること。",
    "duration_sec": 2.496
  },
  {
    "index": 202,
    "text": "自分のパターンに気づき、意図的に選択すること。",
    "group_id": 0,
    "raw_text": "自分のパターンに気づき、意図的に選択すること。",
    "b_text": "自分のパターンに気づき、意図的に選択すること。",
    "duration_sec": 3.445333333333333
  },
  {
    "index": 203,
    "text": "間違えたら、謝る勇気を持つこと。",
    "group_id": 0,
    "raw_text": "間違えたら、謝る勇気を持つこと。",
    "b_text": "間違えたら、謝る勇気を持つこと。",
    "duration_sec": 2.7946666666666666
  },
  {
    "index": 204,
    "text": "子供の話を聴く姿勢を持つこと。",
    "group_id": 0,
    "raw_text": "子供の話を聴く姿勢を持つこと。",
    "b_text": "子供の話を聴く姿勢を持つこと。",
    "duration_sec": 2.3893333333333335
  },
  {
    "index": 205,
    "text": "自分自身のケアを怠らないこと。",
    "group_id": 0,
    "raw_text": "自分自身のケアを怠らないこと。",
    "b_text": "自分自身のケアを怠らないこと。",
    "duration_sec": 2.304
  },
  {
    "index": 206,
    "text": "消耗した親からは、健全な養育は生まれません。",
    "group_id": 0,
    "raw_text": "消耗した親からは、健全な養育は生まれません。",
    "b_text": "消耗した親からは、健全な養育は生まれません。",
    "duration_sec": 3.7013333333333334
  },
  {
    "index": 207,
    "text": "世代間で受け継がれてきたパターンについても考えてみましょう。",
    "group_id": 0,
    "raw_text": "世代間で受け継がれてきたパターンについても考えてみましょう。",
    "b_text": "世代間で受け継がれてきたパターンについても考えてみましょう。",
    "duration_sec": 3.7546666666666666
  },
  {
    "index": 208,
    "text": "あなたの親が示した行動パターンは、その親から学んだものかもしれません。",
    "group_id": 0,
    "raw_text": "あなたの親が示した行動パターンは、その親から学んだものかもしれません。",
    "b_text": "あなたの親が示した行動パターンは、その親から学んだものかもしれません。",
    "duration_sec": 4.96
  },
  {
    "index": 209,
    "text": "そのまた親から。",
    "group_id": 0,
    "raw_text": "そのまた親から。",
    "b_text": "そのまた親から。",
    "duration_sec": 1.2586666666666666
  },
  {
    "index": 210,
    "text": "何世代にもわたって、無意識に引き継がれてきた。",
    "group_id": 0,
    "raw_text": "何世代にもわたって、無意識に引き継がれてきた。",
    "b_text": "何世代にもわたって、無意識に引き継がれてきた。",
    "duration_sec": 3.3066666666666666
  },
  {
    "index": 211,
    "text": "これらのパターンには肯定的なものもあります。",
    "group_id": 0,
    "raw_text": "これらのパターンには肯定的なものもあります。",
    "b_text": "これらのパターンには肯定的なものもあります。",
    "duration_sec": 2.848
  },
  {
    "index": 212,
    "text": "家族の絆、特定の価値観、生きる知恵。",
    "group_id": 0,
    "raw_text": "家族の絆、特定の価値観、生きる知恵。",
    "b_text": "家族の絆、特定の価値観、生きる知恵。",
    "duration_sec": 3.6053333333333333
  },
  {
    "index": 213,
    "text": "しかし、否定的なパターンも引き継がれることがあります。",
    "group_id": 0,
    "raw_text": "しかし、否定的なパターンも引き継がれることがあります。",
    "b_text": "しかし、否定的なパターンも引き継がれることがあります。",
    "duration_sec": 3.6586666666666665
  },
  {
    "index": 214,
    "text": "感情の抑圧、暴力、依存症、コミュニケーションの問題。",
    "group_id": 0,
    "raw_text": "感情の抑圧、暴力、依存症、コミュニケーションの問題。",
    "b_text": "感情の抑圧、暴力、依存症、コミュニケーションの問題。",
    "duration_sec": 5.045333333333334
  },
  {
    "index": 215,
    "text": "あなたは、このパターンの連鎖を意識的に断ち切る力を持っています。",
    "group_id": 0,
    "raw_text": "あなたは、このパターンの連鎖を意識的に断ち切る力を持っています。",
    "b_text": "あなたは、このパターンの連鎖を意識的に断ち切る力を持っています。",
    "duration_sec": 4.490666666666667
  },
  {
    "index": 216,
    "text": "「自分はこうされた。",
    "group_id": 0,
    "raw_text": "「自分はこうされた。",
    "b_text": "「自分はこうされた。",
    "duration_sec": 1.376
  },
  {
    "index": 217,
    "text": "だから子供にも同じことをする」という自動的な反応ではなく、「自分はこうされた。",
    "group_id": 0,
    "raw_text": "だから子供にも同じことをする」という自動的な反応ではなく、「自分はこうされた。",
    "b_text": "だから子供にも同じことをする」という自動的な反応ではなく、「自分はこうされた。",
    "duration_sec": 5.888
  },
  {
    "index": 218,
    "text": "だから子供には違う経験を与える」という意識的な選択ができます。",
    "group_id": 0,
    "raw_text": "だから子供には違う経験を与える」という意識的な選択ができます。",
    "b_text": "だから子供には違う経験を与える」という意識的な選択ができます。",
    "duration_sec": 4.896
  },
  {
    "index": 219,
    "text": "これは簡単ではありません。",
    "group_id": 0,
    "raw_text": "これは簡単ではありません。",
    "b_text": "これは簡単ではありません。",
    "duration_sec": 1.8133333333333332
  },
  {
    "index": 220,
    "text": "無意識のパターンは強力で、ストレス下では自動的に発動します。",
    "group_id": 0,
    "raw_text": "無意識のパターンは強力で、ストレス下では自動的に発動します。",
    "b_text": "無意識のパターンは強力で、ストレス下では自動的に発動します。",
    "duration_sec": 4.629333333333333
  },
  {
    "index": 221,
    "text": "しかし、気づくことが第一歩です。",
    "group_id": 0,
    "raw_text": "しかし、気づくことが第一歩です。",
    "b_text": "しかし、気づくことが第一歩です。",
    "duration_sec": 2.6666666666666665
  },
  {
    "index": 222,
    "text": "そして、少しずつ、意識的に違う選択をすることで、パターンは変わっていきます。",
    "group_id": 0,
    "raw_text": "そして、少しずつ、意識的に違う選択をすることで、パターンは変わっていきます。",
    "b_text": "そして、少しずつ、意識的に違う選択をすることで、パターンは変わっていきます。",
    "duration_sec": 6.24
  },
  {
    "index": 223,
    "text": "科学的な視点から見ても、私たちの行動パターンの多くは幼少期に形成されます。",
    "group_id": 0,
    "raw_text": "科学的な視点から見ても、私たちの行動パターンの多くは幼少期に形成されます。",
    "b_text": "科学的な視点から見ても、私たちの行動パターンの多くは幼少期に形成されます。",
    "duration_sec": 5.824
  },
  {
    "index": 224,
    "text": "ミラーニューロンと呼ばれる脳の仕組みにより、子供は親の行動を無意識に模倣します。",
    "group_id": 0,
    "raw_text": "ミラーニューロンと呼ばれる脳の仕組みにより、子供は親の行動を無意識に模倣します。",
    "b_text": "ミラーニューロンと呼ばれる脳の仕組みにより、子供は親の行動を無意識に模倣します。",
    "duration_sec": 5.44
  },
  {
    "index": 225,
    "text": "しかし、脳の可塑性により、大人になってからもパターンを変えることは可能です。",
    "group_id": 0,
    "raw_text": "しかし、脳の可塑性により、大人になってからもパターンを変えることは可能です。",
    "b_text": "しかし、脳の可塑性により、大人になってからもパターンを変えることは可能です。",
    "duration_sec": 5.514666666666667
  },
  {
    "index": 226,
    "text": "セラピー、自己啓発、意識的な実践。",
    "group_id": 0,
    "raw_text": "セラピー、自己啓発、意識的な実践。",
    "b_text": "セラピー、自己啓発、意識的な実践。",
    "duration_sec": 3.6053333333333333
  },
  {
    "index": 227,
    "text": "これらを通じて、古いパターンを解除し、新しいパターンを構築できます。",
    "group_id": 0,
    "raw_text": "これらを通じて、古いパターンを解除し、新しいパターンを構築できます。",
    "b_text": "これらを通じて、古いパターンを解除し、新しいパターンを構築できます。",
    "duration_sec": 5.397333333333333
  },
  {
    "index": 228,
    "text": "過去に縛られる必要はないのです。",
    "group_id": 0,
    "raw_text": "過去に縛られる必要はないのです。",
    "b_text": "過去に縛られる必要はないのです。",
    "duration_sec": 2.2293333333333334
  },
  {
    "index": 229,
    "text": "具体的な癒しのステップをお伝えします。",
    "group_id": 0,
    "raw_text": "具体的な癒しのステップをお伝えします。",
    "b_text": "具体的な癒しのステップをお伝えします。",
    "duration_sec": 2.72
  },
  {
    "index": 230,
    "text": "ステップ1：認識。",
    "group_id": 0,
    "raw_text": "ステップ1：認識。",
    "b_text": "ステップワン：認識。",
    "duration_sec": 1.9733333333333334
  },
  {
    "index": 231,
    "text": "まず、自分の傷を認識してください。",
    "group_id": 0,
    "raw_text": "まず、自分の傷を認識してください。",
    "b_text": "まず、自分の傷を認識してください。",
    "duration_sec": 3.018666666666667
  },
  {
    "index": 232,
    "text": "何が辛かったか、何が悲しかったか、何が怖かったか。",
    "group_id": 0,
    "raw_text": "何が辛かったか、何が悲しかったか、何が怖かったか。",
    "b_text": "何が辛かったか、何が悲しかったか、何が怖かったか。",
    "duration_sec": 4.426666666666667
  },
  {
    "index": 233,
    "text": "感じないふりをせず、正直に認める。",
    "group_id": 0,
    "raw_text": "感じないふりをせず、正直に認める。",
    "b_text": "感じないふりをせず、正直に認める。",
    "duration_sec": 2.8373333333333335
  },
  {
    "index": 234,
    "text": "これが癒しの土台です。",
    "group_id": 0,
    "raw_text": "これが癒しの土台です。",
    "b_text": "これが癒しの土台です。",
    "duration_sec": 1.6106666666666667
  },
  {
    "index": 235,
    "text": "ステップ2：表現。",
    "group_id": 0,
    "raw_text": "ステップ2：表現。",
    "b_text": "ステップツー：表現。",
    "duration_sec": 1.8346666666666667
  },
  {
    "index": 236,
    "text": "感情を表現してください。",
    "group_id": 0,
    "raw_text": "感情を表現してください。",
    "b_text": "感情を表現してください。",
    "duration_sec": 1.856
  },
  {
    "index": 237,
    "text": "書く、話す、泣く、叫ぶ。",
    "group_id": 0,
    "raw_text": "書く、話す、泣く、叫ぶ。",
    "b_text": "書く、話す、泣く、叫ぶ。",
    "duration_sec": 3.6053333333333333
  },
  {
    "index": 238,
    "text": "抑え込んできた感情を安全に解放する。",
    "group_id": 0,
    "raw_text": "抑え込んできた感情を安全に解放する。",
    "b_text": "抑え込んできた感情を安全に解放する。",
    "duration_sec": 2.8693333333333335
  },
  {
    "index": 239,
    "text": "セラピストや信頼できる友人と共にするのもいいでしょう。",
    "group_id": 0,
    "raw_text": "セラピストや信頼できる友人と共にするのもいいでしょう。",
    "b_text": "セラピストや信頼できる友人と共にするのもいいでしょう。",
    "duration_sec": 3.5733333333333333
  },
  {
    "index": 240,
    "text": "ステップ3：理解。",
    "group_id": 0,
    "raw_text": "ステップ3：理解。",
    "b_text": "ステップスリー：理解。",
    "duration_sec": 1.8666666666666667
  },
  {
    "index": 241,
    "text": "親の行動の背景を理解しようとしてください。",
    "group_id": 0,
    "raw_text": "親の行動の背景を理解しようとしてください。",
    "b_text": "親の行動の背景を理解しようとしてください。",
    "duration_sec": 3.029333333333333
  },
  {
    "index": 242,
    "text": "批判ではなく理解。",
    "group_id": 0,
    "raw_text": "批判ではなく理解。",
    "b_text": "批判ではなく理解。",
    "duration_sec": 1.3973333333333333
  },
  {
    "index": 243,
    "text": "なぜ親はああなったのか。",
    "group_id": 0,
    "raw_text": "なぜ親はああなったのか。",
    "b_text": "なぜ親はああなったのか。",
    "duration_sec": 1.6853333333333333
  },
  {
    "index": 244,
    "text": "何を経験してきたのか。",
    "group_id": 0,
    "raw_text": "何を経験してきたのか。",
    "b_text": "何を経験してきたのか。",
    "duration_sec": 1.7173333333333334
  },
  {
    "index": 245,
    "text": "これは許しの準備になります。",
    "group_id": 0,
    "raw_text": "これは許しの準備になります。",
    "b_text": "これは許しの準備になります。",
    "duration_sec": 1.9413333333333334
  },
  {
    "index": 246,
    "text": "ステップ4：許し。",
    "group_id": 0,
    "raw_text": "ステップ4：許し。",
    "b_text": "ステップフォー：許し。",
    "duration_sec": 1.9733333333333334
  },
  {
    "index": 247,
    "text": "準備ができたら、許しを考えてください。",
    "group_id": 0,
    "raw_text": "準備ができたら、許しを考えてください。",
    "b_text": "準備ができたら、許しを考えてください。",
    "duration_sec": 3.050666666666667
  },
  {
    "index": 248,
    "text": "許しは一瞬で起きるものではなく、プロセスです。",
    "group_id": 0,
    "raw_text": "許しは一瞬で起きるものではなく、プロセスです。",
    "b_text": "許しは一瞬で起きるものではなく、プロセスです。",
    "duration_sec": 3.456
  },
  {
    "index": 249,
    "text": "少しずつ、手放していく。",
    "group_id": 0,
    "raw_text": "少しずつ、手放していく。",
    "b_text": "少しずつ、手放していく。",
    "duration_sec": 2.272
  },
  {
    "index": 250,
    "text": "自分のペースで構いません。",
    "group_id": 0,
    "raw_text": "自分のペースで構いません。",
    "b_text": "自分のペースで構いません。",
    "duration_sec": 1.8453333333333333
  },
  {
    "index": 251,
    "text": "ステップ5：統合。",
    "group_id": 0,
    "raw_text": "ステップ5：統合。",
    "b_text": "ステップファイブ：統合。",
    "duration_sec": 1.7493333333333334
  },
  {
    "index": 252,
    "text": "経験から学んだことを人生に活かしてください。",
    "group_id": 0,
    "raw_text": "経験から学んだことを人生に活かしてください。",
    "b_text": "経験から学んだことを人生に活かしてください。",
    "duration_sec": 2.976
  },
  {
    "index": 253,
    "text": "傷から得た知恵、強さ、慈悲。",
    "group_id": 0,
    "raw_text": "傷から得た知恵、強さ、慈悲。",
    "b_text": "傷から得た知恵、強さ、慈悲。",
    "duration_sec": 2.944
  },
  {
    "index": 254,
    "text": "これらを世界への貢献に変える。",
    "group_id": 0,
    "raw_text": "これらを世界への貢献に変える。",
    "b_text": "これらを世界への貢献に変える。",
    "duration_sec": 2.144
  },
  {
    "index": 255,
    "text": "ステップ6：前進。",
    "group_id": 0,
    "raw_text": "ステップ6：前進。",
    "b_text": "ステップシックス：前進。",
    "duration_sec": 1.8986666666666667
  },
  {
    "index": 256,
    "text": "過去にしがみつくのをやめ、今と未来に向かってください。",
    "group_id": 0,
    "raw_text": "過去にしがみつくのをやめ、今と未来に向かってください。",
    "b_text": "過去にしがみつくのをやめ、今と未来に向かってください。",
    "duration_sec": 3.712
  },
  {
    "index": 257,
    "text": "過去から学んだ。",
    "group_id": 0,
    "raw_text": "過去から学んだ。",
    "b_text": "過去から学んだ。",
    "duration_sec": 1.152
  },
  {
    "index": 258,
    "text": "それを胸に、新しい章を始める。",
    "group_id": 0,
    "raw_text": "それを胸に、新しい章を始める。",
    "b_text": "それを胸に、新しい章を始める。",
    "duration_sec": 2.7733333333333334
  },
  {
    "index": 259,
    "text": "この動画を見ているあなたには、すでに変化への準備ができています。",
    "group_id": 0,
    "raw_text": "この動画を見ているあなたには、すでに変化への準備ができています。",
    "b_text": "この動画を見ているあなたには、すでに変化への準備ができています。",
    "duration_sec": 4.277333333333333
  },
  {
    "index": 260,
    "text": "そうでなければ、この動画に惹かれなかったでしょう。",
    "group_id": 0,
    "raw_text": "そうでなければ、この動画に惹かれなかったでしょう。",
    "b_text": "そうでなければ、この動画に惹かれなかったでしょう。",
    "duration_sec": 3.2746666666666666
  },
  {
    "index": 261,
    "text": "変化は一日で起きるものではありません。",
    "group_id": 0,
    "raw_text": "変化は一日で起きるものではありません。",
    "b_text": "変化は一日で起きるものではありません。",
    "duration_sec": 2.570666666666667
  },
  {
    "index": 262,
    "text": "しかし、毎日少しずつ意識を向けることで、確実に変わっていきます。",
    "group_id": 0,
    "raw_text": "しかし、毎日少しずつ意識を向けることで、確実に変わっていきます。",
    "b_text": "しかし、毎日少しずつ意識を向けることで、確実に変わっていきます。",
    "duration_sec": 5.269333333333333
  },
  {
    "index": 263,
    "text": "高評価、チャンネル登録をお願いします。",
    "group_id": 0,
    "raw_text": "高評価、チャンネル登録をお願いします。",
    "b_text": "高評価、チャンネル登録をお願いします。",
    "duration_sec": 3.082666666666667
  },
  {
    "index": 264,
    "text": "コメント欄であなたの家族に関する気づきを共有してください。",
    "group_id": 0,
    "raw_text": "コメント欄であなたの家族に関する気づきを共有してください。",
    "b_text": "コメント欄であなたの家族に関する気づきを共有してください。",
    "duration_sec": 3.872
  },
  {
    "index": 265,
    "text": "あなたの経験が、誰かの癒しになるかもしれません。",
    "group_id": 0,
    "raw_text": "あなたの経験が、誰かの癒しになるかもしれません。",
    "b_text": "あなたの経験が、誰かの癒しになるかもしれません。",
    "duration_sec": 3.7333333333333334
  },
  {
    "index": 266,
    "text": "では、またお会いする日まで。",
    "group_id": 0,
    "raw_text": "では、またお会いする日まで。",
    "b_text": "では、またお会いする日まで。",
    "duration_sec": 2.1013333333333333
  },
  {
    "index": 267,
    "text": "過去が癒され、未来が開かれますように。",
    "group_id": 0,
    "raw_text": "過去が癒され、未来が開かれますように。",
    "b_text": "過去が癒され、未来が開かれますように。",
    "duration_sec": 2.944
  },
  {
    "index": 268,
    "text": "魂が選んだ旅が、あなたを光へと導きますように。",
    "group_id": 0,
    "raw_text": "魂が選んだ旅が、あなたを光へと導きますように。",
    "b_text": "魂が選んだ旅が、あなたを光へと導きますように。",
    "duration_sec": 4.010666666666666
  }
]