[
  {
    "index": 0,
    "text": "誰かの正解を読み取ることばかりに意識が向き、自分の言葉が喉で消えていく。",
    "raw_text": "誰かの正解を読み取ることばかりに意識が向き、自分の言葉が喉で消えていく。",
    "b_text": "誰かの正解を読み取ることばかりに意識が向き、自分の言葉が喉で消えていく。"
  },
  {
    "index": 1,
    "text": "場に合わせて笑い、相槌を打ち、帰り道に「今のは自分じゃなかった」とため息をつく。",
    "raw_text": "場に合わせて笑い、相槌を打ち、帰り道に「今のは自分じゃなかった」とため息をつく。",
    "b_text": "場に合わせて笑い、相槌を打ち、帰り道に「今のは自分じゃなかった」とため息をつく。"
  },
  {
    "index": 2,
    "text": "合わせるほど周りには好かれているはずなのに、自分の輪郭だけが薄くなる。",
    "raw_text": "合わせるほど周りには好かれているはずなのに、自分の輪郭だけが薄くなる。",
    "b_text": "合わせるほど周りには好かれているはずなのに、自分の輪郭だけが薄くなる。"
  },
  {
    "index": 3,
    "text": "今日は「周囲に合わせすぎて、自分が透明になる感覚」を扱います。",
    "raw_text": "今日は「周囲に合わせすぎて、自分が透明になる感覚」を扱います。",
    "b_text": "今日は「周囲に合わせすぎて、自分が透明になる感覚」を扱います。"
  },
  {
    "index": 4,
    "text": "合わせる力は大事な技ですが、技が自分を飲み込まないように、軸を持ち直す方法を具体的に探ります。",
    "raw_text": "合わせる力は大事な技ですが、技が自分を飲み込まないように、軸を持ち直す方法を具体的に探ります。",
    "b_text": "合わせる力は大事な技ですが、技が自分を飲み込まないように、軸を持ち直す方法を具体的に探ります。"
  },
  {
    "index": 5,
    "text": "平易な言葉で進めます。",
    "raw_text": "平易な言葉で進めます。",
    "b_text": "平易な言葉で進めます。"
  },
  {
    "index": 6,
    "text": "まず、合わせることは悪ではありません。",
    "raw_text": "まず、合わせることは悪ではありません。",
    "b_text": "まず、合わせることは悪ではありません。"
  },
  {
    "index": 7,
    "text": "空気を読む力は、社会での潤滑油です。",
    "raw_text": "空気を読む力は、社会での潤滑油です。",
    "b_text": "空気を読む力は、社会での潤滑油です。"
  },
  {
    "index": 8,
    "text": "ただ、油を注ぎすぎると、機械の部品が逆に滑って空回りします。",
    "raw_text": "ただ、油を注ぎすぎると、機械の部品が逆に滑って空回りします。",
    "b_text": "ただ、油を注ぎすぎると、機械の部品が逆に滑って空回りします。"
  },
  {
    "index": 9,
    "text": "あなたの内側の声が聞こえないほど注ぎすぎているなら、量を調整する時期です。",
    "raw_text": "あなたの内側の声が聞こえないほど注ぎすぎているなら、量を調整する時期です。",
    "b_text": "あなたの内側の声が聞こえないほど注ぎすぎているなら、量を調整する時期です。"
  },
  {
    "index": 10,
    "text": "合わせる力を技と癖に分けてみてください。",
    "raw_text": "合わせる力を技と癖に分けてみてください。",
    "b_text": "合わせる力を技と癖に分けてみてください。"
  },
  {
    "index": 11,
    "text": "技は意識して使うもの、癖は無意識に出るもの。",
    "raw_text": "技は意識して使うもの、癖は無意識に出るもの。",
    "b_text": "技は意識して使うもの、癖は無意識に出るもの。"
  },
  {
    "index": 12,
    "text": "癖が出たときは、「いま自動で合わせた」と一言心でつぶやく。",
    "raw_text": "癖が出たときは、「いま自動で合わせた」と一言心でつぶやく。",
    "b_text": "癖が出たときは、「いま自動で合わせた」と一言心でつぶやく。"
  },
  {
    "index": 13,
    "text": "気づけば、次に選び直す余地が生まれます。",
    "raw_text": "気づけば、次に選び直す余地が生まれます。",
    "b_text": "気づけば、次に選び直す余地が生まれます。"
  },
  {
    "index": 14,
    "text": "軸を短い言葉にして携帯します。",
    "raw_text": "軸を短い言葉にして携帯します。",
    "b_text": "軸を短い言葉にして携帯します。"
  },
  {
    "index": 15,
    "text": "丁寧に話す正直に伝える静けさを守る「好奇心を優先する」。",
    "raw_text": "丁寧に話す正直に伝える静けさを守る「好奇心を優先する」。",
    "b_text": "丁寧に話す正直に伝える静けさを守る「好奇心を優先する」。"
  },
  {
    "index": 16,
    "text": "四つも要りません。",
    "raw_text": "四つも要りません。",
    "b_text": "四つも要りません。"
  },
  {
    "index": 17,
    "text": "一つで十分です。",
    "raw_text": "一つで十分です。",
    "b_text": "一つで十分です。"
  },
  {
    "index": 18,
    "text": "名刺の裏に書く、スマホのロック画面に設定する。",
    "raw_text": "名刺の裏に書く、スマホのロック画面に設定する。",
    "b_text": "名刺の裏に書く、スマホのロック画面に設定する。"
  },
  {
    "index": 19,
    "text": "軸が目に入ると、場で迷ったときの指針になります。",
    "raw_text": "軸が目に入ると、場で迷ったときの指針になります。",
    "b_text": "軸が目に入ると、場で迷ったときの指針になります。"
  },
  {
    "index": 20,
    "text": "指針があると、全てに合わせなくても怖くなくなります。",
    "raw_text": "指針があると、全てに合わせなくても怖くなくなります。",
    "b_text": "指針があると、全てに合わせなくても怖くなくなります。"
  },
  {
    "index": 21,
    "text": "合わせすぎて飲み込んだ言葉は、どこかに残っています。",
    "raw_text": "合わせすぎて飲み込んだ言葉は、どこかに残っています。",
    "b_text": "合わせすぎて飲み込んだ言葉は、どこかに残っています。"
  },
  {
    "index": 22,
    "text": "日記に一行でいいので「今日はこれを飲み込んだ」と書く。",
    "raw_text": "日記に一行でいいので「今日はこれを飲み込んだ」と書く。",
    "b_text": "日記に一行でいいので「今日はこれを飲み込んだ」と書く。"
  },
  {
    "index": 23,
    "text": "誰かへの不満ではなく、自分が選ばなかった選択を書き残す。",
    "raw_text": "誰かへの不満ではなく、自分が選ばなかった選択を書き残す。",
    "b_text": "誰かへの不満ではなく、自分が選ばなかった選択を書き残す。"
  },
  {
    "index": 24,
    "text": "書くと、飲み込んだ言葉が外に出て、輪郭が少し戻ります。",
    "raw_text": "書くと、飲み込んだ言葉が外に出て、輪郭が少し戻ります。",
    "b_text": "書くと、飲み込んだ言葉が外に出て、輪郭が少し戻ります。"
  },
  {
    "index": 25,
    "text": "戻った輪郭は、次に出せる言葉の貯金になります。",
    "raw_text": "戻った輪郭は、次に出せる言葉の貯金になります。",
    "b_text": "戻った輪郭は、次に出せる言葉の貯金になります。"
  },
  {
    "index": 26,
    "text": "周囲の期待を想像で膨らませると、必要以上に合わせます。",
    "raw_text": "周囲の期待を想像で膨らませると、必要以上に合わせます。",
    "b_text": "周囲の期待を想像で膨らませると、必要以上に合わせます。"
  },
  {
    "index": 27,
    "text": "実際に何が求められているかを短く確認する習慣を持つ。",
    "raw_text": "実際に何が求められているかを短く確認する習慣を持つ。",
    "b_text": "実際に何が求められているかを短く確認する習慣を持つ。"
  },
  {
    "index": 28,
    "text": "「今回は何が一番大事ですか」「どの範囲まで必要ですか」。",
    "raw_text": "「今回は何が一番大事ですか」「どの範囲まで必要ですか」。",
    "b_text": "「今回は何が一番大事ですか」「どの範囲まで必要ですか」。"
  },
  {
    "index": 29,
    "text": "聞いてみると、想像より軽いことが多い。",
    "raw_text": "聞いてみると、想像より軽いことが多い。",
    "b_text": "聞いてみると、想像より軽いことが多い。"
  },
  {
    "index": 30,
    "text": "軽さを知れば、削る自分の量も減ります。",
    "raw_text": "軽さを知れば、削る自分の量も減ります。",
    "b_text": "軽さを知れば、削る自分の量も減ります。"
  },
  {
    "index": 31,
    "text": "頭の中で鳴り続けるこうあるべきの声は、放っておくと音量が上がります。",
    "raw_text": "頭の中で鳴り続けるこうあるべきの声は、放っておくと音量が上がります。",
    "b_text": "頭の中で鳴り続けるこうあるべきの声は、放っておくと音量が上がります。"
  },
  {
    "index": 32,
    "text": "鳴った瞬間に、誰の声かをラベルづけする。",
    "raw_text": "鳴った瞬間に、誰の声かをラベルづけする。",
    "b_text": "鳴った瞬間に、誰の声かをラベルづけする。"
  },
  {
    "index": 33,
    "text": "親の声か、過去の上司の声か、世間の声か。",
    "raw_text": "親の声か、過去の上司の声か、世間の声か。",
    "b_text": "親の声か、過去の上司の声か、世間の声か。"
  },
  {
    "index": 34,
    "text": "ラベルが貼れれば、距離ができます。",
    "raw_text": "ラベルが貼れれば、距離ができます。",
    "b_text": "ラベルが貼れれば、距離ができます。"
  },
  {
    "index": 35,
    "text": "距離ができれば、音量を下げられます。",
    "raw_text": "距離ができれば、音量を下げられます。",
    "b_text": "距離ができれば、音量を下げられます。"
  },
  {
    "index": 36,
    "text": "下げるとは、別の行動を選ぶことです。",
    "raw_text": "下げるとは、別の行動を選ぶことです。",
    "b_text": "下げるとは、別の行動を選ぶことです。"
  },
  {
    "index": 37,
    "text": "選び直した回数が、あなたの自由の証拠になります。",
    "raw_text": "選び直した回数が、あなたの自由の証拠になります。",
    "b_text": "選び直した回数が、あなたの自由の証拠になります。"
  },
  {
    "index": 38,
    "text": "演じること自体は悪ではありません。",
    "raw_text": "演じること自体は悪ではありません。",
    "b_text": "演じること自体は悪ではありません。"
  },
  {
    "index": 39,
    "text": "役割に合わせて演じるのは、社会の中で生きる技です。",
    "raw_text": "役割に合わせて演じるのは、社会の中で生きる技です。",
    "b_text": "役割に合わせて演じるのは、社会の中で生きる技です。"
  },
  {
    "index": 40,
    "text": "ただ、演じっぱなしだと疲弊します。",
    "raw_text": "ただ、演じっぱなしだと疲弊します。",
    "b_text": "ただ、演じっぱなしだと疲弊します。"
  },
  {
    "index": 41,
    "text": "演じた後は必ず素の時間を入れる。",
    "raw_text": "演じた後は必ず素の時間を入れる。",
    "b_text": "演じた後は必ず素の時間を入れる。"
  },
  {
    "index": 42,
    "text": "好きな音楽を聴き、誰にも見せないノートに雑記を書く。",
    "raw_text": "好きな音楽を聴き、誰にも見せないノートに雑記を書く。",
    "b_text": "好きな音楽を聴き、誰にも見せないノートに雑記を書く。"
  },
  {
    "index": 43,
    "text": "信頼できる一人に、今日の本音を一言だけ話す。",
    "raw_text": "信頼できる一人に、今日の本音を一言だけ話す。",
    "b_text": "信頼できる一人に、今日の本音を一言だけ話す。"
  },
  {
    "index": 44,
    "text": "戻る場所があると、演じることが負担ではなくなります。",
    "raw_text": "戻る場所があると、演じることが負担ではなくなります。",
    "b_text": "戻る場所があると、演じることが負担ではなくなります。"
  },
  {
    "index": 45,
    "text": "断ることへの怖さが、合わせすぎを加速させます。",
    "raw_text": "断ることへの怖さが、合わせすぎを加速させます。",
    "b_text": "断ることへの怖さが、合わせすぎを加速させます。"
  },
  {
    "index": 46,
    "text": "小さなノーの練習を始めます。",
    "raw_text": "小さなノーの練習を始めます。",
    "b_text": "小さなノーの練習を始めます。"
  },
  {
    "index": 47,
    "text": "「今日は時間が足りません」「今回は別の人が適任だと思います」。",
    "raw_text": "「今日は時間が足りません」「今回は別の人が適任だと思います」。",
    "b_text": "「今日は時間が足りません」「今回は別の人が適任だと思います」。"
  },
  {
    "index": 48,
    "text": "短く、理由は一言で。",
    "raw_text": "短く、理由は一言で。",
    "b_text": "短く、理由は一言で。"
  },
  {
    "index": 49,
    "text": "ノーを一度言えれば、次も言えます。",
    "raw_text": "ノーを一度言えれば、次も言えます。",
    "b_text": "ノーを一度言えれば、次も言えます。"
  },
  {
    "index": 50,
    "text": "ノーは、輪郭を守る線です。",
    "raw_text": "ノーは、輪郭を守る線です。",
    "b_text": "ノーは、輪郭を守る線です。"
  },
  {
    "index": 51,
    "text": "その線が引ければ、はいの重みも軽くなります。",
    "raw_text": "その線が引ければ、はいの重みも軽くなります。",
    "b_text": "その線が引ければ、はいの重みも軽くなります。"
  },
  {
    "index": 52,
    "text": "体が固いと、心はさらに合わせに走ります。",
    "raw_text": "体が固いと、心はさらに合わせに走ります。",
    "b_text": "体が固いと、心はさらに合わせに走ります。"
  },
  {
    "index": 53,
    "text": "肩を下げ、足裏を床に押し、深く息を吐く。",
    "raw_text": "肩を下げ、足裏を床に押し、深く息を吐く。",
    "b_text": "肩を下げ、足裏を床に押し、深く息を吐く。"
  },
  {
    "index": 54,
    "text": "視線を少し外に広げ、窓の外の空を見る。",
    "raw_text": "視線を少し外に広げ、窓の外の空を見る。",
    "b_text": "視線を少し外に広げ、窓の外の空を見る。"
  },
  {
    "index": 55,
    "text": "体の緊張がほどけると、合わせる以外の選択肢が見えます。",
    "raw_text": "体の緊張がほどけると、合わせる以外の選択肢が見えます。",
    "b_text": "体の緊張がほどけると、合わせる以外の選択肢が見えます。"
  },
  {
    "index": 56,
    "text": "見えれば、選べます。",
    "raw_text": "見えれば、選べます。",
    "b_text": "見えれば、選べます。"
  },
  {
    "index": 57,
    "text": "他者の視線を完全に消すことはできませんが、視線の強度は調整できます。",
    "raw_text": "他者の視線を完全に消すことはできませんが、視線の強度は調整できます。",
    "b_text": "他者の視線を完全に消すことはできませんが、視線の強度は調整できます。"
  },
  {
    "index": 58,
    "text": "見る人の数を減らし、質を上げる。",
    "raw_text": "見る人の数を減らし、質を上げる。",
    "b_text": "見る人の数を減らし、質を上げる。"
  },
  {
    "index": 59,
    "text": "信頼できる少数の人と深く関われば、不特定多数の期待に合わせる必要が減ります。",
    "raw_text": "信頼できる少数の人と深く関われば、不特定多数の期待に合わせる必要が減ります。",
    "b_text": "信頼できる少数の人と深く関われば、不特定多数の期待に合わせる必要が減ります。"
  },
  {
    "index": 60,
    "text": "サルトルは他者の視線が自由を脅かすと語りましたが、視線を選ぶことで、脅威は弱まります。",
    "raw_text": "サルトルは他者の視線が自由を脅かすと語りましたが、視線を選ぶことで、脅威は弱まります。",
    "b_text": "サルトルは他者の視線が自由を脅かすと語りましたが、視線を選ぶことで、脅威は弱まります。"
  },
  {
    "index": 61,
    "text": "心理学では、自己一致が心の安定を支えるとされています。",
    "raw_text": "心理学では、自己一致が心の安定を支えるとされています。",
    "b_text": "心理学では、自己一致が心の安定を支えるとされています。"
  },
  {
    "index": 62,
    "text": "内側と外側が近いほど、揺れが小さくなります。",
    "raw_text": "内側と外側が近いほど、揺れが小さくなります。",
    "b_text": "内側と外側が近いほど、揺れが小さくなります。"
  },
  {
    "index": 63,
    "text": "分からないときに分からないと言う、無理なときに無理だと言う。",
    "raw_text": "分からないときに分からないと言う、無理なときに無理だと言う。",
    "b_text": "分からないときに分からないと言う、無理なときに無理だと言う。"
  },
  {
    "index": 64,
    "text": "短い正直さを積むと、自己一致が増え、合わせすぎが減ります。",
    "raw_text": "短い正直さを積むと、自己一致が増え、合わせすぎが減ります。",
    "b_text": "短い正直さを積むと、自己一致が増え、合わせすぎが減ります。"
  },
  {
    "index": 65,
    "text": "合わせる人ほど、自分の強みを見落とします。",
    "raw_text": "合わせる人ほど、自分の強みを見落とします。",
    "b_text": "合わせる人ほど、自分の強みを見落とします。"
  },
  {
    "index": 66,
    "text": "聞く力、まとめる力、空気の流れを読む力、静かに支える力。",
    "raw_text": "聞く力、まとめる力、空気の流れを読む力、静かに支える力。",
    "b_text": "聞く力、まとめる力、空気の流れを読む力、静かに支える力。"
  },
  {
    "index": 67,
    "text": "強みを一つだけ意識して場に持ち込む。",
    "raw_text": "強みを一つだけ意識して場に持ち込む。",
    "b_text": "強みを一つだけ意識して場に持ち込む。"
  },
  {
    "index": 68,
    "text": "強みを使っている実感があれば、「ただ合わせているだけ」という感覚が薄れます。",
    "raw_text": "強みを使っている実感があれば、「ただ合わせているだけ」という感覚が薄れます。",
    "b_text": "強みを使っている実感があれば、「ただ合わせているだけ」という感覚が薄れます。"
  },
  {
    "index": 69,
    "text": "薄れれば、疲労も減ります。",
    "raw_text": "薄れれば、疲労も減ります。",
    "b_text": "薄れれば、疲労も減ります。"
  },
  {
    "index": 70,
    "text": "誰にも合わせない時間を意図して作ります。",
    "raw_text": "誰にも合わせない時間を意図して作ります。",
    "b_text": "誰にも合わせない時間を意図して作ります。"
  },
  {
    "index": 71,
    "text": "スマホを閉じ、静かな場所に座り、好きな香りや音に身を置く。",
    "raw_text": "スマホを閉じ、静かな場所に座り、好きな香りや音に身を置く。",
    "b_text": "スマホを閉じ、静かな場所に座り、好きな香りや音に身を置く。"
  },
  {
    "index": 72,
    "text": "誰にも見せない時間は、内側の声を回復させます。",
    "raw_text": "誰にも見せない時間は、内側の声を回復させます。",
    "b_text": "誰にも見せない時間は、内側の声を回復させます。"
  },
  {
    "index": 73,
    "text": "回復した声が、次に外に出たときの芯になります。",
    "raw_text": "回復した声が、次に外に出たときの芯になります。",
    "b_text": "回復した声が、次に外に出たときの芯になります。"
  },
  {
    "index": 74,
    "text": "完璧を目指すと、合わせ続ける罠に陥ります。",
    "raw_text": "完璧を目指すと、合わせ続ける罠に陥ります。",
    "b_text": "完璧を目指すと、合わせ続ける罠に陥ります。"
  },
  {
    "index": 75,
    "text": "完璧は終わりがなく、他人の期待も無限です。",
    "raw_text": "完璧は終わりがなく、他人の期待も無限です。",
    "b_text": "完璧は終わりがなく、他人の期待も無限です。"
  },
  {
    "index": 76,
    "text": "完璧の代わりに十分を目指します。",
    "raw_text": "完璧の代わりに十分を目指します。",
    "b_text": "完璧の代わりに十分を目指します。"
  },
  {
    "index": 77,
    "text": "目的に対して十分かどうかで線を引き、「ここまでで良し」と自分に言う。",
    "raw_text": "目的に対して十分かどうかで線を引き、「ここまでで良し」と自分に言う。",
    "b_text": "目的に対して十分かどうかで線を引き、「ここまでで良し」と自分に言う。"
  },
  {
    "index": 78,
    "text": "十分で止めると、余白が残ります。",
    "raw_text": "十分で止めると、余白が残ります。",
    "b_text": "十分で止めると、余白が残ります。"
  },
  {
    "index": 79,
    "text": "余白は、自分の声が呼吸する場所です。",
    "raw_text": "余白は、自分の声が呼吸する場所です。",
    "b_text": "余白は、自分の声が呼吸する場所です。"
  },
  {
    "index": 80,
    "text": "軸は固定ではありません。",
    "raw_text": "軸は固定ではありません。",
    "b_text": "軸は固定ではありません。"
  },
  {
    "index": 81,
    "text": "今の自分に合う軸を仮で置き、合わなければ変える。",
    "raw_text": "今の自分に合う軸を仮で置き、合わなければ変える。",
    "b_text": "今の自分に合う軸を仮で置き、合わなければ変える。"
  },
  {
    "index": 82,
    "text": "仮の軸があると、毎回ゼロから悩まずに済みます。",
    "raw_text": "仮の軸があると、毎回ゼロから悩まずに済みます。",
    "b_text": "仮の軸があると、毎回ゼロから悩まずに済みます。"
  },
  {
    "index": 83,
    "text": "悩むエネルギーが減れば、合わせるか合わせないかを落ち着いて選べます。",
    "raw_text": "悩むエネルギーが減れば、合わせるか合わせないかを落ち着いて選べます。",
    "b_text": "悩むエネルギーが減れば、合わせるか合わせないかを落ち着いて選べます。"
  },
  {
    "index": 84,
    "text": "ここから、日常の流れに組み込む具体を重ねます。",
    "raw_text": "ここから、日常の流れに組み込む具体を重ねます。",
    "b_text": "ここから、日常の流れに組み込む具体を重ねます。"
  },
  {
    "index": 85,
    "text": "朝、鏡の前で軸を一言だけ口に出す。",
    "raw_text": "朝、鏡の前で軸を一言だけ口に出す。",
    "b_text": "朝、鏡の前で軸を一言だけ口に出す。"
  },
  {
    "index": 86,
    "text": "「今日は丁寧に話す」「今日は正直に言う」。",
    "raw_text": "「今日は丁寧に話す」「今日は正直に言う」。",
    "b_text": "「今日は丁寧に話す」「今日は正直に言う」。"
  },
  {
    "index": 87,
    "text": "声にすると、頭の中の言葉より強く記憶に残ります。",
    "raw_text": "声にすると、頭の中の言葉より強く記憶に残ります。",
    "b_text": "声にすると、頭の中の言葉より強く記憶に残ります。"
  },
  {
    "index": 88,
    "text": "通勤中に、今日の場面で飲み込みそうな言葉を一つ想像し、どう出すかを決めておく。",
    "raw_text": "通勤中に、今日の場面で飲み込みそうな言葉を一つ想像し、どう出すかを決めておく。",
    "b_text": "通勤中に、今日の場面で飲み込みそうな言葉を一つ想像し、どう出すかを決めておく。"
  },
  {
    "index": 89,
    "text": "決めておけば、場で迷う時間が減ります。",
    "raw_text": "決めておけば、場で迷う時間が減ります。",
    "b_text": "決めておけば、場で迷う時間が減ります。"
  },
  {
    "index": 90,
    "text": "昼、短いチェックインを入れます。",
    "raw_text": "昼、短いチェックインを入れます。",
    "b_text": "昼、短いチェックインを入れます。"
  },
  {
    "index": 91,
    "text": "今、自分の声が聞こえているか。",
    "raw_text": "今、自分の声が聞こえているか。",
    "b_text": "今、自分の声が聞こえているか。"
  },
  {
    "index": 92,
    "text": "どこかで自動で合わせていないか。",
    "raw_text": "どこかで自動で合わせていないか。",
    "b_text": "どこかで自動で合わせていないか。"
  },
  {
    "index": 93,
    "text": "気づいたら、一つだけ自分の選択を挟む。",
    "raw_text": "気づいたら、一つだけ自分の選択を挟む。",
    "b_text": "気づいたら、一つだけ自分の選択を挟む。"
  },
  {
    "index": 94,
    "text": "昼ご飯の店を自分で選ぶ、会話で一文だけ本音を言う。",
    "raw_text": "昼ご飯の店を自分で選ぶ、会話で一文だけ本音を言う。",
    "b_text": "昼ご飯の店を自分で選ぶ、会話で一文だけ本音を言う。"
  },
  {
    "index": 95,
    "text": "小さな選択が、午後の輪郭を太くします。",
    "raw_text": "小さな選択が、午後の輪郭を太くします。",
    "b_text": "小さな選択が、午後の輪郭を太くします。"
  },
  {
    "index": 96,
    "text": "夕方、消耗していると感じたら、五分だけ目を閉じて呼吸を整える。",
    "raw_text": "夕方、消耗していると感じたら、五分だけ目を閉じて呼吸を整える。",
    "b_text": "夕方、消耗していると感じたら、五分だけ目を閉じて呼吸を整える。"
  },
  {
    "index": 97,
    "text": "合わせすぎているとき、呼吸は浅くなっています。",
    "raw_text": "合わせすぎているとき、呼吸は浅くなっています。",
    "b_text": "合わせすぎているとき、呼吸は浅くなっています。"
  },
  {
    "index": 98,
    "text": "呼吸を深くするだけで、脳の警戒が下がり、内側の声が戻りやすくなります。",
    "raw_text": "呼吸を深くするだけで、脳の警戒が下がり、内側の声が戻りやすくなります。",
    "b_text": "呼吸を深くするだけで、脳の警戒が下がり、内側の声が戻りやすくなります。"
  },
  {
    "index": 99,
    "text": "戻った声を、一言メモに残す。",
    "raw_text": "戻った声を、一言メモに残す。",
    "b_text": "戻った声を、一言メモに残す。"
  },
  {
    "index": 100,
    "text": "夜、今日飲み込んだ言葉と、出せた本音を一行ずつ書く。",
    "raw_text": "夜、今日飲み込んだ言葉と、出せた本音を一行ずつ書く。",
    "b_text": "夜、今日飲み込んだ言葉と、出せた本音を一行ずつ書く。"
  },
  {
    "index": 101,
    "text": "飲み込んだ理由も一行添える。",
    "raw_text": "飲み込んだ理由も一行添える。",
    "b_text": "飲み込んだ理由も一行添える。"
  },
  {
    "index": 102,
    "text": "書き残した事実は、翌日に生かせる素材です。",
    "raw_text": "書き残した事実は、翌日に生かせる素材です。",
    "b_text": "書き残した事実は、翌日に生かせる素材です。"
  },
  {
    "index": 103,
    "text": "素材が増えるほど、合わせるかどうかを意図的に選べる回数が増えます。",
    "raw_text": "素材が増えるほど、合わせるかどうかを意図的に選べる回数が増えます。",
    "b_text": "素材が増えるほど、合わせるかどうかを意図的に選べる回数が増えます。"
  },
  {
    "index": 104,
    "text": "職場や友人の中で、安心して本音を出せる人を二人だけ思い浮かべます。",
    "raw_text": "職場や友人の中で、安心して本音を出せる人を二人だけ思い浮かべます。",
    "b_text": "職場や友人の中で、安心して本音を出せる人を二人だけ思い浮かべます。"
  },
  {
    "index": 105,
    "text": "二人で十分です。",
    "raw_text": "二人で十分です。",
    "b_text": "二人で十分です。"
  },
  {
    "index": 106,
    "text": "その人たちに、短く感想や本音を送る習慣を持つ。",
    "raw_text": "その人たちに、短く感想や本音を送る習慣を持つ。",
    "b_text": "その人たちに、短く感想や本音を送る習慣を持つ。"
  },
  {
    "index": 107,
    "text": "小さく出す場があると、他の場で飲み込む回数が減ります。",
    "raw_text": "小さく出す場があると、他の場で飲み込む回数が減ります。",
    "b_text": "小さく出す場があると、他の場で飲み込む回数が減ります。"
  },
  {
    "index": 108,
    "text": "服や持ち物にも、自分の声を混ぜます。",
    "raw_text": "服や持ち物にも、自分の声を混ぜます。",
    "b_text": "服や持ち物にも、自分の声を混ぜます。"
  },
  {
    "index": 109,
    "text": "色、質感、香り。",
    "raw_text": "色、質感、香り。",
    "b_text": "色、質感、香り。"
  },
  {
    "index": 110,
    "text": "小さな部分でも自分の選んだものを身につけると、外側の圧が全て他人のものではなくなります。",
    "raw_text": "小さな部分でも自分の選んだものを身につけると、外側の圧が全て他人のものではなくなります。",
    "b_text": "小さな部分でも自分の選んだものを身につけると、外側の圧が全て他人のものではなくなります。"
  },
  {
    "index": 111,
    "text": "物理的な輪郭が整うと、心の輪郭も思い出しやすくなります。",
    "raw_text": "物理的な輪郭が整うと、心の輪郭も思い出しやすくなります。",
    "b_text": "物理的な輪郭が整うと、心の輪郭も思い出しやすくなります。"
  },
  {
    "index": 112,
    "text": "自分に貼られたラベルも見直します。",
    "raw_text": "自分に貼られたラベルも見直します。",
    "b_text": "自分に貼られたラベルも見直します。"
  },
  {
    "index": 113,
    "text": "聞き役調整役いい人。",
    "raw_text": "聞き役調整役いい人。",
    "b_text": "聞き役調整役いい人。"
  },
  {
    "index": 114,
    "text": "役は便利ですが、貼りっぱなしだと身動きが取れなくなります。",
    "raw_text": "役は便利ですが、貼りっぱなしだと身動きが取れなくなります。",
    "b_text": "役は便利ですが、貼りっぱなしだと身動きが取れなくなります。"
  },
  {
    "index": 115,
    "text": "今日は別の役を一つだけ試す。",
    "raw_text": "今日は別の役を一つだけ試す。",
    "b_text": "今日は別の役を一つだけ試す。"
  },
  {
    "index": 116,
    "text": "提案する人「問いを投げる人」。",
    "raw_text": "提案する人「問いを投げる人」。",
    "b_text": "提案する人「問いを投げる人」。"
  },
  {
    "index": 117,
    "text": "役を変えると、他人の期待も変わり、合わせる形も変えられます。",
    "raw_text": "役を変えると、他人の期待も変わり、合わせる形も変えられます。",
    "b_text": "役を変えると、他人の期待も変わり、合わせる形も変えられます。"
  },
  {
    "index": 118,
    "text": "文化や時代が作るこうあるべきにも気づきます。",
    "raw_text": "文化や時代が作るこうあるべきにも気づきます。",
    "b_text": "文化や時代が作るこうあるべきにも気づきます。"
  },
  {
    "index": 119,
    "text": "集団の中では、目に見えないルールが動いています。",
    "raw_text": "集団の中では、目に見えないルールが動いています。",
    "b_text": "集団の中では、目に見えないルールが動いています。"
  },
  {
    "index": 120,
    "text": "ルールに気づくだけで、飲み込まれずに距離を取ることができます。",
    "raw_text": "ルールに気づくだけで、飲み込まれずに距離を取ることができます。",
    "b_text": "ルールに気づくだけで、飲み込まれずに距離を取ることができます。"
  },
  {
    "index": 121,
    "text": "「これはこの集団特有のルールだ」と自覚する。",
    "raw_text": "「これはこの集団特有のルールだ」と自覚する。",
    "b_text": "「これはこの集団特有のルールだ」と自覚する。"
  },
  {
    "index": 122,
    "text": "自覚すれば、選択が生まれます。",
    "raw_text": "自覚すれば、選択が生まれます。",
    "b_text": "自覚すれば、選択が生まれます。"
  },
  {
    "index": 123,
    "text": "哲学では、他者と向き合うときに本来的な自分と世俗的な自分が揺れると言われます。",
    "raw_text": "哲学では、他者と向き合うときに本来的な自分と世俗的な自分が揺れると言われます。",
    "b_text": "哲学では、他者と向き合うときに本来的な自分と世俗的な自分が揺れると言われます。"
  },
  {
    "index": 124,
    "text": "ハイデガーの言う「世人の中に沈む」状態から抜け出すには、静かな場所で自分に立ち返る時間が欠かせません。",
    "raw_text": "ハイデガーの言う「世人の中に沈む」状態から抜け出すには、静かな場所で自分に立ち返る時間が欠かせません。",
    "b_text": "ハイデガーの言う「世人の中に沈む」状態から抜け出すには、静かな場所で自分に立ち返る時間が欠かせません。"
  },
  {
    "index": 125,
    "text": "静寂は、軸を見つけるための道具です。",
    "raw_text": "静寂は、軸を見つけるための道具です。",
    "b_text": "静寂は、軸を見つけるための道具です。"
  },
  {
    "index": 126,
    "text": "静けさをスケジュールに入れる。",
    "raw_text": "静けさをスケジュールに入れる。",
    "b_text": "静けさをスケジュールに入れる。"
  },
  {
    "index": 127,
    "text": "予定として確保すれば、罪悪感なく休めます。",
    "raw_text": "予定として確保すれば、罪悪感なく休めます。",
    "b_text": "予定として確保すれば、罪悪感なく休めます。"
  },
  {
    "index": 128,
    "text": "心理学では、ウィニコットが偽りの自己と真の自己を論じました。",
    "raw_text": "心理学では、ウィニコットが偽りの自己と真の自己を論じました。",
    "b_text": "心理学では、ウィニコットが偽りの自己と真の自己を論じました。"
  },
  {
    "index": 129,
    "text": "偽りの自己は周囲に合わせるために作られ、真の自己は内側の欲求に根ざします。",
    "raw_text": "偽りの自己は周囲に合わせるために作られ、真の自己は内側の欲求に根ざします。",
    "b_text": "偽りの自己は周囲に合わせるために作られ、真の自己は内側の欲求に根ざします。"
  },
  {
    "index": 130,
    "text": "偽りの自己が全て悪ではありませんが、真の自己と交代で呼吸させる必要があります。",
    "raw_text": "偽りの自己が全て悪ではありませんが、真の自己と交代で呼吸させる必要があります。",
    "b_text": "偽りの自己が全て悪ではありませんが、真の自己と交代で呼吸させる必要があります。"
  },
  {
    "index": 131,
    "text": "交代を意識的に行えば、どちらも枯れません。",
    "raw_text": "交代を意識的に行えば、どちらも枯れません。",
    "b_text": "交代を意識的に行えば、どちらも枯れません。"
  },
  {
    "index": 132,
    "text": "誰かに合わせすぎたと感じたら、後からでも一言だけフォローを入れる。",
    "raw_text": "誰かに合わせすぎたと感じたら、後からでも一言だけフォローを入れる。",
    "b_text": "誰かに合わせすぎたと感じたら、後からでも一言だけフォローを入れる。"
  },
  {
    "index": 133,
    "text": "「さっきはこう思っていた」と短く伝える。",
    "raw_text": "「さっきはこう思っていた」と短く伝える。",
    "b_text": "「さっきはこう思っていた」と短く伝える。"
  },
  {
    "index": 134,
    "text": "後出しでも、本音を出せた事実が残ります。",
    "raw_text": "後出しでも、本音を出せた事実が残ります。",
    "b_text": "後出しでも、本音を出せた事実が残ります。"
  },
  {
    "index": 135,
    "text": "事実が一つ増えれば、次に出すハードルが下がります。",
    "raw_text": "事実が一つ増えれば、次に出すハードルが下がります。",
    "b_text": "事実が一つ増えれば、次に出すハードルが下がります。"
  },
  {
    "index": 136,
    "text": "「今日は合わせない」と決める日を作ります。",
    "raw_text": "「今日は合わせない」と決める日を作ります。",
    "b_text": "「今日は合わせない」と決める日を作ります。"
  },
  {
    "index": 137,
    "text": "誰にも会わず、一人で歩き、一人で考える。",
    "raw_text": "誰にも会わず、一人で歩き、一人で考える。",
    "b_text": "誰にも会わず、一人で歩き、一人で考える。"
  },
  {
    "index": 138,
    "text": "合わせない日があると、合わせる日の負担が軽くなります。",
    "raw_text": "合わせない日があると、合わせる日の負担が軽くなります。",
    "b_text": "合わせない日があると、合わせる日の負担が軽くなります。"
  },
  {
    "index": 139,
    "text": "軽くなれば、意図的に合わせることも、意図的に合わせないことも、自由に選べます。",
    "raw_text": "軽くなれば、意図的に合わせることも、意図的に合わせないことも、自由に選べます。",
    "b_text": "軽くなれば、意図的に合わせることも、意図的に合わせないことも、自由に選べます。"
  },
  {
    "index": 140,
    "text": "体のサインを記録します。",
    "raw_text": "体のサインを記録します。",
    "b_text": "体のサインを記録します。"
  },
  {
    "index": 141,
    "text": "肩が固まる場、息が浅くなる場、逆に肩がゆるむ場、深く息ができる場。",
    "raw_text": "肩が固まる場、息が浅くなる場、逆に肩がゆるむ場、深く息ができる場。",
    "b_text": "肩が固まる場、息が浅くなる場、逆に肩がゆるむ場、深く息ができる場。"
  },
  {
    "index": 142,
    "text": "体は正直です。",
    "raw_text": "体は正直です。",
    "b_text": "体は正直です。"
  },
  {
    "index": 143,
    "text": "サインを場所や人と紐づけておくと、どこで合わせすぎているかが見えます。",
    "raw_text": "サインを場所や人と紐づけておくと、どこで合わせすぎているかが見えます。",
    "b_text": "サインを場所や人と紐づけておくと、どこで合わせすぎているかが見えます。"
  },
  {
    "index": 144,
    "text": "見えれば、避けたり時間を短くしたりできます。",
    "raw_text": "見えれば、避けたり時間を短くしたりできます。",
    "b_text": "見えれば、避けたり時間を短くしたりできます。"
  },
  {
    "index": 145,
    "text": "一日の終わりに、今日の自分に題名をつけます。",
    "raw_text": "一日の終わりに、今日の自分に題名をつけます。",
    "b_text": "一日の終わりに、今日の自分に題名をつけます。"
  },
  {
    "index": 146,
    "text": "「静かな反逆の日」「一言だけ本音の日」「軸を思い出した日」。",
    "raw_text": "「静かな反逆の日」「一言だけ本音の日」「軸を思い出した日」。",
    "b_text": "「静かな反逆の日」「一言だけ本音の日」「軸を思い出した日」。"
  },
  {
    "index": 147,
    "text": "題名は物語の表紙になります。",
    "raw_text": "題名は物語の表紙になります。",
    "b_text": "題名は物語の表紙になります。"
  },
  {
    "index": 148,
    "text": "表紙が並ぶと、自分がどの方向に歩いているかが見えます。",
    "raw_text": "表紙が並ぶと、自分がどの方向に歩いているかが見えます。",
    "b_text": "表紙が並ぶと、自分がどの方向に歩いているかが見えます。"
  },
  {
    "index": 149,
    "text": "見えれば、合わせすぎの道から少し外れる勇気が出ます。",
    "raw_text": "見えれば、合わせすぎの道から少し外れる勇気が出ます。",
    "b_text": "見えれば、合わせすぎの道から少し外れる勇気が出ます。"
  },
  {
    "index": 150,
    "text": "視線を外す場所を決めておきます。",
    "raw_text": "視線を外す場所を決めておきます。",
    "b_text": "視線を外す場所を決めておきます。"
  },
  {
    "index": 151,
    "text": "会議なら窓の外の木、カフェなら隣のテーブルの花。",
    "raw_text": "会議なら窓の外の木、カフェなら隣のテーブルの花。",
    "b_text": "会議なら窓の外の木、カフェなら隣のテーブルの花。"
  },
  {
    "index": 152,
    "text": "視線を一瞬外に置き、戻す。",
    "raw_text": "視線を一瞬外に置き、戻す。",
    "b_text": "視線を一瞬外に置き、戻す。"
  },
  {
    "index": 153,
    "text": "視線のリセットは、心のリセットです。",
    "raw_text": "視線のリセットは、心のリセットです。",
    "b_text": "視線のリセットは、心のリセットです。"
  },
  {
    "index": 154,
    "text": "リセットできると知っていると、他人の視線に飲まれにくくなります。",
    "raw_text": "リセットできると知っていると、他人の視線に飲まれにくくなります。",
    "b_text": "リセットできると知っていると、他人の視線に飲まれにくくなります。"
  },
  {
    "index": 155,
    "text": "言葉の速度も調整します。",
    "raw_text": "言葉の速度も調整します。",
    "b_text": "言葉の速度も調整します。"
  },
  {
    "index": 156,
    "text": "早口になると、自分の声が追いつかず、周囲に流されます。",
    "raw_text": "早口になると、自分の声が追いつかず、周囲に流されます。",
    "b_text": "早口になると、自分の声が追いつかず、周囲に流されます。"
  },
  {
    "index": 157,
    "text": "語尾まで息を残し、ゆっくり話す。",
    "raw_text": "語尾まで息を残し、ゆっくり話す。",
    "b_text": "語尾まで息を残し、ゆっくり話す。"
  },
  {
    "index": 158,
    "text": "ゆっくり話せば、言葉を選ぶ余裕ができます。",
    "raw_text": "ゆっくり話せば、言葉を選ぶ余裕ができます。",
    "b_text": "ゆっくり話せば、言葉を選ぶ余裕ができます。"
  },
  {
    "index": 159,
    "text": "余裕ができれば、自分の言葉を差し込めます。",
    "raw_text": "余裕ができれば、自分の言葉を差し込めます。",
    "b_text": "余裕ができれば、自分の言葉を差し込めます。"
  },
  {
    "index": 160,
    "text": "小さな反逆を日常に入れます。",
    "raw_text": "小さな反逆を日常に入れます。",
    "b_text": "小さな反逆を日常に入れます。"
  },
  {
    "index": 161,
    "text": "いつもの道を一本変える、いつもの飲み物を別にする、いつも座る席を変える。",
    "raw_text": "いつもの道を一本変える、いつもの飲み物を別にする、いつも座る席を変える。",
    "b_text": "いつもの道を一本変える、いつもの飲み物を別にする、いつも座る席を変える。"
  },
  {
    "index": 162,
    "text": "小さな反逆は、選ぶ感覚を思い出させます。",
    "raw_text": "小さな反逆は、選ぶ感覚を思い出させます。",
    "b_text": "小さな反逆は、選ぶ感覚を思い出させます。"
  },
  {
    "index": 163,
    "text": "思い出した感覚が、場でも役立ちます。",
    "raw_text": "思い出した感覚が、場でも役立ちます。",
    "b_text": "思い出した感覚が、場でも役立ちます。"
  },
  {
    "index": 164,
    "text": "味方をつくります。",
    "raw_text": "味方をつくります。",
    "b_text": "味方をつくります。"
  },
  {
    "index": 165,
    "text": "同じように合わせすぎに疲れたことのある人、静けさを大事にする人。",
    "raw_text": "同じように合わせすぎに疲れたことのある人、静けさを大事にする人。",
    "b_text": "同じように合わせすぎに疲れたことのある人、静けさを大事にする人。"
  },
  {
    "index": 166,
    "text": "味方と短く感想を交換すると、「自分だけではない」と分かります。",
    "raw_text": "味方と短く感想を交換すると、「自分だけではない」と分かります。",
    "b_text": "味方と短く感想を交換すると、「自分だけではない」と分かります。"
  },
  {
    "index": 167,
    "text": "「自分だけではない」は、合わせすぎの孤独を溶かします。",
    "raw_text": "「自分だけではない」は、合わせすぎの孤独を溶かします。",
    "b_text": "「自分だけではない」は、合わせすぎの孤独を溶かします。"
  },
  {
    "index": 168,
    "text": "孤独が溶けると、輪郭は太くなります。",
    "raw_text": "孤独が溶けると、輪郭は太くなります。",
    "b_text": "孤独が溶けると、輪郭は太くなります。"
  },
  {
    "index": 169,
    "text": "他人の期待に合わせて動くのではなく、自分の価値に合わせて動く日を一日だけ設定します。",
    "raw_text": "他人の期待に合わせて動くのではなく、自分の価値に合わせて動く日を一日だけ設定します。",
    "b_text": "他人の期待に合わせて動くのではなく、自分の価値に合わせて動く日を一日だけ設定します。"
  },
  {
    "index": 170,
    "text": "「今日は好奇心に従う」「今日は誠実さを守る」。",
    "raw_text": "「今日は好奇心に従う」「今日は誠実さを守る」。",
    "b_text": "「今日は好奇心に従う」「今日は誠実さを守る」。"
  },
  {
    "index": 171,
    "text": "価値に従って動いた感覚が残れば、次も価値に沿って選びやすくなります。",
    "raw_text": "価値に従って動いた感覚が残れば、次も価値に沿って選びやすくなります。",
    "b_text": "価値に従って動いた感覚が残れば、次も価値に沿って選びやすくなります。"
  },
  {
    "index": 172,
    "text": "価値が軸になれば、期待は軸の周りを回るだけです。",
    "raw_text": "価値が軸になれば、期待は軸の周りを回るだけです。",
    "b_text": "価値が軸になれば、期待は軸の周りを回るだけです。"
  },
  {
    "index": 173,
    "text": "もし合わせすぎが癖になっているなら、開始と終了の合図を作ります。",
    "raw_text": "もし合わせすぎが癖になっているなら、開始と終了の合図を作ります。",
    "b_text": "もし合わせすぎが癖になっているなら、開始と終了の合図を作ります。"
  },
  {
    "index": 174,
    "text": "仕事の始まりに深呼吸三回、終わりに机を拭く。",
    "raw_text": "仕事の始まりに深呼吸三回、終わりに机を拭く。",
    "b_text": "仕事の始まりに深呼吸三回、終わりに机を拭く。"
  },
  {
    "index": 175,
    "text": "合図はリズムです。",
    "raw_text": "合図はリズムです。",
    "b_text": "合図はリズムです。"
  },
  {
    "index": 176,
    "text": "リズムがあると、演じる時間と戻る時間の境界がはっきりします。",
    "raw_text": "リズムがあると、演じる時間と戻る時間の境界がはっきりします。",
    "b_text": "リズムがあると、演じる時間と戻る時間の境界がはっきりします。"
  },
  {
    "index": 177,
    "text": "境界がはっきりすれば、内側の声は迷子になりません。",
    "raw_text": "境界がはっきりすれば、内側の声は迷子になりません。",
    "b_text": "境界がはっきりすれば、内側の声は迷子になりません。"
  },
  {
    "index": 178,
    "text": "最後に、今日一つだけ自分の選択を優先してください。",
    "raw_text": "最後に、今日一つだけ自分の選択を優先してください。",
    "b_text": "最後に、今日一つだけ自分の選択を優先してください。"
  },
  {
    "index": 179,
    "text": "昼ご飯の店を決めるでも、会話で一文だけ本音を添えるでも、帰り道の曲を自分で選ぶでもいい。",
    "raw_text": "昼ご飯の店を決めるでも、会話で一文だけ本音を添えるでも、帰り道の曲を自分で選ぶでもいい。",
    "b_text": "昼ご飯の店を決めるでも、会話で一文だけ本音を添えるでも、帰り道の曲を自分で選ぶでもいい。"
  },
  {
    "index": 180,
    "text": "小さな選択は小さな輪郭です。",
    "raw_text": "小さな選択は小さな輪郭です。",
    "b_text": "小さな選択は小さな輪郭です。"
  },
  {
    "index": 181,
    "text": "小さな輪郭が積み重なると、場に合わせるか合わせないかを自分で決められるようになります。",
    "raw_text": "小さな輪郭が積み重なると、場に合わせるか合わせないかを自分で決められるようになります。",
    "b_text": "小さな輪郭が積み重なると、場に合わせるか合わせないかを自分で決められるようになります。"
  },
  {
    "index": 182,
    "text": "合わせることは技、軸はあなたのもの。",
    "raw_text": "合わせることは技、軸はあなたのもの。",
    "b_text": "合わせることは技、軸はあなたのもの。"
  },
  {
    "index": 183,
    "text": "技と軸を両方持って、静かに、しなやかに場に立ってください。",
    "raw_text": "技と軸を両方持って、静かに、しなやかに場に立ってください。",
    "b_text": "技と軸を両方持って、静かに、しなやかに場に立ってください。"
  },
  {
    "index": 184,
    "text": "ここからさらに輪郭を厚くする手を加えます。",
    "raw_text": "ここからさらに輪郭を厚くする手を加えます。",
    "b_text": "ここからさらに輪郭を厚くする手を加えます。"
  },
  {
    "index": 185,
    "text": "役割ごとにカードを持ちます。",
    "raw_text": "役割ごとにカードを持ちます。",
    "b_text": "役割ごとにカードを持ちます。"
  },
  {
    "index": 186,
    "text": "仕事の場、友人の場、家族の場。",
    "raw_text": "仕事の場、友人の場、家族の場。",
    "b_text": "仕事の場、友人の場、家族の場。"
  },
  {
    "index": 187,
    "text": "それぞれに「この場で大事にする価値」を一行だけ書いたカードをポケットに入れる。",
    "raw_text": "それぞれに「この場で大事にする価値」を一行だけ書いたカードをポケットに入れる。",
    "b_text": "それぞれに「この場で大事にする価値」を一行だけ書いたカードをポケットに入れる。"
  },
  {
    "index": 188,
    "text": "仕事では誠実、友人の前では遊び心、家族とは穏やかさ。",
    "raw_text": "仕事では誠実、友人の前では遊び心、家族とは穏やかさ。",
    "b_text": "仕事では誠実、友人の前では遊び心、家族とは穏やかさ。"
  },
  {
    "index": 189,
    "text": "場が変わってもカードがあれば、演じるだけでなく価値を持ち運べます。",
    "raw_text": "場が変わってもカードがあれば、演じるだけでなく価値を持ち運べます。",
    "b_text": "場が変わってもカードがあれば、演じるだけでなく価値を持ち運べます。"
  },
  {
    "index": 190,
    "text": "持ち運べる価値があれば、合わせ方も自分で選べます。",
    "raw_text": "持ち運べる価値があれば、合わせ方も自分で選べます。",
    "b_text": "持ち運べる価値があれば、合わせ方も自分で選べます。"
  },
  {
    "index": 191,
    "text": "合わせすぎる人は、共感と融合を混同しがちです。",
    "raw_text": "合わせすぎる人は、共感と融合を混同しがちです。",
    "b_text": "合わせすぎる人は、共感と融合を混同しがちです。"
  },
  {
    "index": 192,
    "text": "共感は相手の気持ちを理解すること、融合は相手と自分の境界がなくなること。",
    "raw_text": "共感は相手の気持ちを理解すること、融合は相手と自分の境界がなくなること。",
    "b_text": "共感は相手の気持ちを理解すること、融合は相手と自分の境界がなくなること。"
  },
  {
    "index": 193,
    "text": "共感に留めるために、心の中で「私は私、あなたはあなた」と一度区切る。",
    "raw_text": "共感に留めるために、心の中で「私は私、あなたはあなた」と一度区切る。",
    "b_text": "共感に留めるために、心の中で「私は私、あなたはあなた」と一度区切る。"
  },
  {
    "index": 194,
    "text": "区切った上で寄り添う。",
    "raw_text": "区切った上で寄り添う。",
    "b_text": "区切った上で寄り添う。"
  },
  {
    "index": 195,
    "text": "寄り添う距離感を意識すると、境界線が残ります。",
    "raw_text": "寄り添う距離感を意識すると、境界線が残ります。",
    "b_text": "寄り添う距離感を意識すると、境界線が残ります。"
  },
  {
    "index": 196,
    "text": "境界線が残れば、透明になりません。",
    "raw_text": "境界線が残れば、透明になりません。",
    "b_text": "境界線が残れば、透明になりません。"
  },
  {
    "index": 197,
    "text": "身体の感覚を記録する地図を作ります。",
    "raw_text": "身体の感覚を記録する地図を作ります。",
    "b_text": "身体の感覚を記録する地図を作ります。"
  },
  {
    "index": 198,
    "text": "どの場で胃が重くなり、どの場で肩がゆるむか。",
    "raw_text": "どの場で胃が重くなり、どの場で肩がゆるむか。",
    "b_text": "どの場で胃が重くなり、どの場で肩がゆるむか。"
  },
  {
    "index": 199,
    "text": "誰といるときに呼吸が浅くなり、誰といるときに深くなるか。",
    "raw_text": "誰といるときに呼吸が浅くなり、誰といるときに深くなるか。",
    "b_text": "誰といるときに呼吸が浅くなり、誰といるときに深くなるか。"
  },
  {
    "index": 200,
    "text": "地図は、どこで合わせすぎているかのヒントです。",
    "raw_text": "地図は、どこで合わせすぎているかのヒントです。",
    "b_text": "地図は、どこで合わせすぎているかのヒントです。"
  },
  {
    "index": 201,
    "text": "地図があれば、居場所を選べます。",
    "raw_text": "地図があれば、居場所を選べます。",
    "b_text": "地図があれば、居場所を選べます。"
  },
  {
    "index": 202,
    "text": "選べること自体が、自分を濃くする力です。",
    "raw_text": "選べること自体が、自分を濃くする力です。",
    "b_text": "選べること自体が、自分を濃くする力です。"
  },
  {
    "index": 203,
    "text": "SNSも、見えない期待を運びます。",
    "raw_text": "SNSも、見えない期待を運びます。",
    "b_text": "エスエヌエスも、見えない期待を運びます。"
  },
  {
    "index": 204,
    "text": "スクロールするだけでこうあるべきが流れ込みます。",
    "raw_text": "スクロールするだけでこうあるべきが流れ込みます。",
    "b_text": "スクロールするだけでこうあるべきが流れ込みます。"
  },
  {
    "index": 205,
    "text": "流れを浴び続けると、内側の声がかき消されます。",
    "raw_text": "流れを浴び続けると、内側の声がかき消されます。",
    "b_text": "流れを浴び続けると、内側の声がかき消されます。"
  },
  {
    "index": 206,
    "text": "見る時間を決め、終わりの時間をアラームで区切る。",
    "raw_text": "見る時間を決め、終わりの時間をアラームで区切る。",
    "b_text": "見る時間を決め、終わりの時間をアラームで区切る。"
  },
  {
    "index": 207,
    "text": "区切った後は、静かな音楽を一曲聴く。",
    "raw_text": "区切った後は、静かな音楽を一曲聴く。",
    "b_text": "区切った後は、静かな音楽を一曲聴く。"
  },
  {
    "index": 208,
    "text": "静けさで内側の声を戻す習慣を入れると、見えない期待の音量を下げられます。",
    "raw_text": "静けさで内側の声を戻す習慣を入れると、見えない期待の音量を下げられます。",
    "b_text": "静けさで内側の声を戻す習慣を入れると、見えない期待の音量を下げられます。"
  },
  {
    "index": 209,
    "text": "やさしい嘘も、合わせすぎの原因になります。",
    "raw_text": "やさしい嘘も、合わせすぎの原因になります。",
    "b_text": "やさしい嘘も、合わせすぎの原因になります。"
  },
  {
    "index": 210,
    "text": "場を乱さないために、過剰な同意や笑顔を使うと、内側が疲れます。",
    "raw_text": "場を乱さないために、過剰な同意や笑顔を使うと、内側が疲れます。",
    "b_text": "場を乱さないために、過剰な同意や笑顔を使うと、内側が疲れます。"
  },
  {
    "index": 211,
    "text": "乱さずに正直でいる方法を探します。",
    "raw_text": "乱さずに正直でいる方法を探します。",
    "b_text": "乱さずに正直でいる方法を探します。"
  },
  {
    "index": 212,
    "text": "「少し違う視点を持っています」「こう感じました」と短く伝える。",
    "raw_text": "「少し違う視点を持っています」「こう感じました」と短く伝える。",
    "b_text": "「少し違う視点を持っています」「こう感じました」と短く伝える。"
  },
  {
    "index": 213,
    "text": "短い正直さは、場を壊さずに自分を保つ技です。",
    "raw_text": "短い正直さは、場を壊さずに自分を保つ技です。",
    "b_text": "短い正直さは、場を壊さずに自分を保つ技です。"
  },
  {
    "index": 214,
    "text": "合わせるか合わせないかの二択ではなく、「どれくらい合わせるか」という濃度で考えます。",
    "raw_text": "合わせるか合わせないかの二択ではなく、「どれくらい合わせるか」という濃度で考えます。",
    "b_text": "合わせるか合わせないかの二択ではなく、「どれくらい合わせるか」という濃度で考えます。"
  },
  {
    "index": 215,
    "text": "濃度を決めるのは自分です。",
    "raw_text": "濃度を決めるのは自分です。",
    "b_text": "濃度を決めるのは自分です。"
  },
  {
    "index": 216,
    "text": "今日は三割合わせ、七割は自分のまま。",
    "raw_text": "今日は三割合わせ、七割は自分のまま。",
    "b_text": "今日は三割合わせ、七割は自分のまま。"
  },
  {
    "index": 217,
    "text": "明日は五分五分。",
    "raw_text": "明日は五分五分。",
    "b_text": "明日は五分五分。"
  },
  {
    "index": 218,
    "text": "濃度を決めると、ただ流される感覚が減ります。",
    "raw_text": "濃度を決めると、ただ流される感覚が減ります。",
    "b_text": "濃度を決めると、ただ流される感覚が減ります。"
  },
  {
    "index": 219,
    "text": "減れば、疲れも減ります。",
    "raw_text": "減れば、疲れも減ります。",
    "b_text": "減れば、疲れも減ります。"
  },
  {
    "index": 220,
    "text": "朝の装いに自分の好きな色を一つ必ず入れる。",
    "raw_text": "朝の装いに自分の好きな色を一つ必ず入れる。",
    "b_text": "朝の装いに自分の好きな色を一つ必ず入れる。"
  },
  {
    "index": 221,
    "text": "靴下でも小物でもいい。",
    "raw_text": "靴下でも小物でもいい。",
    "b_text": "靴下でも小物でもいい。"
  },
  {
    "index": 222,
    "text": "色は視覚的な軸になります。",
    "raw_text": "色は視覚的な軸になります。",
    "b_text": "色は視覚的な軸になります。"
  },
  {
    "index": 223,
    "text": "目に入るたびに、「ここに自分がいる」と思い出せます。",
    "raw_text": "目に入るたびに、「ここに自分がいる」と思い出せます。",
    "b_text": "目に入るたびに、「ここに自分がいる」と思い出せます。"
  },
  {
    "index": 224,
    "text": "思い出す回数が増えるほど、場で透明になりにくくなります。",
    "raw_text": "思い出す回数が増えるほど、場で透明になりにくくなります。",
    "b_text": "思い出す回数が増えるほど、場で透明になりにくくなります。"
  },
  {
    "index": 225,
    "text": "他人の評価を整理する時間を週に一度持ちます。",
    "raw_text": "他人の評価を整理する時間を週に一度持ちます。",
    "b_text": "他人の評価を整理する時間を週に一度持ちます。"
  },
  {
    "index": 226,
    "text": "褒められた言葉、指摘された言葉を書き出し、自分がどれほど同意するかを隣に書く。",
    "raw_text": "褒められた言葉、指摘された言葉を書き出し、自分がどれほど同意するかを隣に書く。",
    "b_text": "褒められた言葉、指摘された言葉を書き出し、自分がどれほど同意するかを隣に書く。"
  },
  {
    "index": 227,
    "text": "同意しないものは封筒に入れてしまう。",
    "raw_text": "同意しないものは封筒に入れてしまう。",
    "b_text": "同意しないものは封筒に入れてしまう。"
  },
  {
    "index": 228,
    "text": "同意するものだけ机に残す。",
    "raw_text": "同意するものだけ机に残す。",
    "b_text": "同意するものだけ机に残す。"
  },
  {
    "index": 229,
    "text": "評価の取捨選択をすると、外の声の支配力が弱まります。",
    "raw_text": "評価の取捨選択をすると、外の声の支配力が弱まります。",
    "b_text": "評価の取捨選択をすると、外の声の支配力が弱まります。"
  },
  {
    "index": 230,
    "text": "弱まれば、合わせ方を自分で決められます。",
    "raw_text": "弱まれば、合わせ方を自分で決められます。",
    "b_text": "弱まれば、合わせ方を自分で決められます。"
  },
  {
    "index": 231,
    "text": "沈黙を使う練習も有効です。",
    "raw_text": "沈黙を使う練習も有効です。",
    "b_text": "沈黙を使う練習も有効です。"
  },
  {
    "index": 232,
    "text": "言葉で埋める前に、一拍置く。",
    "raw_text": "言葉で埋める前に、一拍置く。",
    "b_text": "言葉で埋める前に、一拍置く。"
  },
  {
    "index": 233,
    "text": "置いた一拍の間に、自分の声を聞く。",
    "raw_text": "置いた一拍の間に、自分の声を聞く。",
    "b_text": "置いた一拍の間に、自分の声を聞く。"
  },
  {
    "index": 234,
    "text": "自分の声が聞こえたら、それを短く出す。",
    "raw_text": "自分の声が聞こえたら、それを短く出す。",
    "b_text": "自分の声が聞こえたら、それを短く出す。"
  },
  {
    "index": 235,
    "text": "沈黙は怖いものではなく、声を拾うための間です。",
    "raw_text": "沈黙は怖いものではなく、声を拾うための間です。",
    "b_text": "沈黙は怖いものではなく、声を拾うための間です。"
  },
  {
    "index": 236,
    "text": "間を持てれば、流されることが減ります。",
    "raw_text": "間を持てれば、流されることが減ります。",
    "b_text": "間を持てれば、流されることが減ります。"
  },
  {
    "index": 237,
    "text": "未来の自分への手紙も書いてみてください。",
    "raw_text": "未来の自分への手紙も書いてみてください。",
    "b_text": "未来の自分への手紙も書いてみてください。"
  },
  {
    "index": 238,
    "text": "半年後の自分に向けて、「いま合わせすぎて苦しい」こうしたいという本音を三行書く。",
    "raw_text": "半年後の自分に向けて、「いま合わせすぎて苦しい」こうしたいという本音を三行書く。",
    "b_text": "半年後の自分に向けて、「いま合わせすぎて苦しい」こうしたいという本音を三行書く。"
  },
  {
    "index": 239,
    "text": "未来の自分は、その手紙を読むとき、過去の自分が本音を出した事実に勇気づけられます。",
    "raw_text": "未来の自分は、その手紙を読むとき、過去の自分が本音を出した事実に勇気づけられます。",
    "b_text": "未来の自分は、その手紙を読むとき、過去の自分が本音を出した事実に勇気づけられます。"
  },
  {
    "index": 240,
    "text": "時間を越えた本音の交換は、輪郭を保つ力になります。",
    "raw_text": "時間を越えた本音の交換は、輪郭を保つ力になります。",
    "b_text": "時間を越えた本音の交換は、輪郭を保つ力になります。"
  },
  {
    "index": 241,
    "text": "一日の終わりに今日の境界点を一つ振り返る。",
    "raw_text": "一日の終わりに今日の境界点を一つ振り返る。",
    "b_text": "一日の終わりに今日の境界点を一つ振り返る。"
  },
  {
    "index": 242,
    "text": "どこでノーを言えたか、どこで自分の意見を出せたか。",
    "raw_text": "どこでノーを言えたか、どこで自分の意見を出せたか。",
    "b_text": "どこでノーを言えたか、どこで自分の意見を出せたか。"
  },
  {
    "index": 243,
    "text": "境界を引けた瞬間を覚えておくと、次も引きやすくなります。",
    "raw_text": "境界を引けた瞬間を覚えておくと、次も引きやすくなります。",
    "b_text": "境界を引けた瞬間を覚えておくと、次も引きやすくなります。"
  },
  {
    "index": 244,
    "text": "境界を引けた回数が増えるほど、合わせすぎは減ります。",
    "raw_text": "境界を引けた回数が増えるほど、合わせすぎは減ります。",
    "b_text": "境界を引けた回数が増えるほど、合わせすぎは減ります。"
  },
  {
    "index": 245,
    "text": "休日に「一人で行く場所」を増やします。",
    "raw_text": "休日に「一人で行く場所」を増やします。",
    "b_text": "休日に「一人で行く場所」を増やします。"
  },
  {
    "index": 246,
    "text": "映画館、喫茶店、美術館。",
    "raw_text": "映画館、喫茶店、美術館。",
    "b_text": "映画館、喫茶店、美術館。"
  },
  {
    "index": 247,
    "text": "誰にも合わせず、自分のペースで過ごす場所を持つと、日常で合わせるときの回復力が上がります。",
    "raw_text": "誰にも合わせず、自分のペースで過ごす場所を持つと、日常で合わせるときの回復力が上がります。",
    "b_text": "誰にも合わせず、自分のペースで過ごす場所を持つと、日常で合わせるときの回復力が上がります。"
  },
  {
    "index": 248,
    "text": "回復力が上がれば、合わせる・合わせないを自分で選べます。",
    "raw_text": "回復力が上がれば、合わせる・合わせないを自分で選べます。",
    "b_text": "回復力が上がれば、合わせる合わせないを自分で選べます。"
  },
  {
    "index": 249,
    "text": "合わせすぎる背景には、過去の経験も影響しています。",
    "raw_text": "合わせすぎる背景には、過去の経験も影響しています。",
    "b_text": "合わせすぎる背景には、過去の経験も影響しています。"
  },
  {
    "index": 250,
    "text": "子どもの頃に空気を読めと言われ続けたかもしれない。",
    "raw_text": "子どもの頃に空気を読めと言われ続けたかもしれない。",
    "b_text": "子どもの頃に空気を読めと言われ続けたかもしれない。"
  },
  {
    "index": 251,
    "text": "過去の声を現在の場に持ち込まないために、「あれは過去の場のルールだ」と心で区切る。",
    "raw_text": "過去の声を現在の場に持ち込まないために、「あれは過去の場のルールだ」と心で区切る。",
    "b_text": "過去の声を現在の場に持ち込まないために、「あれは過去の場のルールだ」と心で区切る。"
  },
  {
    "index": 252,
    "text": "区切ると、今の場に合った選択ができます。",
    "raw_text": "区切ると、今の場に合った選択ができます。",
    "b_text": "区切ると、今の場に合った選択ができます。"
  },
  {
    "index": 253,
    "text": "過去を尊重しながら、今の軸を立てることができます。",
    "raw_text": "過去を尊重しながら、今の軸を立てることができます。",
    "b_text": "過去を尊重しながら、今の軸を立てることができます。"
  },
  {
    "index": 254,
    "text": "もしどうしても本音が出せない場なら、場の時間を短くする工夫をします。",
    "raw_text": "もしどうしても本音が出せない場なら、場の時間を短くする工夫をします。",
    "b_text": "もしどうしても本音が出せない場なら、場の時間を短くする工夫をします。"
  },
  {
    "index": 255,
    "text": "開始と終了を決めて参加する。",
    "raw_text": "開始と終了を決めて参加する。",
    "b_text": "開始と終了を決めて参加する。"
  },
  {
    "index": 256,
    "text": "途中で外に出て呼吸を整える。",
    "raw_text": "途中で外に出て呼吸を整える。",
    "b_text": "途中で外に出て呼吸を整える。"
  },
  {
    "index": 257,
    "text": "時間の枠を自分で握れば、合わせることが完全に受け身ではなくなります。",
    "raw_text": "時間の枠を自分で握れば、合わせることが完全に受け身ではなくなります。",
    "b_text": "時間の枠を自分で握れば、合わせることが完全に受け身ではなくなります。"
  },
  {
    "index": 258,
    "text": "受け身でなければ、消耗も減ります。",
    "raw_text": "受け身でなければ、消耗も減ります。",
    "b_text": "受け身でなければ、消耗も減ります。"
  },
  {
    "index": 259,
    "text": "手を動かすリチュアルを入れます。",
    "raw_text": "手を動かすリチュアルを入れます。",
    "b_text": "手を動かすリチュアルを入れます。"
  },
  {
    "index": 260,
    "text": "会議の前にペンを回す、ノートに一行書く。",
    "raw_text": "会議の前にペンを回す、ノートに一行書く。",
    "b_text": "会議の前にペンを回す、ノートに一行書く。"
  },
  {
    "index": 261,
    "text": "手の動きは、頭の緊張をほぐします。",
    "raw_text": "手の動きは、頭の緊張をほぐします。",
    "b_text": "手の動きは、頭の緊張をほぐします。"
  },
  {
    "index": 262,
    "text": "ほぐれた頭は、自分の言葉を拾いやすくなります。",
    "raw_text": "ほぐれた頭は、自分の言葉を拾いやすくなります。",
    "b_text": "ほぐれた頭は、自分の言葉を拾いやすくなります。"
  },
  {
    "index": 263,
    "text": "拾えれば、出せます。",
    "raw_text": "拾えれば、出せます。",
    "b_text": "拾えれば、出せます。"
  },
  {
    "index": 264,
    "text": "合わせすぎで失ったと感じるものを取り戻す時間も作ります。",
    "raw_text": "合わせすぎで失ったと感じるものを取り戻す時間も作ります。",
    "b_text": "合わせすぎで失ったと感じるものを取り戻す時間も作ります。"
  },
  {
    "index": 265,
    "text": "昔好きだった音楽を聴く、昔夢中になった本を読み返す。",
    "raw_text": "昔好きだった音楽を聴く、昔夢中になった本を読み返す。",
    "b_text": "昔好きだった音楽を聴く、昔夢中になった本を読み返す。"
  },
  {
    "index": 266,
    "text": "過去の好きを体に思い出させると、今の好みも鮮やかになります。",
    "raw_text": "過去の好きを体に思い出させると、今の好みも鮮やかになります。",
    "b_text": "過去の好きを体に思い出させると、今の好みも鮮やかになります。"
  },
  {
    "index": 267,
    "text": "鮮やかな好みは、合わせるだけではない自分を教えてくれます。",
    "raw_text": "鮮やかな好みは、合わせるだけではない自分を教えてくれます。",
    "b_text": "鮮やかな好みは、合わせるだけではない自分を教えてくれます。"
  },
  {
    "index": 268,
    "text": "自分の声を録音して聞き返すことも役立ちます。",
    "raw_text": "自分の声を録音して聞き返すことも役立ちます。",
    "b_text": "自分の声を録音して聞き返すことも役立ちます。"
  },
  {
    "index": 269,
    "text": "本音を言ったときの声と、合わせたときの声は違います。",
    "raw_text": "本音を言ったときの声と、合わせたときの声は違います。",
    "b_text": "本音を言ったときの声と、合わせたときの声は違います。"
  },
  {
    "index": 270,
    "text": "違いを知れば、場で自分の声がどちらに近いかを感じ取れます。",
    "raw_text": "違いを知れば、場で自分の声がどちらに近いかを感じ取れます。",
    "b_text": "違いを知れば、場で自分の声がどちらに近いかを感じ取れます。"
  },
  {
    "index": 271,
    "text": "感じ取れれば、合わせすぎに気づき、戻せます。",
    "raw_text": "感じ取れれば、合わせすぎに気づき、戻せます。",
    "b_text": "感じ取れれば、合わせすぎに気づき、戻せます。"
  },
  {
    "index": 272,
    "text": "哲学者ブーバーは、他者をそれではなくあなたとして向き合うことで真の関係が生まれると述べました。",
    "raw_text": "哲学者ブーバーは、他者をそれではなくあなたとして向き合うことで真の関係が生まれると述べました。",
    "b_text": "哲学者ブーバーは、他者をそれではなくあなたとして向き合うことで真の関係が生まれると述べました。"
  },
  {
    "index": 273,
    "text": "あなた自身もそれとして扱わず、あなたとして扱う。",
    "raw_text": "あなた自身もそれとして扱わず、あなたとして扱う。",
    "b_text": "あなた自身もそれとして扱わず、あなたとして扱う。"
  },
  {
    "index": 274,
    "text": "自分に対しても敬意を払うと、合わせるだけの関係から一歩離れ、相互の関係を築けます。",
    "raw_text": "自分に対しても敬意を払うと、合わせるだけの関係から一歩離れ、相互の関係を築けます。",
    "b_text": "自分に対しても敬意を払うと、合わせるだけの関係から一歩離れ、相互の関係を築けます。"
  },
  {
    "index": 275,
    "text": "相互の関係では、透明にはなりません。",
    "raw_text": "相互の関係では、透明にはなりません。",
    "b_text": "相互の関係では、透明にはなりません。"
  },
  {
    "index": 276,
    "text": "周囲の期待が重く感じるときは、「期待を持つ権利は相手にあるが、応えるかは自分が決める」と心でつぶやく。",
    "raw_text": "周囲の期待が重く感じるときは、「期待を持つ権利は相手にあるが、応えるかは自分が決める」と心でつぶやく。",
    "b_text": "周囲の期待が重く感じるときは、「期待を持つ権利は相手にあるが、応えるかは自分が決める」と心でつぶやく。"
  },
  {
    "index": 277,
    "text": "権利と選択を分けると、義務感が和らぎます。",
    "raw_text": "権利と選択を分けると、義務感が和らぎます。",
    "b_text": "権利と選択を分けると、義務感が和らぎます。"
  },
  {
    "index": 278,
    "text": "和らげば、無理な同調が減ります。",
    "raw_text": "和らげば、無理な同調が減ります。",
    "b_text": "和らげば、無理な同調が減ります。"
  },
  {
    "index": 279,
    "text": "最後に、明日のための合図を用意します。",
    "raw_text": "最後に、明日のための合図を用意します。",
    "b_text": "最後に、明日のための合図を用意します。"
  },
  {
    "index": 280,
    "text": "ポケットに小さな紙を入れ、軸一言本音ノー休むと書く。",
    "raw_text": "ポケットに小さな紙を入れ、軸一言本音ノー休むと書く。",
    "b_text": "ポケットに小さな紙を入れ、軸一言本音ノー休むと書く。"
  },
  {
    "index": 281,
    "text": "触れるたびに思い出せるようにする。",
    "raw_text": "触れるたびに思い出せるようにする。",
    "b_text": "触れるたびに思い出せるようにする。"
  },
  {
    "index": 282,
    "text": "思い出すたびに、輪郭が濃くなります。",
    "raw_text": "思い出すたびに、輪郭が濃くなります。",
    "b_text": "思い出すたびに、輪郭が濃くなります。"
  },
  {
    "index": 283,
    "text": "濃くなった輪郭で、必要なだけ合わせ、必要なだけ合わせず、あなたの形を保ってください。",
    "raw_text": "濃くなった輪郭で、必要なだけ合わせ、必要なだけ合わせず、あなたの形を保ってください。",
    "b_text": "濃くなった輪郭で、必要なだけ合わせ、必要なだけ合わせず、あなたの形を保ってください。"
  },
  {
    "index": 284,
    "text": "さらに、仮のラベルを使う方法も試してください。",
    "raw_text": "さらに、仮のラベルを使う方法も試してください。",
    "b_text": "さらに、仮のラベルを使う方法も試してください。"
  },
  {
    "index": 285,
    "text": "いまの自分に探求中回復中調整中と小さく名前を付ける。",
    "raw_text": "いまの自分に探求中回復中調整中と小さく名前を付ける。",
    "b_text": "いまの自分に探求中回復中調整中と小さく名前を付ける。"
  },
  {
    "index": 286,
    "text": "ラベルが仮だと分かっていれば、他人の視線に合わせて貼られる固定のラベルから距離を取れます。",
    "raw_text": "ラベルが仮だと分かっていれば、他人の視線に合わせて貼られる固定のラベルから距離を取れます。",
    "b_text": "ラベルが仮だと分かっていれば、他人の視線に合わせて貼られる固定のラベルから距離を取れます。"
  },
  {
    "index": 287,
    "text": "仮のラベルは、自分で貼り、自分で剥がせます。",
    "raw_text": "仮のラベルは、自分で貼り、自分で剥がせます。",
    "b_text": "仮のラベルは、自分で貼り、自分で剥がせます。"
  },
  {
    "index": 288,
    "text": "剥がせるものを持つと、貼られるものに支配されません。",
    "raw_text": "剥がせるものを持つと、貼られるものに支配されません。",
    "b_text": "剥がせるものを持つと、貼られるものに支配されません。"
  },
  {
    "index": 289,
    "text": "通勤や移動時間を戻る時間にします。",
    "raw_text": "通勤や移動時間を戻る時間にします。",
    "b_text": "通勤や移動時間を戻る時間にします。"
  },
  {
    "index": 290,
    "text": "電車の中で深呼吸を三回し、今日守りたい軸を心で唱える。",
    "raw_text": "電車の中で深呼吸を三回し、今日守りたい軸を心で唱える。",
    "b_text": "電車の中で深呼吸を三回し、今日守りたい軸を心で唱える。"
  },
  {
    "index": 291,
    "text": "駅に着くまでの数分を、外から内へ戻す儀式にする。",
    "raw_text": "駅に着くまでの数分を、外から内へ戻す儀式にする。",
    "b_text": "駅に着くまでの数分を、外から内へ戻す儀式にする。"
  },
  {
    "index": 292,
    "text": "外に出る前に内側に戻る癖がつけば、透明になる前に輪郭を濃くできます。",
    "raw_text": "外に出る前に内側に戻る癖がつけば、透明になる前に輪郭を濃くできます。",
    "b_text": "外に出る前に内側に戻る癖がつけば、透明になる前に輪郭を濃くできます。"
  },
  {
    "index": 293,
    "text": "家族や長く付き合う人との関係では、過去の役割が惰性で続きます。",
    "raw_text": "家族や長く付き合う人との関係では、過去の役割が惰性で続きます。",
    "b_text": "家族や長く付き合う人との関係では、過去の役割が惰性で続きます。"
  },
  {
    "index": 294,
    "text": "聞き役明るくする役。",
    "raw_text": "聞き役明るくする役。",
    "b_text": "聞き役明るくする役。"
  },
  {
    "index": 295,
    "text": "惰性の役割を一度手放し、「今日は別の役割に変えたい」と短く伝える。",
    "raw_text": "惰性の役割を一度手放し、「今日は別の役割に変えたい」と短く伝える。",
    "b_text": "惰性の役割を一度手放し、「今日は別の役割に変えたい」と短く伝える。"
  },
  {
    "index": 296,
    "text": "長い関係ほど、一度言えば意外と理解されます。",
    "raw_text": "長い関係ほど、一度言えば意外と理解されます。",
    "b_text": "長い関係ほど、一度言えば意外と理解されます。"
  },
  {
    "index": 297,
    "text": "言えた事実が、次の役割変更の道を開きます。",
    "raw_text": "言えた事実が、次の役割変更の道を開きます。",
    "b_text": "言えた事実が、次の役割変更の道を開きます。"
  },
  {
    "index": 298,
    "text": "小さな選択を積むために、「三回の自分決定」を日課にします。",
    "raw_text": "小さな選択を積むために、「三回の自分決定」を日課にします。",
    "b_text": "小さな選択を積むために、「三回の自分決定」を日課にします。"
  },
  {
    "index": 299,
    "text": "朝に一つ、昼に一つ、夜に一つ。",
    "raw_text": "朝に一つ、昼に一つ、夜に一つ。",
    "b_text": "朝に一つ、昼に一つ、夜に一つ。"
  },
  {
    "index": 300,
    "text": "内容は何でも構いません。",
    "raw_text": "内容は何でも構いません。",
    "b_text": "内容は何でも構いません。"
  },
  {
    "index": 301,
    "text": "三回の決定は、合わせる癖をほぐすストレッチです。",
    "raw_text": "三回の決定は、合わせる癖をほぐすストレッチです。",
    "b_text": "三回の決定は、合わせる癖をほぐすストレッチです。"
  },
  {
    "index": 302,
    "text": "ストレッチが習慣になると、急に走らされても筋を痛めません。",
    "raw_text": "ストレッチが習慣になると、急に走らされても筋を痛めません。",
    "b_text": "ストレッチが習慣になると、急に走らされても筋を痛めません。"
  },
  {
    "index": 303,
    "text": "場から帰った後のデトックスを忘れないでください。",
    "raw_text": "場から帰った後のデトックスを忘れないでください。",
    "b_text": "場から帰った後のデトックスを忘れないでください。"
  },
  {
    "index": 304,
    "text": "温かいシャワーを浴びる、手を洗いながら今日の本音を心で唱える、短い散歩で景色を眺める。",
    "raw_text": "温かいシャワーを浴びる、手を洗いながら今日の本音を心で唱える、短い散歩で景色を眺める。",
    "b_text": "温かいシャワーを浴びる、手を洗いながら今日の本音を心で唱える、短い散歩で景色を眺める。"
  },
  {
    "index": 305,
    "text": "体を通して場を洗い流すと、他人の期待が体に残りにくくなります。",
    "raw_text": "体を通して場を洗い流すと、他人の期待が体に残りにくくなります。",
    "b_text": "体を通して場を洗い流すと、他人の期待が体に残りにくくなります。"
  },
  {
    "index": 306,
    "text": "残らなければ、透明になる速度が遅くなります。",
    "raw_text": "残らなければ、透明になる速度が遅くなります。",
    "b_text": "残らなければ、透明になる速度が遅くなります。"
  },
  {
    "index": 307,
    "text": "言葉のリハーサルも、輪郭を守る助けになります。",
    "raw_text": "言葉のリハーサルも、輪郭を守る助けになります。",
    "b_text": "言葉のリハーサルも、輪郭を守る助けになります。"
  },
  {
    "index": 308,
    "text": "言いにくい一言を、声に出して練習する。",
    "raw_text": "言いにくい一言を、声に出して練習する。",
    "b_text": "言いにくい一言を、声に出して練習する。"
  },
  {
    "index": 309,
    "text": "「それは少し違うと思います」「ここはこう感じました」。",
    "raw_text": "「それは少し違うと思います」「ここはこう感じました」。",
    "b_text": "「それは少し違うと思います」「ここはこう感じました」。"
  },
  {
    "index": 310,
    "text": "声帯がその音を覚えれば、本番でも出しやすくなります。",
    "raw_text": "声帯がその音を覚えれば、本番でも出しやすくなります。",
    "b_text": "声帯がその音を覚えれば、本番でも出しやすくなります。"
  },
  {
    "index": 311,
    "text": "出せた一言は、あなたの存在の証になります。",
    "raw_text": "出せた一言は、あなたの存在の証になります。",
    "b_text": "出せた一言は、あなたの存在の証になります。"
  },
  {
    "index": 312,
    "text": "週に一度、自分の価値リストを見直す時間を取ります。",
    "raw_text": "週に一度、自分の価値リストを見直す時間を取ります。",
    "b_text": "週に一度、自分の価値リストを見直す時間を取ります。"
  },
  {
    "index": 313,
    "text": "今週大事にした価値、手放した価値、新しく気づいた価値を一行ずつ書く。",
    "raw_text": "今週大事にした価値、手放した価値、新しく気づいた価値を一行ずつ書く。",
    "b_text": "今週大事にした価値、手放した価値、新しく気づいた価値を一行ずつ書く。"
  },
  {
    "index": 314,
    "text": "価値の更新は、軸のメンテナンスです。",
    "raw_text": "価値の更新は、軸のメンテナンスです。",
    "b_text": "価値の更新は、軸のメンテナンスです。"
  },
  {
    "index": 315,
    "text": "メンテナンスを続けると、合わせすぎて軸が錆びるのを防げます。",
    "raw_text": "メンテナンスを続けると、合わせすぎて軸が錆びるのを防げます。",
    "b_text": "メンテナンスを続けると、合わせすぎて軸が錆びるのを防げます。"
  }
]