[
  {
    "title": "挨拶しない人の心理を理解してご近所トラブルを防ぐ！",
    "url": "https://tantei-ch.jp/article/85/",
    "type": "web",
    "source": "",
    "year": null,
    "note": "web_search から自動抽出",
    "confidence": 0.35
  },
  {
    "title": "マンション挨拶しない住民との付き合い方を解説！心地よい ...",
    "url": "https://shintoakogyo.co.jp/column/posts/160627/",
    "type": "web",
    "source": "",
    "year": null,
    "note": "web_search から自動抽出",
    "confidence": 0.35
  },
  {
    "title": "マンションで挨拶しない人への対処法｜心理を理解して適度な ...",
    "url": "https://shintoa-tosou.jp/blog/apartment-no-greetings/",
    "type": "web",
    "source": "",
    "year": null,
    "note": "web_search から自動抽出",
    "confidence": 0.35
  },
  {
    "title": "同じマンションの住民ですれ違っても挨拶しない人への対処は？",
    "url": "https://kashiwabaralife.com/mansion/article/mansion-aisatsusinai",
    "type": "web",
    "source": "",
    "year": null,
    "note": "web_search から自動抽出",
    "confidence": 0.35
  },
  {
    "title": "挨拶しない人の8つの心理。職場や近所で挨拶を返さないで ...",
    "url": "https://smartlog.jp/147123",
    "type": "web",
    "source": "",
    "year": null,
    "note": "web_search から自動抽出",
    "confidence": 0.35
  },
  {
    "title": "ご近所トラブルに巻き込まれてしまったら？ 解決方法や相談 ...",
    "url": "https://star-forest.biz/blog/2958/",
    "type": "web",
    "source": "",
    "year": null,
    "note": "web_search から自動抽出",
    "confidence": 0.35
  },
  {
    "title": "【対策】“ご近所トラブル”の正しい対処法を教えます！ あなたも ...",
    "url": "https://www.youtube.com/watch?v=sqHZzOfUlsY",
    "type": "web",
    "source": "",
    "year": null,
    "note": "web_search から自動抽出",
    "confidence": 0.35
  },
  {
    "title": "隣人の無愛想なあいさつに嫌気がさします",
    "url": "https://baby-calendar.jp/knowledge/qanda/qa12/2426",
    "type": "web",
    "source": "",
    "year": null,
    "note": "web_search から自動抽出",
    "confidence": 0.35
  }
]
